Workbook
Name Validation_004b65848935b9e1ea176accdf8cebf7d7029af2629c4de75630ab35c71de4d8_product_attr_measurement_unit_seat_height: ReferenceData!$R$2:$R$2
Name Validation_034cc2e2142336c3f3bfac769ac755443f3d6a6890a9f0925b3b209c653301a0_product_attr_measurement_unit_package10_weight: ReferenceData!$AK$2:$AK$3
Name Validation_04e80df5cfe830552f34fddeda4036f17d4d208514dc6275e59139ab0abc6e22_product_attr_sofa_type: ReferenceData!$CE$2:$CE$5
Name Validation_073d2eb236ab7ddf49de1eb396004a4aee02632b32a507d43532114a3edb6b87_product_attr_measurement_unit_width: ReferenceData!$G$2:$G$2
Name Validation_081c0b5c08f42c382055f4180ed8d7d86182f3f83c79c4f165c9ff556d693424_product_attr_production: ReferenceData!$BD$2:$BD$3
Name Validation_0926fa9e6fbc6e480b2fd4d6032b23daf00b3ea8e315d11ec9a9c3f2af385135_product_attr_energy: ReferenceData!$AT$2:$AT$6
Name Validation_0b385e520545f4158f2262322b3f3db446eaff3b703348005ee353787e8601a8_product_attr_power_measurement_unit: ReferenceData!$S$2:$S$3
Name Validation_0db360015f4b36b8605332b1d2529fa7e65674f082f3fed33104b65851651672_product_attr_sofa_corner: ReferenceData!$BJ$2:$BJ$4
Name Validation_107488bc1a3a8fbcb9219fd28c1dba94cd3082529e0255cfbe09298f30cabd29_product_attr_measurement_unit_capacity: ReferenceData!$BW$2:$BW$4
Name Validation_15f0d09dfb358b3f11f461549215d1fea73b3df99b6f6db0afb3eef26342cb09_product_attr_measurement_unit_package5_weight: ReferenceData!$W$2:$W$3
Name Validation_186140fed797e97033dd68e3f039e4784a84bca9b288ef9e21aaffe4b45d2ae1_product_attr_scent: ReferenceData!$BV$2:$BV$3
Name Validation_18feb6fd7dc73dece159e4acb5b60dfcbe61dce7706daaf44521276fe91c5c25_product_attr_hanger_model: ReferenceData!$BQ$2:$BQ$11
Name Validation_19b229d00d671648c3466340d16fc940d4dfac4ad229b903d3a2f14cef42409d_product_attr_measurement_unit_seat_width: ReferenceData!$T$2:$T$2
Name Validation_261ae4c40bdcb680387c70d5475f39b88948224a7a7a44bb067ee63009f2d2ca_product_attr_portion: ReferenceData!$CC$2:$CC$3
Name Validation_27dbd16c9733711f7bdbbc94eb77be1e2dce4ed5e023b96b222e2bdc0ee3d7d3_product_attr_measurement_unit_package4_weight: ReferenceData!$AJ$2:$AJ$3
Name Validation_27f7e932441c45390790396bf14a9ec4b117841f8f75340d464bc667390fa086_product_attr_ideal_for: ReferenceData!$AY$2:$AY$7
Name Validation_2d4ef00828481e6edbc83fcc6197865f37020fef99ff496cce1ddb89a8652c5c_product_attr_table_model: ReferenceData!$CG$2:$CG$2
Name Validation_2e62d2d04449b29259f350761525dbec7e04f759d68a47d3846c73f9696d7e05_product_attr_lamp_model: ReferenceData!$AU$2:$AU$3
Name Validation_2f85fcf368c29e61b3d0429a91df69230f1a128e3d979c9d42c0b75aa0d238a1_product_attr_is_product_recyclable: ReferenceData!$O$2:$O$3
Name Validation_328b9876965cf8161081ebec49b5d122a92884208edd7fb6cdb1dbf3c416e0d2_product_attr_measurement_unit_height: ReferenceData!$E$2:$E$2
Name Validation_34ed3e0c2a6c1ffa9f43b3c8d6cad6ad0a6f276d09f7b0ac0d96276e125043b5_product_attr_mirror_model: ReferenceData!$BB$2:$BB$13
Name Validation_39674193e4e465e1d11369002294284c6f0c538a7e9d53c8b05d0c3fd10540b4_product_attr_characteristic: ReferenceData!$Y$2:$Y$18
Name Validation_3a5607bc90c739387de9081c3fb5eb706e4f334b2887737dd354fee3a757915c_product_attr_style: ReferenceData!$K$2:$K$8
Name Validation_3c68c6523dd07bff0c29e856adc1b72966fc7aff2d2a3a2f4237ee295d621097_product_attr_product_finish: ReferenceData!$P$2:$P$12
Name Validation_3fadda4850edf058a64944408c88b40e6734c6c7c4293d3a02d7dabc9513376b_product_attr_measurement_unit_package2_weight: ReferenceData!$AF$2:$AF$3
Name Validation_4177f839b50cba64238187a248a918fb49bf545fdf70144d98998ea0cc65d469_product_attr_vase_model: ReferenceData!$BX$2:$BX$7
Name Validation_4876bc139665ccb9242cabf44652c979cf63868556a6b04614caf02fe9f895fe_product_attr_measurement_unit_package6_weight: ReferenceData!$AA$2:$AA$3
Name Validation_4c1c4731a9ae52779239b82b7d4b67745983fe30fb0c5c28aee7e339182d5140_product_attr_bulb_base_type: ReferenceData!$Q$2:$Q$17
Name Validation_523e92f02b0e70d27f6ac509a3a844aa39a0936b8cda01d0a8a14a989d7cf056_product_attr_washable_care: ReferenceData!$L$2:$L$7
Name Validation_53fdf102506278c56b96dadd6577bfeb8e9fdd65b086f2f1d1e419a7ec29dae9_product_attr_number_battery: ReferenceData!$BI$2:$BI$11
Name Validation_54f7557410ebf02ef20a0b9f7ac87e668b58ed97df9fa9cd94583975b2b99c11_product_attr_bathroom_accessory_model: ReferenceData!$BL$2:$BL$5
Name Validation_575b43b55067814554be1c07d11ef4154a79b34daa1c56fc81fb45165d2410e5_product_attr_does_product_contain_dangerous_substances: ReferenceData!$M$2:$M$3
Name Validation_57cf927f889b85715ce85accc3e2d5994dc11ba39dcf549b2d13791dc1fee871_product_attr_pattern: ReferenceData!$X$2:$X$3
Name Validation_592fd27c4bdf7bc45d2125c9423a2da20eeaea8b22abe07803283385719d2c51_product_attr_furniture_type: ReferenceData!$BY$2:$BY$5
Name Validation_5d225a507a9c87f4759308b2798de1b7c468a8289e4b99578d2389c7c71d6241_product_attr_nb_doors: ReferenceData!$BU$2:$BU$6
Name Validation_64c0e6b5337bdd1310d888c16566d4354da69ff9ff0dc9c3bee6f1af4292cb7b_product_attr_turn_on_system: ReferenceData!$AO$2:$AO$5
Name Validation_6f183be25cad241f19a07e36e6ac377e646cdea25e3bd3a5e8108f074c720bf7_product_attr_accessory_included: ReferenceData!$CF$2:$CF$13
Name Validation_6f3363ce38783950ca8b8106e9ddb5d97b797e9d7c6f6cc0568b7700bf38dc01_product_attr_bottom_typ: ReferenceData!$AV$2:$AV$3
Name Validation_6f7b2a51e857050b0248f722d466e5274d567637db9024d22bc4c7625b0b1022_product_attr_brand: ReferenceData!$B$2:$B$3653
Name Validation_75b06dc2c7e899e739470de5f2c35722fd48e593ea0b9a3bc70dff2e76f2ee46_product_attr_measurement_unit_diameter: ReferenceData!$H$2:$H$2
Name Validation_774a52a94dadf8305d05db5133e1fcebd0c78791f67871b7e7fcce0b5a8c81c8_product_attr_battery_type: ReferenceData!$BH$2:$BH$7
Name Validation_89abe726d61831fe243275e73176ec0994d3495661e7e94597aff3db182e046b_product_attr_measurement_unit_package7_weight: ReferenceData!$AE$2:$AE$3
Name Validation_8b83d2f1d8286bf1a90e40b7e55ba20d0f92ebcf22f86cb38416aa951ec41d20_product_attr_chair_model: ReferenceData!$AS$2:$AS$4
Name Validation_8f523cd390ff91edf9fbe78aa24bd642aa342ee36309a2b7f21a376d69a24bb6_product_attr_measurement_unit_seat_depth: ReferenceData!$U$2:$U$2
Name Validation_8ff177e64dd98071eeb68fea12c970a1a429c04e29e874705f4b410c7305af2b_product_attr_made_in: ReferenceData!$I$2:$I$205
Name Validation_92de071aebc97e378ae9b7a302e90b019fd10d7321796809000f5dbff9f2dcef_product_attr_modular_type: ReferenceData!$AQ$2:$AQ$8
Name Validation_942c733d78b217d5af2f6cd4432a3564b3a20e4e268be845b8ea005fc8206dda_product_attr_theme: ReferenceData!$AM$2:$AM$17
Name Validation_9798d01db3854a31923e0925f00d99bb93e2dad39b80d39a18a1c0fd4ddb6214_product_attr_specific_treatment: ReferenceData!$Z$2:$Z$7
Name Validation_98a0c32f3932767727ea6c27f3a11e9002c121df7fae47a0406302d074698436_product_attr_measurement_unit_length: ReferenceData!$F$2:$F$2
Name Validation_99bc66488194f93ea9cc9f9c9faf4d89ed0871f91475debb51c1d3542addf02d_product_attr_measurement_unit_package8_weight: ReferenceData!$AG$2:$AG$3
Name Validation_9ae9b620ca27a6948276d84e5df9d633fa516ccbf63b793c2081080eb38eeac8_product_attr_category: ReferenceData!$A$2:$A$111
Name Validation_a01ea7592c0c0e5a9dcf312b7318c5a576cdab41a411b83a5552e14bf5499ef5_product_attr_measurement_unit_package3_weight: ReferenceData!$AH$2:$AH$3
Name Validation_a044674cea1ebe2def514978765fdb7c9f18e00a6dc52e5834730482ae026de0_product_attr_padding: ReferenceData!$AW$2:$AW$5
Name Validation_a3d65393ac3942743b9de113f6a9f1abe7769d29052e9f6ea978c93fe63774a3_product_attr_pose: ReferenceData!$BF$2:$BF$6
Name Validation_a59ef51f4b287e47a443018e6be0c9a8ed8c835fca6ee0634e87b786cd1c9d27_product_attr_lounge_chair_model: ReferenceData!$CD$2:$CD$5
Name Validation_a5c2f46a5e679273bca1d36811a8d63334f2d329b5274de7006634536d28c10f_product_attr_nb_seats: ReferenceData!$BE$2:$BE$11
Name Validation_acef16430d35b9704e8b261bb996c5c85aa7ab14c71c30bae653ef88bef191a0_product_attr_baking_accesory: ReferenceData!$BP$2:$BP$11
Name Validation_b0e6a72a59d74a730cb09a4fc97bbe94eac35697ad7c9d82aa9aabc7e52be8b6_product_attr_energy_source: ReferenceData!$AN$2:$AN$7
Name Validation_bdee35a5463e4c34ee3a6d9a0f69bc6fb5083745b974129b3e1e71a6f2f99a72_product_attr_measurement_unit_armrest_width: ReferenceData!$V$2:$V$2
Name Validation_c3364daee02ad55a75b442bed8d1ded8b18246e611257bfa56d2e57ef025deef_product_attr_quality_bed: ReferenceData!$AR$2:$AR$3

Sheet Data
A1: Category | B1: Reference | D1: Product title | E1: Product title | F1: Product title | G1: Product title | H1: Ean Code | I1: Variant Code Group | J1: Brand | K1: Collection | L1: Description | M1: Description | N1: Description | O1: Description | P1: Color | Q1: Main Material | R1: Material Description | S1: Material Description | T1: Material Description | U1: Material Description | V1: Marketing Color | W1: Marketing Color | X1: Marketing Color | Y1: Marketing Color | Z1: Height | AA1: Measurement Unit Height | AB1: Length | AC1: Measurement Unit Length | AD1: Width | AE1: Measurement Unit Width | AF1: Diameter | AG1: Measurement Unit Diameter | AH1: Structure Material | AI1: Structure Material | AJ1: Structure Material | AK1: Structure Material | AL1: Wood Essence | AM1: Wood Essence | AN1: Wood Essence | AO1: Wood Essence | AP1: Wood Origin | AQ1: Wood Origin | AR1: Wood Origin | AS1: Wood Origin | AT1: Made In | AU1: Guarantee | AV1: Guarantee | AW1: Guarantee | AX1: Guarantee | AY1: Eco Responsible Label | AZ1: Style | BA1: Standards | BB1: Standards | BC1: Standards | BD1: Standards | BE1: Washable Care | BF1: Vidéo | BG1: Media 1 | BH1: Media 5 | BI1: Media 6 | BJ1: Media 7 | BK1: Media 8 | BL1: Media 9 | BM1: Media 10 | BN1: Pays principal de teinture ou impression du produit | BO1: Pays principal de confection du produit | BP1: Pays principal de tissage du produit | BQ1: Le produit contient au moins __value__ milligrammes de métaux précieux | BR1: Le produit contient au moins __value__ milligrammes de terres rares | BS1: Contenu minimum en matières recyclées dans l'emballage | BT1: Contenu minimum en matières recyclées dans le produit | BU1: Contient une substance extrêmement préoccupante | BV1: Contenu minimum en matières d'origine renouvelable dans le produit | BW1: Rejette des microfibres plastiques dans l'environnement lors du lavage | BX1: Présence de substances dangereuses | BY1: Emballage majoritairement recyclable | BZ1: Produit majoritairement recyclable | CA1: Name, company name or registered trademark of the manufacturer if in the EU, or of the responsible person in the EU | CB1: Postal address of the manufacturer if in the EU, or of the responsible person in the EU | CC1: Electronic contact details of the manufacturer if in the EU, or of the responsible person in the EU | CD1: Product size | CE1: Product Finish | CF1: Seat Height | CG1: Media 2 | CH1: Bulb Base Type | CI1: Measurement Unit Seat Height | CJ1: Media 3 | CK1: Watt Power | CL1: Seat Width | CM1: Media 4 | CN1: Power Measurement Unit | CO1: Measurement Unit Seat Width | CP1: Protection Index | CQ1: Seat Depth | CR1: Protection Index | CS1: Measurement Unit Seat Depth | CT1: Protection Index | CU1: Armrest Width | CV1: Protection Index | CW1: Measurement Unit Armrest Width | CX1: Seat Cushion Padding | CY1: Back Cushion Padding | CZ1: Armrest Cushion Padding | DA1: Package5 Weight | DB1: Seat Suspensions | DC1: Measurement Unit Package5 Weight | DD1: Pattern | DE1: Package5 Size | DF1: Characteristic | DG1: Package6 Weight | DH1: Specific Treatment | DI1: Measurement Unit Package6 Weight | DJ1: Assembling | DK1: Package6 Size | DL1: Nb Packages | DM1: Package7 Weight | DN1: Package1 Weight | DO1: Measurement Unit Package1 Weight | DP1: Measurement Unit Package7 Weight | DQ1: Package1 Size | DR1: Package7 Size | DS1: Package8 Weight | DT1: Package2 Weight | DU1: Measurement Unit Package2 Weight | DV1: Measurement Unit Package8 Weight | DW1: Package2 Size | DX1: Package8 Size | DY1: Package3 Weight | DZ1: Package9 Weight | EA1: Measurement Unit Package3 Weight | EB1: Measurement Unit Package9 Weight | EC1: Package3 Size | ED1: Package9 Size | EE1: Package4 Weight | EF1: Package10 Weight | EG1: Measurement Unit Package4 Weight | EH1: Measurement Unit Package10 Weight | EI1: Package4 Size | EJ1: Package10 Size | EK1: Armrest Cushion Padding | EL1: Seat Cushion Padding | EM1: Back Cushion Padding | EN1: Seat Suspensions | EO1: Armrest Cushion Padding | EP1: Back Cushion Padding | EQ1: Seat Cushion Padding | ER1: Seat Suspensions | ES1: Armrest Cushion Padding | ET1: Back Cushion Padding | EU1: Seat Cushion Padding | EV1: Seat Suspensions | EW1: Armchair Model | EX1: Theme | EY1: Energy Source | EZ1: Turn On System | FA1: Form | FB1: Modular Type | FC1: Quality Bed | FD1: Chair Model | FE1: Energy | FF1: Lamp model | FG1: Specific Bed Size | FH1: Bottom Typ | FI1: Padding | FJ1: Storage | FK1: Ideal for | FL1: Compatible With | FM1: Floor Lamp Model | FN1: Bulb Number | FO1: Mirror Model | FP1: Function | FQ1: Production | FR1: Nb Seats | FS1: Pose | FT1: Armrest | FU1: Compatible With | FV1: Battery | FW1: Compatible With | FX1: Nb Battery | FY1: Compatible With | FZ1: Sofa Corner | GA1: Food Type | GB1: Bathroom Accessory Model | GC1: Bed Size | GD1: Burning Time | GE1: Cup Model | GF1: Furniture Model | GG1: Baking Accesory | GH1: Capacity | GI1: Hanger Model | GJ1: Plate Model | GK1: Pan Model | GL1: Baking Sheet Type | GM1: Nb Doors | GN1: Perfume | GO1: Measurement Unit Capacity | GP1: Vase model | GQ1: Furniture Type | GR1: Nb Drawer | GS1: Carpet Model | GT1: Handle Type | GU1: Portion | GV1: Type of fragrance | GW1: Weaving Technical | GX1: Lounge Chair Model | GY1: Sofa Type | GZ1: Accessory Included | HA1: Burning Time | HB1: Table Model | HC1: Wick Thickness | HD1: Type of fragrance | HE1: Weaving Technical | HF1: Burning Time | HG1: Weaving Technical | HH1: Type of fragrance | HI1: Weaving Technical | HJ1: Burning Time | HK1: Type of fragrance
A2: attr_category | B2: attr_reference | D2: attr_name | E2: attr_name_es | F2: attr_name_it | G2: attr_name_de | H2: attr_ean | I2: attr_variant_code_group | J2: attr_brand | K2: attr_collection | L2: attr_description | M2: attr_description_it | N2: attr_description_es | O2: attr_description_de | P2: attr_color | Q2: attr_material | R2: attr_material_description | S2: attr_material_description_es | T2: attr_material_description_de | U2: attr_material_description_it | V2: attr_marketing_color | W2: attr_marketing_color_es | X2: attr_marketing_color_it | Y2: attr_marketing_color_de | Z2: attr_height | AA2: attr_measurement_unit_height | AB2: attr_length | AC2: attr_measurement_unit_length | AD2: attr_width | AE2: attr_measurement_unit_width | AF2: attr_diameter | AG2: attr_measurement_unit_diameter | AH2: attr_structure_material | AI2: attr_structure_material_es | AJ2: attr_structure_material_it | AK2: attr_structure_material_de | AL2: attr_wood_essence | AM2: attr_wood_essence_es | AN2: attr_wood_essence_it | AO2: attr_wood_essence_de | AP2: attr_wood_country_origin | AQ2: attr_wood_country_origin_es | AR2: attr_wood_country_origin_it | AS2: attr_wood_country_origin_de | AT2: attr_made_in | AU2: attr_guarantee | AV2: attr_guarantee_es | AW2: attr_guarantee_it | AX2: attr_guarantee_de | AY2: attr_eco_responsible_label | AZ2: attr_style | BA2: attr_standards | BB2: attr_standards_es | BC2: attr_standards_it | BD2: attr_standards_de | BE2: attr_washable_care | BF2: attr_video | BG2: attr_media_1 | BH2: attr_media_5 | BI2: attr_media_6 | BJ2: attr_media_7 | BK2: attr_media_8 | BL2: attr_media_9 | BM2: attr_media_10 | BN2: attr_country_of_transformation_dyeing_printing_label | BO2: attr_country_of_transformation_garment_label | BP2: attr_country_of_transformation_weaving_label | BQ2: attr_mass_of_precious_metals | BR2: attr_mass_of_rare_earths | BS2: attr_minimum_percentage_of_recycled_material_in_packaging | BT2: attr_minimum_percentage_of_recycled_material_in_product | BU2: attr_name_of_dangerous_substance | BV2: attr_percentage_of_renewable_material | BW2: attr_percentage_of_synthetic_fibres | BX2: attr_does_product_contain_dangerous_substances | BY2: attr_is_packaging_recyclable | BZ2: attr_is_product_recyclable | CA2: attr_ue_manufacturer_representative_name | CB2: attr_ue_manufacturer_representative_address | CC2: attr_ue_manufacturer_representative_email | CD2: attr_product_size | CE2: attr_product_finish | CF2: attr_seat_height | CG2: attr_media_2 | CH2: attr_bulb_base_type | CI2: attr_measurement_unit_seat_height | CJ2: attr_media_3 | CK2: attr_max_power | CL2: attr_seat_width | CM2: attr_media_4 | CN2: attr_power_measurement_unit | CO2: attr_measurement_unit_seat_width | CP2: attr_protection_index | CQ2: attr_seat_depth | CR2: attr_protection_index_es | CS2: attr_measurement_unit_seat_depth | CT2: attr_protection_index_it | CU2: attr_armrest_width | CV2: attr_protection_index_de | CW2: attr_measurement_unit_armrest_width | CX2: attr_seat_cushion_padding | CY2: attr_back_cushion_padding | CZ2: attr_armrest_cushion_padding | DA2: attr_package5_weight | DB2: attr_seat_suspensions | DC2: attr_measurement_unit_package5_weight | DD2: attr_pattern | DE2: attr_package5_size | DF2: attr_characteristic | DG2: attr_package6_weight | DH2: attr_specific_treatment | DI2: attr_measurement_unit_package6_weight | DJ2: attr_assembled | DK2: attr_package6_size | DL2: attr_nb_packages | DM2: attr_package7_weight | DN2: attr_package1_weight | DO2: attr_measurement_unit_package1_weight | DP2: attr_measurement_unit_package7_weight | DQ2: attr_package1_size | DR2: attr_package7_size | DS2: attr_package8_weight | DT2: attr_package2_weight | DU2: attr_measurement_unit_package2_weight | DV2: attr_measurement_unit_package8_weight | DW2: attr_package2_size | DX2: attr_package8_size | DY2: attr_package3_weight | DZ2: attr_package9_weight | EA2: attr_measurement_unit_package3_weight | EB2: attr_measurement_unit_package9_weight | EC2: attr_package3_size | ED2: attr_package9_size | EE2: attr_package4_weight | EF2: attr_package10_weight | EG2: attr_measurement_unit_package4_weight | EH2: attr_measurement_unit_package10_weight | EI2: attr_package4_size | EJ2: attr_package10_size | EK2: attr_armrest_cushion_padding_es | EL2: attr_seat_cushion_padding_es | EM2: attr_back_cushion_padding_es | EN2: attr_seat_suspensions_es | EO2: attr_armrest_cushion_padding_it | EP2: attr_back_cushion_padding_it | EQ2: attr_seat_cushion_padding_it | ER2: attr_seat_suspensions_it | ES2: attr_armrest_cushion_padding_de | ET2: attr_back_cushion_padding_de | EU2: attr_seat_cushion_padding_de | EV2: attr_seat_suspensions_de | EW2: attr_armchair_model | EX2: attr_theme | EY2: attr_energy_source | EZ2: attr_turn_on_system | FA2: attr_form | FB2: attr_modular_type | FC2: attr_quality_bed | FD2: attr_chair_model | FE2: attr_energy | FF2: attr_lamp_model | FG2: attr_specific_bed_size | FH2: attr_bottom_typ | FI2: attr_padding | FJ2: attr_storage | FK2: attr_ideal_for | FL2: attr_compatible_with | FM2: attr_floor_lamp_model | FN2: attr_number_bulbs | FO2: attr_mirror_model | FP2: attr_function | FQ2: attr_production | FR2: attr_nb_seats | FS2: attr_pose | FT2: attr_armrest | FU2: attr_compatible_with_es | FV2: attr_battery_type | FW2: attr_compatible_with_it | FX2: attr_number_battery | FY2: attr_compatible_with_de | FZ2: attr_sofa_corner | GA2: attr_food_type | GB2: attr_bathroom_accessory_model | GC2: attr_bed_size | GD2: attr_burning_time | GE2: attr_cup_model | GF2: attr_furniture_model | GG2: attr_baking_accesory | GH2: attr_product_capacity | GI2: attr_hanger_model | GJ2: attr_plate_model | GK2: attr_pan_model | GL2: attr_baking_sheet_type | GM2: attr_nb_doors | GN2: attr_scent | GO2: attr_measurement_unit_capacity | GP2: attr_vase_model | GQ2: attr_furniture_type | GR2: attr_nb_drawer | GS2: attr_carpet_model | GT2: attr_handle_type | GU2: attr_portion | GV2: attr_type_fragrance | GW2: attr_weaving_technical | GX2: attr_lounge_chair_model | GY2: attr_sofa_type | GZ2: attr_accessory_included | HA2: attr_burning_time_es | HB2: attr_table_model | HC2: attr_wick_thickness | HD2: attr_type_fragrance_es | HE2: attr_weaving_technical_es | HF2: attr_burning_time_it | HG2: attr_weaving_technical_it | HH2: attr_type_fragrance_it | HI2: attr_weaving_technical_de | HJ2: attr_burning_time_de | HK2: attr_type_fragrance_de
A3: Decoration/Rugs/Living room rugs | B3: AFCHU001_0298-290x197 | C3: =_xlfn.XLOOKUP(B3,Sheet1!A:A,Sheet1!A:A,) -> AFCHU001_0298-290x197 | H3: 6097312255277 | J3: Bazar Bizar | L3: <p><span>Le Tapis Afghan Tissé à la Main #0298 porte l’héritage des traditions afghanes séculaires, où motifs et textures dépassent la décoration pour devenir récit culturel. Sa base en laine ivoire douce est parcourue de fines lignes brunes, encadrée de tons plus profonds et terminée par des franges qui célèbrent son essence artisanale.<br><br>Mesurant 290 × 197 cm, il apporte équilibre et chaleur aux grands espaces, qu’il s’agisse d’un salon formel, d’une salle à manger ou d’un bureau. Les fibres de laine durables, travaillées à la main et souvent teintées avec des pigments naturels, assurent solidité au quotidien tout en offrant confort tactile et douceur sous les pieds.<br><br>Chaque tapis est une création singulière, avec des nuances et irrégularités de tissage révélant la main de l’artisan. Cette pièce est non seulement un textile fonctionnel mais aussi un patrimoine vivant, reconnu mondialement par des prix internationaux et transmis de génération en génération par les tisserands afghans.</span></p> | M3: <p><span>Il Tappeto Afgano Tessuto a Mano #0298 porta con sé il peso delle tradizioni tessili afghane secolari, dove motivi e texture sono più che decorazione: sono narrazione culturale. La sua base in lana avorio è segnata da sottili linee marroni, bordata da tonalità più scure e rifinita con frange che celebrano la sua essenza artigianale.<br><br>Con dimensioni di 290 × 197 cm, dona equilibrio e calore a spazi ampi, che si tratti di un soggiorno formale, di una sala da pranzo o di uno studio. Le fibre di lana resistenti, lavorate a mano e spesso colorate con pigmenti naturali, garantiscono solidità nell’uso quotidiano mantenendo comfort e morbidezza.<br><br>Ogni tappeto è una creazione singolare, con variazioni di tono e tessitura che rivelano la mano dell’artigiano. Questo pezzo non è solo un tessuto funzionale ma un patrimonio vivente, parte di una tradizione riconosciuta a livello internazionale e tramandata da generazioni di tessitori afghani.</span></p> | N3: <p><span>La Alfombra Afgana Tejida a Mano #0298 lleva consigo el peso de las tradiciones afganas ancestrales, donde los patrones y texturas son narración cultural más allá de la decoración. Su base de lana marfil suave está trazada con finas líneas marrones, enmarcada por tonos más profundos y acabada con flecos que celebran su esencia artesanal.<br><br>Con un tamaño de 290 × 197 cm, aporta equilibrio y calidez a amplios espacios, ya sea en un salón formal, un comedor o un estudio. Las fibras de lana duraderas, trabajadas a mano y teñidas a menudo con pigmentos naturales, garantizan resistencia para el uso diario y suavidad bajo los pies.<br><br>Cada alfombra es una creación única, con sutiles variaciones en el tejido y el tono que revelan la mano del artesano. Esta pieza no solo es un textil funcional sino también un patrimonio vivo, parte de una tradición reconocida mundialmente con premios internacionales y transmitida por generaciones de tejedores afganos.</span></p> | O3: <p><span>Der Handgewebte Afghanische Teppich #0298 trägt das Gewicht jahrhundertealter afghanischer Webtraditionen, in denen Muster und Texturen mehr als Dekoration sind – sie sind kulturelles Erzählen. Der weiche elfenbeinfarbene Wollgrund ist mit feinen braunen Linien durchzogen, von dunkleren Tönen eingefasst und mit Fransen versehen, die seine handwerkliche Essenz betonen.<br><br>Mit den Maßen 290 × 197 cm bringt er Balance und Wärme in großzügige Räume, sei es ein formales Wohnzimmer, ein Essbereich oder ein Arbeitszimmer. Strapazierfähige Wollfasern, von Hand verarbeitet und oft mit Naturfarben gefärbt, sorgen für Stärke im Alltag und bieten zugleich weichen Komfort.<br><br>Jeder Teppich ist ein Unikat, mit feinen Abweichungen in Gewebe und Farbton, die die Hand des Kunsthandwerkers sichtbar machen. Dieses Stück ist nicht nur funktionaler Textil, sondern auch lebendiges Erbe, Teil einer Tradition, die weltweit mit internationalen Preisen ausgezeichnet und von Generation zu Generation afghanischer Weber weitergegeben wird.</span></p> | P3: Beige | Q3: Wool | Z3: 1 | AA3: cm | AB3: 290 | AC3: cm | AD3: 197 | AE3: cm | AG3: cm | AT3: United Arab Emirates | BG3: https://bazarbizar.katanapim.com/content/images/thumbs/002/0028137_afchu001_0298-290x197.jpeg | CA3: Bazar Bizar | CB3: 2550 | CD3: 290 x 197 x 1 cm | CG3: https://bazarbizar.katanapim.com/content/images/thumbs/002/0024083_the-handwoven-afghan-rug-0298.jpeg | CJ3: https://bazarbizar.katanapim.com/content/images/thumbs/002/0024082_the-handwoven-afghan-rug-0298.jpeg | DD3: Without pattern | FA3: Rectangular | GS3: Oriental carpet | HC3: Short wick
A4: Storage accessories/Decorative storages/Baskets | B4: BA001B-M | C4: =_xlfn.XLOOKUP(B4,Sheet1!A:A,Sheet1!A:A,) -> BA001B-M | D4: Panier en bambou et perles noir 15x15x15cm | E4: Cesta de bambú y cuentas en negro 15x15x15 cm | F4: Cesto in bambù e perline nero 15x15x15 cm | G4: Korb aus Bambus und Perlen in schwarz, 15 x 15 x 15 cm | H4: 7438246078089 | I4: BA001 | J4: Bazar Bizar | K4: Beaded | L4: <p>Ces boîtes à offrandes joliment perlées sont entièrement fabriquées à la main par des artisans balinais avec amour et soin. À utiliser comme rangement ou simple élément décoratif, séparément ou ensemble, elles trouveront une place remarquable dans votre intérieur. Utilisées à Bali lors des cérémonies religieuses pour contenir les offrandes destinées aux dieux, elles ajouteront une touche d'authenticité et d'exotisme à votre décoration.</p> | M4: <p>Questi splendidi cestini d'offerta con perline sono interamente fatti a mano da artigiani balinesi con amore e cura. Perfetti come contenitori o come elementi decorativi, separati o insieme trovano posto nella vostra casa. Utilizzati a Bali per custodire le offerte agli dei, oggi arricchiscono l'arredo con autenticità ed esotismo.</p> | N4: <p>Estas cajas de ofrenda con abalorios están hechas completamente a mano por artesanos balineses con cuidado y dedicación. Puedes usarlas para guardar objetos o como elemento decorativo. Se emplean en Bali durante ceremonias religiosas para guardar ofrendas y ahora añadirán autenticidad y exotismo a tu hogar.</p> | O4: <p>Diese liebevoll mit Perlen verzierten Opferboxen werden von balinesischen Kunsthandwerkern handgefertigt. Ob als Aufbewahrung oder Dekoration, einzeln oder zusammen sind sie ein Blickfang in Ihrem Zuhause. In Bali dienen sie zur Aufbewahrung von Opfergaben für die Götter und bringen nun Authentizität und Exotik in Ihre Einrichtung.</p> | P4: Black | Q4: Bamboo | Z4: 15 | AA4: cm | AB4: 15 | AC4: cm | AD4: 15 | AE4: cm | AG4: cm | AT4: Indonesia | BG4: https://bazarbizar.katanapim.com/content/images/thumbs/002/0027694_ba001b-m.jpeg | CA4: Bazar Bizar | CB4: 2550 | CD4: 15 x 15 x 15 cm | CG4: https://bazarbizar.katanapim.com/content/images/thumbs/001/0019005_the-burned-bowl-black-s.jpeg | CJ4: https://bazarbizar.katanapim.com/content/images/thumbs/001/0019008_the-beaded-basket-black-s.jpeg | CM4: https://bazarbizar.katanapim.com/content/images/thumbs/001/0019007_the-beaded-basket-black-s.jpeg | FA4: Square | FQ4: Artisanal
A5: Storage accessories/Decorative storages/Baskets | B5: BA001B-SET3 | C5: =_xlfn.XLOOKUP(B5,Sheet1!A:A,Sheet1!A:A,) -> BA001B-SET3 | H5: 7438246089078 | J5: Bazar Bizar | L5: Ces boîtes à offrandes joliment perlées sont entièrement fabriquées à la main par des artisans balinais avec amour et soin. A utiliser comme rangement ou simple élément décoratif, séparément ou ensemble ces boîtes trouveront une place accrocheuse dans votre maison ! Elles sont utilisées à Bali lors des cérémonies religieuses pour contenir les offrandes aux dieux, transformées en objet décoratif ces boîtes ajouteront une touche d'authenticité et d'exotisme à votre décoration. | M5: Questi bellissimi cestini d'offerta di perline sono completamente fatte a mano da artigiani balinesi con amore e cura. Possono essere utilizzati per lo stoccaggio o semplicemente come elemento decorativo. Separatamente o insieme, questi cestini troveranno un posto accattivante nella vostra casa. Sono stati utilizzati a Bali durante le cerimonie religiose per contenere le offerte agli dei, e ora saranno un oggetto decorativo che aggiungerà un tocco di autenticità ed esotismo alla vostra decorazione. | N5: Estas cajas de ofrenda decoradas con hermosos abalorios, son hechas completamente a mano con mucho amor y cuidado por artesanos balineses. Puedes utilizarlas para almacenar cosas o simplemente como un bonito elemento decorativo. Se conocen por ser usadas en Bali para guardar ofrendas a los dioses durante ceremonias religiosas, y ahora han sido transformadas en un bonito objeto que añadirá un toque de autenticidad y exotismo a tu decoración. | O5: Diese wunderschön mit Perlen verzierten Opferboxen werden von balinesischen Kunsthandwerkern mit viel Liebe und Sorgfalt handgefertigt. Als Aufbewahrung oder einfaches Dekorationselement zu verwenden, einzeln oder zusammen werden diese Boxen einen auffälligen Platz in Ihrem Zuhause finden! Sie werden in Bali bei religiösen Zeremonien verwendet, um Opfergaben für die Götter aufzubewahren. In ein dekoratives Objekt verwandelt, werden diese Boxen Ihrer Dekoration einen Hauch von Authentizität und Exotik verleihen. | P5: Black | Q5: Bamboo | R5: Bambou - Perles | S5: Bambú - Cuentas | T5: Bamboo - Perlen | U5: Bambù - Perline | V5: Noir | W5: Negro | X5: Nero | Y5: Schwarz | Z5: 0 | AA5: cm | AB5: 12-15-20 | AC5: cm | AD5: 12-15-20 | AE5: cm | AG5: cm | AT5: Indonesia | AZ5: Sea side | BG5: https://bazarbizar.katanapim.com/content/images/thumbs/0009384_ba001b-set3.webp | BH5: https://bazarbizar.katanapim.com/content/images/thumbs/0009391_ba001b-set3_5.webp | CD5: 12-15-20cm x 12-15-20cm x 0cm | CG5: https://bazarbizar.katanapim.com/content/images/thumbs/0013994_the-burned-bowl-black-s.webp | CJ5: https://bazarbizar.katanapim.com/content/images/thumbs/0009385_ba001b-set3_100.webp | CM5: https://bazarbizar.katanapim.com/content/images/thumbs/0009386_ba001b-set3_101.webp | FA5: Other form | FQ5: Artisanal
A6: Storage accessories/Decorative storages/Baskets | B6: BA001W-SET3 | C6: =_xlfn.XLOOKUP(B6,Sheet1!A:A,Sheet1!A:A,) -> BA001W-SET3 | F6: Set di 3 cestini bianchi con perline | H6: 7438246089061 | J6: Bazar Bizar | M6: Questi bellissimi cestini d'offerta di perline sono completamente fatte a mano da artigiani balinesi con amore e cura. Possono essere utilizzati per lo stoccaggio o semplicemente come elemento decorativo. Separatamente o insieme, questi cestini troveranno un posto accattivante nella vostra casa. Sono stati utilizzati a Bali durante le cerimonie religiose per contenere le offerte agli dei, e ora saranno un oggetto decorativo che aggiungerà un tocco di autenticità ed esotismo alla vostra decorazione. | Z6: 15 | AA6: cm | AB6: 20 | AC6: cm | AD6: 20 | AE6: cm | AZ6: Sea side | BG6: https://cdn.webshopapp.com/shops/298158/files/326410098/file.jpg | FQ6: Artisanal
A7: Decoration/Wall decoration/Decorative plates | B7: BA002W-L | C7: =_xlfn.XLOOKUP(B7,Sheet1!A:A,Sheet1!A:A,) -> BA002W-L | D7: A croix de la coquille blanc | E7: La concha cruz blanca | F7: Croce di conchiglia bianca | G7: Weißes Muschelkreuz | H7: 7438246080013 | J7: Bazar Bizar | L7: <p>Ces belles croix décoratives côtières sont recouvertes de coquillages blancs qui composent un joli motif floral. Elles sont superbes suspendues ou posées sur une table ou une étagère. Un joli must de la décoration côtière !</p> | M7: <p>Queste belle croci decorative stile costiere, sono coperte di conchiglie bianche che formano un bel motivo floreale. Stanno benissimo appese o appoggiate su un tavolo o una mensola. Una bella must-have decorazione boho!</p> | N7: <p>Estas bonitas cruces costeras decorativas están cubiertas de conchas blancas, formando un bonito diseño de flores. Quedan muy bien colgadas o colocadas sobre una mesa o estantería. ¡Una preciosa adición a tu decoración costera!</p> | O7: <p>Diese schönen dekorativen Küstenkreuze sind mit weißen Muscheln bedeckt, die ein hübsches Muster bilden. Sie sehen toll aus, wenn man sie aufhängt oder auf einen Tisch oder ein Regal legt. Eine schöne Küstendekoration, die man einfach haben muss!</p> | P7: White | Q7: Mother-of-pear | R7: Coquille | S7: Concha | T7: Schale | U7: Conchiglia | V7: White | W7: White | X7: White | Y7: White | Z7: 4 | AA7: cm | AB7: 32 | AC7: cm | AD7: 43 | AE7: cm | AG7: cm | AT7: Indonesia | AZ7: Sea side | BG7: https://bazarbizar.katanapim.com/content/images/thumbs/001/0013971_the-shell-cross-white-l.jpeg | CD7: 32cm x 43cm x 4cm | CG7: https://bazarbizar.katanapim.com/content/images/thumbs/001/0013972_the-shell-cross-white-l.jpeg | CJ7: https://bazarbizar.katanapim.com/content/images/thumbs/001/0013973_the-shell-cross-white-l.jpeg | EX7: Sea
A8: Decoration/Wall decoration/Decorative plates | B8: BA002W-M | C8: =_xlfn.XLOOKUP(B8,Sheet1!A:A,Sheet1!A:A,) -> BA002W-M | D8: Croix suspendue en coquillages blanc | E8: Cruz colgante de conchas | F8: Croce appesa in conchiglie bianche | H8: 7438246080006 | L8: Ces belles croix décoratives côtières sont recouvertes de coquillages blancs qui composent un joli motif floral. Elles sont superbes suspendues ou posées sur une table ou une étagère. Un joli must de la décoration côtière ! | N8: Estas bonitas cruces recubiertas de conchas blancas, forman un bonito diseño en forma de flor. Son el perfecto elemento decorativo de estilo costero, que queda muy bien colgada, encima de una mesa o sobre una estantería. ¡No te quedes sin la tuya! | P8: White | Z8: 31 | AA8: cm | AC8: cm | AE8: cm | BG8: https://cdn.webshopapp.com/shops/298158/files/454900699/file.jpg
A9: Decoration/Wall decoration/Decorative plates | B9: BA005W-M | C9: =_xlfn.XLOOKUP(B9,Sheet1!A:A,Sheet1!A:A,) -> BA005W-M | D9: Coeur suspendu en coquillages | E9: Corazón colgante de conchas | F9: Cuore appeso in conchiglie bianche | H9: 7438246079086 | J9: Bazar Bizar | L9: Ces magnifiques cœurs décoratifs côtiers sont recouverts de coquillages blancs qui composent un joli motif floral. Ils sont superbes suspendus ou posés sur une table ou une étagère. Un joli must de la décoration côtière ! | M9: Questa bella croce decorativa costiera è ricoperta di conchiglie bianche, creando un bel motivo. Può essere appeso al muro o su un tavolo o una mensola - una bella decorazione costiera must-have! | N9: Estos bonitos corazones recubiertos de conchas blancas, forman un bonito diseño en forma de flor. Son el perfecto elemento decorativo de estilo costero, que queda muy bien colgado, encima de una mesa o sobre una estantería. ¡No te quedes sin el tuyo! | O9: Diese schönen dekorativen Küstenherzen sind mit weißen Muscheln bedeckt, die ein hübsches Blumenmuster bilden. Sie sehen toll aus, wenn man sie aufhängt oder auf einen Tisch oder ein Regal legt. Eine schöne Küstendekoration, die man einfach haben muss! | P9: White | Q9: Natural fibers | AA9: cm | AB9: 17 | AC9: cm | AD9: 17 | AE9: cm | BG9: https://cdn.webshopapp.com/shops/298158/files/426857694/file.jpg | BH9: https://cdn.webshopapp.com/shops/298158/files/430889573/file.jpg | CG9: https://cdn.webshopapp.com/shops/298158/files/430889465/file.jpg | CJ9: https://cdn.webshopapp.com/shops/298158/files/430889567/file.jpg | CM9: https://cdn.webshopapp.com/shops/298158/files/432095718/file.jpg
A10: Lifestyle/Pockets and wallets/Purses and wallets | B10: BA017Br | C10: =_xlfn.XLOOKUP(B10,Sheet1!A:A,Sheet1!A:A,) -> BA017Br | H10: 7438246176174 | J10: Bazar Bizar | L10: <p>Un équilibre délicat entre texture et fonction définit la Pochette Purse en Cuir, conçue pour accompagner des moments qui traversent la journée avec fluidité. Dans cette composition apaisée, cette petite pochette en cuir marron s’intègre naturellement aux routines détendues et offre une présence discrète.</p> <p>Au delà de sa taille, l’expérience se révèle à l’usage. Portée à la main ou glissée sous le bras, elle accompagne les déplacements lents à travers marchés, dîners ou soirées improvisées. La façade tissée apporte de la profondeur tandis que le dos en cuir lisse repose confortablement contre le corps, créant un dialogue subtil entre matière et toucher.</p> <p>Fabriquée en Indonésie, cette pochette en cuir faite main associe cuir et coquillage selon des techniques traditionnelles. De légères variations de ton et de tissage reflètent l’origine des matériaux et confèrent à chaque pochette un caractère façonné par le lieu et le geste.</p> | M10: <p>Un delicato equilibrio tra texture e funzione definisce la Borsa Purse in Pelle, pensata per accompagnare momenti che scorrono con naturalezza durante la giornata. In questa composizione calma, questa piccola borsa in pelle marrone si inserisce spontaneamente nelle routine rilassate offrendo una presenza discreta.</p> <p>Oltre alle dimensioni, l’esperienza emerge nell’uso. Portata a mano o sotto il braccio, accompagna movimenti lenti tra mercati, cene o serate senza programma. Il pannello intrecciato frontale aggiunge profondità, mentre il retro in pelle liscia aderisce comodamente al corpo, creando un dialogo silenzioso tra materiale e tatto.</p> <p>Realizzata in Indonesia, questa borsa in pelle artigianale unisce pelle e conchiglia attraverso tecniche tradizionali. Le leggere variazioni di tono e intreccio riflettono l’origine dei materiali e conferiscono a ogni clutch un carattere plasmato dal luogo e dal processo.</p> | N10: <p>Existe un equilibrio suave entre textura y función en el Bolso Purse de Cuero, creado para acompañar momentos que fluyen a lo largo del día. En esta composición serena, este pequeño bolso de cuero marrón se integra de forma natural en rutinas relajadas y ofrece presencia sin imponerse.</p> <p>Más allá del tamaño, la experiencia reside en el uso. Llevado en la mano o bajo el brazo, acompaña movimientos tranquilos por mercados, cenas o noches improvisadas. El frontal tejido aporta profundidad, mientras que la parte trasera de cuero liso descansa cómodamente contra el cuerpo, creando un ritmo discreto entre material y tacto.</p> <p>Elaborado en Indonesia, este bolso de cuero hecho a mano combina cuero y concha mediante técnicas tradicionales. Sutiles variaciones de tono y trama reflejan el origen del material y otorgan a cada bolso tipo clutch un carácter definido por el lugar y el proceso.</p> | O10: <p>Ein sanftes Gleichgewicht zwischen Textur und Funktion prägt die Purse Leder Tasche, gestaltet für Momente, die sich leicht durch den Tag bewegen. In dieser ruhigen Komposition fügt sich diese kleine braune Ledertasche natürlich in entspannte Routinen ein und zeigt Präsenz ohne Aufmerksamkeit zu verlangen.</p> <p>Über die Größe hinaus liegt das Erlebnis in der Nutzung. In der Hand gehalten oder unter dem Arm getragen begleitet sie ruhige Wege über Märkte, zu Abendessen oder durch ungeplante Abende. Die gewebte Vorderseite verleiht Tiefe, während die glatte Lederseite angenehm am Körper anliegt und einen leisen Rhythmus zwischen Material und Berührung schafft.</p> <p>In Indonesien gefertigt vereint diese handgearbeitete Ledertasche Leder und Muschel mit traditionellen Techniken. Feine Variationen in Ton und Flechtung spiegeln die Materialherkunft wider und verleihen jeder Leder Clutch einen Charakter, der von Ort und Prozess geprägt ist.</p> | P10: Brown | Q10: Leather split leather | Z10: 1 | AA10: cm | AB10: 20 | AC10: cm | AD10: 14 | AE10: cm | AG10: cm | AT10: Indonesia | BG10: https://bazarbizar.katanapim.com/content/images/thumbs/001/0016178_the-purse-leather-purse-brown.jpeg | CA10: Bazar Bizar | CB10: 2550 | CD10: 20 x 14 x 1 cm
A11: Decoration/Decoration objects/Indoor pots | B11: BA024NB-M | C11: =_xlfn.XLOOKUP(B11,Sheet1!A:A,Sheet1!A:A,) -> BA024NB-M | H11: 7438246095048 | J11: Bazar Bizar | K11: Cowrie | Z11: 15 | AA11: cm | AB11: 17 | AC11: cm | AD11: 17 | AE11: cm
A12: Decoration/Decoration objects/Vases | B12: BA024N-M | C12: =_xlfn.XLOOKUP(B12,Sheet1!A:A,Sheet1!A:A,) -> BA024N-M | D12: Porte-plante en coton et coquillage blanc | E12: Jardinera de algodón y concha blanca | F12: Portapiante in cotone e conchiglia bianca | H12: 7438246094041 | J12: Bazar Bizar | L12: Vous pouvez habiller vos vieux et laids pots, vases ou planteurs avec nos planteurs au crochet et les rendre tout stylé et conçu vers le haut.Soit il est sur votre table d'appoint, étagère manteau ou dans la salle de bains les planteurs enveloppés dans ces belles couvertures de crochet serait ajouter plus de lunes de beauté à votre décor et le style de la maison. Ces magnifiques couvertures sont le cadeau parfait pour vos proches. | M12: Ora puoi vestire i tuoi vecchi vasi da fiori, vasi o fioriere con i nostri portavasi all'uncinetto e farli sembrare eleganti e disegnati. Sul tavolino, sulla mensola del camino o in bagno, i vasi avvolti in queste belle coperture all'uncinetto aggiungeranno un tocco di stile alla vostra casa. Queste belle copertine sono il regalo perfetto per i vostri cari! | N12: Ahora puedes vestir a tus viejas macetas, jarrones o jardineras con nuestros maceteros de macramé y hacer que se vean mucho más estilizadas y bonitas. Utilízalas en una mesita de noche, en la repisa de la chimenea o en un baño, y observa como agregan belleza a la decoración y al estilo de tu hogar. ¡También hacen el regalo perfecto para tus seres queridos! | P12: Beige | Q12: Cotton | Z12: 15 | AA12: cm | AB12: 17 | AC12: cm | AD12: 17 | AE12: cm | BG12: https://cdn.webshopapp.com/shops/298158/files/456721664/file.jpg
A13: Decoration/Decoration objects/Vases | B13: BA025W-M | C13: =_xlfn.XLOOKUP(B13,Sheet1!A:A,Sheet1!A:A,) -> BA025W-M | H13: 7438246080099 | J13: Bazar Bizar | Z13: 14 | AA13: cm | AB13: 17 | AC13: cm | AD13: 17 | AE13: cm | BG13: https://cdn.webshopapp.com/shops/298158/files/426857738/file.jpg
A14: Decoration/Candles and fragrance/Candles/Candle | B14: BA025W-S | C14: =_xlfn.XLOOKUP(B14,Sheet1!A:A,Sheet1!A:A,) -> BA025W-S | H14: 7438246080082 | J14: Bazar Bizar | Z14: 8 | AA14: cm | AB14: 12 | AC14: cm | AD14: 12 | AE14: cm | BG14: https://cdn.webshopapp.com/shops/298158/files/426857719/file.jpg
A15: Storage accessories/Decorative storages/Baskets | B15: BA028N-SET2 | C15: =_xlfn.XLOOKUP(B15,Sheet1!A:A,Sheet1!A:A,) -> BA028N-SET2 | D15: Panier en perles et noix de coco naturel set de 2 | E15: Cesta de cuentas y coco juego de 2 | F15: Set di 2 cestini di perline e cocco | G15: 2er Set Korb aus coconut und muscheln | H15: 7438246090005 | J15: Bazar Bizar | L15: <p>Le panier carré en coquille de noix de coco est utilisé à l'origine comme boîte à offrandes, entièrement fabriqué à la main par des artisans balinais avec amour et soin. Fabriqué à partir de noix de coco et de bambou. Elles sont utilisées à Bali lors des cérémonies religieuses pour contenir les offrandes aux dieux, transformées en objet décoratif ces boîtes ajouteront une touche d'authenticité et d'exotisme à votre décoration. Posez-les sur une étagère pour attirer le regard dans votre salle de bain, votre chambre à coucher ou votre chambre d'enfant. Parfaites pour ranger vos bijoux ou de plus petits objets précieux que vous ne voulez jamais perdre. Un beau cadeau pour un être cher!</p> | M15: <p>Il Cestino Quadrato in Conchiglia di Cocco è originariamente usato come Scatola delle Offerte, interamente fatto a mano da artigiani balinesi con amore e cura. È stato usato a Bali durante le cerimonie religiose per fare offerte agli dei. Ora potete avere questo elemento bello ed esotico nella tua casa, aggiungerà molto stile alla tua decorazione!</p> | N15: <p>La cesta de cáscara de coco fue creada originalmente como caja de ofrendas, está hecha a mano con coco y bambú por artesanos balineses. Se usa en las ceremonias religiosas para guardar ofrendas a los dioses, pero ahora han sido convertidas en un elegante elemento decorativo que añadirá un toque de autenticidad y exotismo a tu decoración. Colócalas en una estantería, un cuarto de baño, dormitorio o también en la habitación de los niños. Son perfectas para guardar joyas u objetos pequeños que no quisieras perder de vista. ¡Hacen también un bonito regalo para un ser querido!</p> | O15: <p>Der quadratische Korb aus Kokosnussschalen wurde ursprünglich als Opfergabe verwendet und wird von balinesischen Kunsthandwerkern mit viel Liebe und Sorgfalt handgefertigt. Hergestellt aus Kokosnuss und Bambus. Sie werden in Bali bei religiösen Zeremonien verwendet, um Opfergaben für die Götter aufzubewahren. Umgewandelt in ein dekoratives Objekt verleihen diese Boxen Ihrer Dekoration einen Hauch von Authentizität und Exotik. Stellen Sie sie auf ein Regal als Blickfang in Ihrem Badezimmer, Schlafzimmer oder Kinderzimmer. Perfekt für die Aufbewahrung von Schmuck oder kleineren Kostbarkeiten, die Sie nie verlieren möchten. Ein schönes Geschenk für einen geliebten Menschen!</p> | P15: Beige | Q15: Bamboo | R15: Bambou - Coco | S15: Bambú - Coco | T15: Bamboo - Kokosnuss | U15: Bambù - Cocco | V15: Naturel | W15: Natural | X15: Naturale | Y15: Natur | Z15: 13 - 14 | AA15: cm | AB15: 20 - 28 | AC15: cm | AD15: 20 - 28 | AE15: cm | AG15: cm | AT15: Indonesia | AZ15: Sea side | BG15: https://bazarbizar.katanapim.com/content/images/thumbs/0009596_ba028n-set2.webp | BH15: https://bazarbizar.katanapim.com/content/images/thumbs/0009605_ba028n-set2_109.webp | BI15: https://bazarbizar.katanapim.com/content/images/thumbs/0009598_ba028n-set2_102.webp | BJ15: https://bazarbizar.katanapim.com/content/images/thumbs/0012435_ba028n-set2_3.webp | BK15: https://bazarbizar.katanapim.com/content/images/thumbs/0012292_ba028n-set2_4.webp | CD15: 20 - 28cm x 20 - 28cm x 13 - 14cm | CG15: https://bazarbizar.katanapim.com/content/images/thumbs/0014530_the-coconut-shell-basket-natural-set-of-2.webp | CJ15: https://bazarbizar.katanapim.com/content/images/thumbs/0009601_ba028n-set2_105.webp | CM15: https://bazarbizar.katanapim.com/content/images/thumbs/0014529_the-simba-mirror-black-l.webp | FQ15: Artisanal
A16: Lifestyle/Bags/Tote bags | B16: BA032BB-L | C16: =_xlfn.XLOOKUP(B16,Sheet1!A:A,Sheet1!A:A,) -> BA032BB-L | D16: Pochette en raphia noir | E16: Clutch de rafia negro | F16: Pochette in rafia nero 32x3 cm | G16: Reissverschluss aus Bast schwarz | H16: 7438246082000 | I16: BA032 | J16: Bazar Bizar | K16: Raffia | L16: Ajoutez une touche d'lgance votre tenue avec notre Pochette en raphia noir. Fabrique partir de raphia de haute qualit, cette pochette spacieuse dgage sophistication et style. Son design pur et sa couleur noire intemporelle en font l'accessoire parfait pour toutes les occasions, que ce soit une sortie dcontracte ou un vnement spcial en soire. | M16: Aggiungi un tocco di eleganza al tuo outfit con la nostra Clutch in Rafia Nera. Realizzata in rafia di alta qualit, questa clutch spaziosa emana sofisticazione e stile. Il suo design sobrio e il colore nero senza tempo la rendono l'accessorio perfetto per ogni occasione, che sia una gita informale o un evento serale speciale. | N16: Agrega un toque de elegancia a tu conjunto con nuestro Clutch de Rafia en Negro. Confeccionado con rafia de alta calidad, este clutch espacioso irradia sofisticación y estilo. Su o estilizado y su color negro atemporal lo convierten en el accesorio perfecto para cualquier ocasión, ya sea una salida casual o un evento especial por la noche. | O16: Verleihen Sie Ihrem Outfit mit unserer Raffia Clutch in Schwarz eine elegante Note. Hergestellt aus hochwertigem Raffia, strahlt diese geräumige Clutch Raffinesse und Stil aus. Ihr schlankes Design und die zeitlose schwarze Farbe machen sie zum perfekten Accessoire jeden Anlass, ob es sich um einen zwanglosen Ausflug oder ein besonderes Abendevent handelt. | P16: Black | Q16: Natural fibers | R16: Raphia | S16: Rafia | T16: Bast | U16: Rafia | Z16: 20 | AA16: cm | AB16: 32 | AC16: cm | AD16: 3 | AE16: cm | AG16: cm | AT16: Indonesia | BG16: https://bazarbizar.katanapim.com/content/images/thumbs/000/0000368_ba032bb-l.jpeg | CA16: Bazar Bizar | CB16: 2550 | CD16: 32 x 3 x 20 cm | CG16: https://bazarbizar.katanapim.com/content/images/thumbs/002/0023005_the-raffia-clutch-black-l.jpeg | DD16: Without pattern
A17: Lifestyle/Bags/Tote bags | B17: BA032BB-S | C17: =_xlfn.XLOOKUP(B17,Sheet1!A:A,Sheet1!A:A,) -> BA032BB-S | D17: Pochette en raphia noir | E17: Embrague de rafia negro | F17: Pochette in rafia nero | G17: Reissverschluss aus Bast schwarz | H17: 7438246082017 | I17: BA032 | J17: Bazar Bizar | L17: <p><span>Ajoutez une touche d'élégance à votre tenue avec notre Pochette en raphia noir. Fabriquée à partir de raphia de haute qualité, cette pochette compacte dégage sophistication et style. Son design épuré et sa couleur noire intemporelle en font l'accessoire parfait pour toutes les occasions, que ce soit une sortie décontractée ou un événement spécial en soirée.</span></p> | M17: <p><span>Aggiungi un tocco di eleganza al tuo outfit con la nostra Clutch in Rafia Nera. Realizzata in rafia di alta qualità, questa clutch compatta emana sofisticazione e stile. Il suo design sobrio e il colore nero senza tempo la rendono l'accessorio perfetto per ogni occasione, che sia una gita informale o un evento serale speciale.</span></p> | N17: <p><span>Agrega un toque de elegancia a tu conjunto con nuestro Clutch de Rafia en Negro. Confeccionado con rafia de alta calidad, este clutch compacto irradia sofisticación y estilo. Su diseño estilizado y su color negro atemporal lo convierten en el accesorio perfecto para cualquier ocasión, ya sea una salida casual o un evento especial por la noche.</span></p> | O17: <p><span>Verleihen Sie Ihrem Outfit mit unserer Raffia Clutch in Schwarz eine elegante Note. Hergestellt aus hochwertigem Raffia, strahlt diese kompakte Clutch Raffinesse und Stil aus. Ihr schlankes Design und die zeitlose schwarze Farbe machen sie zum perfekten Accessoire für jeden Anlass, ob es sich um einen zwanglosen Ausflug oder ein besonderes Abendevent handelt.</span></p> | P17: Black | R17: Raphia | S17: Rafia | T17: Raffia | U17: Rafia | V17: Noir | W17: Negro | X17: Nero | Y17: Schwarz | Z17: 15 | AA17: cm | AB17: 25 | AC17: cm | AD17: 3 | AE17: cm | AG17: cm | AT17: Indonesia | AZ17: Sea side | BG17: https://bazarbizar.katanapim.com/content/images/thumbs/0000369_ba032bb-s.jpeg | CD17: 25cm x 3cm x 15cm | CG17: https://bazarbizar.katanapim.com/content/images/thumbs/0009619_ba032bb-s_401.webp | CJ17: https://bazarbizar.katanapim.com/content/images/thumbs/0009618_ba032bb-s_400.webp | CM17: https://bazarbizar.katanapim.com/content/images/thumbs/0009620_ba032bb-s_402.webp | DD17: Without pattern
A18: Lifestyle/Bags/Tote bags | B18: BA032NB-L | C18: =_xlfn.XLOOKUP(B18,Sheet1!A:A,Sheet1!A:A,) -> BA032NB-L | D18: Pochette en raphia noir naturel | E18: Embrague de rafia natur negro | F18: Pochette in rafia naturale nero | G18: Reissverschluss aus Bast natur schwarz | H18: 7438246082024 | I18: BA032 | J18: Bazar Bizar | L18: <p><span>Rehaussez votre style de vie côtier avec notre Pochette en raphia naturel noir. Fabriquée à partir de raphia de haute qualité avec des accents noirs, cette pochette mêle élégance naturelle et charme côtier, incarnant l'essence de la sophistication en bord de mer. </span></p> <p><span>Son design épuré et sa combinaison de couleurs intemporelle en font l'accessoire parfait pour toutes les occasions, que ce soit une journée décontractée ou une soirée glamour.</span></p> | M18: <p><span>Eleva il tuo stile di vita costiero con la nostra Clutch in Rafia Naturale Nera. Realizzata in rafia di alta qualità con accenti neri, questa clutch fonde eleganza naturale con il fascino della costa, incarnando l'essenza della sofisticazione marittima. </span></p> <p><span>Il suo design sobrio e la combinazione di colori senza tempo la rendono l'accessorio perfetto per ogni occasione, che sia una giornata casual o una serata glamour.</span></p> | N18: <p><span>Eleva tu estilo de vida costero con nuestro Clutch de Rafia en Negro Natural. Confeccionado con rafia de alta calidad con acentos negros, este clutch combina elegancia natural con el encanto costero, encarnando la esencia de la sofisticación junto al mar. </span></p> <p><span>Su diseño estilizado y su combinación de colores atemporal lo convierten en el accesorio perfecto para cualquier ocasión, ya sea un día casual o una velada glamorosa.</span></p> | O18: <p><span>Verleihen Sie Ihrem Küstenlebensstil mit unserer Raffia Clutch in Natur Schwarz eine besondere Note. Hergestellt aus hochwertigem Raffia mit schwarzen Akzenten, vereint diese Clutch natürliche Eleganz mit dem Charme der Küste und verkörpert so die Essenz der Küstensophistication. </span></p> <p><span>Ihr schlankes Design und die zeitlose Farbkombination machen sie zum perfekten Accessoire für jeden Anlass, ob ein lässiger Tag oder ein glamouröser Abend.</span></p> | P18: Multicolour | R18: Raphia | S18: Rafia | T18: Raffia | U18: Rafia | V18: Naturel Noir | W18: Natural Negro | X18: Naturale Nero | Y18: Natur Schwarz | Z18: 20 | AA18: cm | AB18: 32 | AC18: cm | AD18: 3 | AE18: cm | AG18: cm | AT18: Indonesia | AZ18: Sea side | BG18: https://bazarbizar.katanapim.com/content/images/thumbs/0000370_ba032nb-l.jpeg | CD18: 32cm x 3cm x 20cm | CG18: https://bazarbizar.katanapim.com/content/images/thumbs/0009623_ba032nb-l_302.webp | CJ18: https://bazarbizar.katanapim.com/content/images/thumbs/0009627_ba032nb-l_306.webp | CM18: https://bazarbizar.katanapim.com/content/images/thumbs/0009624_ba032nb-l_303.webp | DD18: Without pattern
A19: Lifestyle/Bags/Tote bags | B19: BA032NB-S | C19: =_xlfn.XLOOKUP(B19,Sheet1!A:A,Sheet1!A:A,) -> BA032NB-S | H19: 7438246082031 | I19: BA032 | J19: Bazar Bizar | L19: <p><span>Rehaussez votre style de vie côtier avec notre Pochette en raphia naturel noir. Fabriquée à partir de raphia de haute qualité avec des accents noirs, cette pochette mêle élégance naturelle et charme côtier, incarnant l'essence de la sophistication en bord de mer. </span></p> <p><span>Son design épuré et sa combinaison de couleurs intemporelle en font l'accessoire parfait pour toutes les occasions, que ce soit une journée décontractée ou une soirée glamour.</span></p> | M19: <p><span>Eleva il tuo stile di vita costiero con la nostra Clutch in Rafia Naturale Nera. Realizzata in rafia di alta qualità con accenti neri, questa clutch fonde eleganza naturale con il fascino della costa, incarnando l'essenza della sofisticazione marittima. </span></p> <p><span>Il suo design sobrio e la combinazione di colori senza tempo la rendono l'accessorio perfetto per ogni occasione, che sia una giornata casual o una serata glamour.</span></p> | N19: <p><span>Eleva tu estilo de vida costero con nuestro Clutch de Rafia en Negro Natural. Confeccionado con rafia de alta calidad con acentos negros, este clutch combina elegancia natural con el encanto costero, encarnando la esencia de la sofisticación junto al mar. </span></p> <p><span>Su diseño estilizado y su combinación de colores atemporal lo convierten en el accesorio perfecto para cualquier ocasión, ya sea un día casual o una velada glamorosa.</span></p> | O19: <p>Verleihen Sie Ihrem Küstenlebensstil mit unserer Raffia Clutch in Natur Schwarz eine besondere Note. Hergestellt aus hochwertigem Raffia mit schwarzen Akzenten, vereint diese Clutch natürliche Eleganz mit dem Charme der Küste und verkörpert so die Essenz der Küstensophistication.</p> <p>Ihr schlankes Design und die zeitlose Farbkombination machen sie zum perfekten Accessoire für jeden Anlass, ob ein lässiger Tag oder ein glamouröser Abend.</p> | P19: Multicolour | R19: Raphia | S19: Rafia | T19: Raffia | U19: Rafia | V19: Naturel Noir | W19: Natural Negro | X19: Naturale Nero | Y19: Natur Schwarz | Z19: 15 | AA19: cm | AB19: 25 | AC19: cm | AD19: 3 | AE19: cm | AG19: cm | AT19: Indonesia | AZ19: Sea side | BG19: https://bazarbizar.katanapim.com/content/images/thumbs/0003395_ba032nb-s.webp | CD19: 25cm x 3cm x 15cm | CG19: https://bazarbizar.katanapim.com/content/images/thumbs/0013870_the-raffia-clutch-natural-black-s.jpeg | CJ19: https://bazarbizar.katanapim.com/content/images/thumbs/0013871_the-raffia-clutch-natural-black-s.jpeg | DD19: Without pattern
A20: Home textiles/Soft furnishings/Cushions and covers/Cushions | B20: BA035N-L-60x60 | C20: =_xlfn.XLOOKUP(B20,Sheet1!A:A,Sheet1!A:A,) -> BA035N-L-60x60 | H20: 7438246082055 | J20: Bazar Bizar | Z20: 10 | AA20: cm | AB20: 60 | AC20: cm | AD20: 60 | AE20: cm | BG20: https://cdn.webshopapp.com/shops/298158/files/426858122/file.jpg | BH20: https://cdn.webshopapp.com/shops/298158/files/426858111/file.jpg | CG20: https://cdn.webshopapp.com/shops/298158/files/329151415/file.jpg | CJ20: https://cdn.webshopapp.com/shops/298158/files/345210143/file.jpg | CM20: https://cdn.webshopapp.com/shops/298158/files/329151451/file.jpg
A21: Home textiles/Soft furnishings/Cushions and covers/Cushions | B21: BA035N-M-40x40 | C21: =_xlfn.XLOOKUP(B21,Sheet1!A:A,Sheet1!A:A,) -> BA035N-M-40x40 | H21: 7438246096007 | J21: Bazar Bizar | Z21: 10 | AA21: cm | AB21: 40 | AC21: cm | AD21: 40 | AE21: cm | BG21: https://cdn.webshopapp.com/shops/298158/files/426858103/file.jpg
A22: Decoration/Decoration objects/Busts and statues | B22: BA068S-S | C22: =_xlfn.XLOOKUP(B22,Sheet1!A:A,Sheet1!A:A,) -> BA068S-S | H22: 7438246171117 | J22: Bazar Bizar | L22: 0 | M22: 0 | N22: 0 | O22: 0 | P22: Silver | Q22: Resin | Z22: 7 | AA22: cm | AB22: 7 | AC22: cm | AD22: 9 | AE22: cm | AG22: cm | AT22: Indonesia | BG22: https://bazarbizar.katanapim.com/content/images/thumbs/001/0016152_the-mexican-sugar-skull-silver-s.jpeg | CA22: Bazar Bizar | CB22: 2550 | CD22: 7 x 9 x 7 cm | EX22: Sea
A23: Storage accessories/Utilitarian storages/Utilitarian boxes | B23: BA072BG-L | C23: =_xlfn.XLOOKUP(B23,Sheet1!A:A,Sheet1!A:A,) -> BA072BG-L | H23: 7438246276232 | J23: Bazar Bizar | K23: Beaded | Z23: 15 | AA23: cm | AB23: 20 | AC23: cm | AD23: 20 | AE23: cm
A24: Storage accessories/Utilitarian storages/Utilitarian boxes | B24: BA072BG-M | C24: =_xlfn.XLOOKUP(B24,Sheet1!A:A,Sheet1!A:A,) -> BA072BG-M | H24: 7438246276225 | J24: Bazar Bizar | K24: Beaded | Z24: 12 | AA24: cm | AB24: 15 | AC24: cm | AD24: 15 | AE24: cm
A25: Storage accessories/Utilitarian storages/Utilitarian boxes | B25: BA072BG-S | C25: =_xlfn.XLOOKUP(B25,Sheet1!A:A,Sheet1!A:A,) -> BA072BG-S | H25: 7438246276218 | J25: Bazar Bizar | K25: Beaded | Z25: 10 | AA25: cm | AB25: 12 | AC25: cm | AD25: 12 | AE25: cm
A26: Storage accessories/Decorative storages/Baskets | B26: BA072BG-SET3 | C26: =_xlfn.XLOOKUP(B26,Sheet1!A:A,Sheet1!A:A,) -> BA072BG-SET3 | H26: 7438246171131 | J26: Bazar Bizar | K26: Diamant
A27: Storage accessories/Decorative storages/Baskets | B27: BA073BG-L | C27: =_xlfn.XLOOKUP(B27,Sheet1!A:A,Sheet1!A:A,) -> BA073BG-L | H27: 7438246094010 | J27: Bazar Bizar | Z27: 30 | AA27: cm | AB27: 25 | AC27: cm | AD27: 25 | AE27: cm | AZ27: Sea side | BG27: https://cdn.webshopapp.com/shops/298158/files/416464275/file.jpg | FQ27: Artisanal
A28: Storage accessories/Decorative storages/Baskets | B28: BA073BG-M | C28: =_xlfn.XLOOKUP(B28,Sheet1!A:A,Sheet1!A:A,) -> BA073BG-M | H28: 7438246094027 | J28: Bazar Bizar | Z28: 25 | AA28: cm | AB28: 20 | AC28: cm | AD28: 20 | AE28: cm | AZ28: Sea side | BG28: https://cdn.webshopapp.com/shops/298158/files/416463848/file.jpg | FQ28: Artisanal
A29: Storage accessories/Utilitarian storages/Utilitarian boxes | B29: BA073BG-S | C29: =_xlfn.XLOOKUP(B29,Sheet1!A:A,Sheet1!A:A,) -> BA073BG-S | H29: 7438246094034 | J29: Bazar Bizar | K29: Beaded | Z29: 20 | AA29: cm | AB29: 15 | AC29: cm | AD29: 15 | AE29: cm
A30: Storage accessories/Decorative storages/Baskets | B30: BA073BG-SET3 | C30: =_xlfn.XLOOKUP(B30,Sheet1!A:A,Sheet1!A:A,) -> BA073BG-SET3 | H30: 7438246111144 | J30: Bazar Bizar | K30: Diamond high | Z30: 30 | AA30: cm | AB30: 25 | AC30: cm
A31: Storage accessories/Utilitarian storages/Utilitarian boxes | B31: BA073BW-L | C31: =_xlfn.XLOOKUP(B31,Sheet1!A:A,Sheet1!A:A,) -> BA073BW-L | H31: 7438246083069 | J31: Bazar Bizar | K31: Beaded | Z31: 30 | AA31: cm | AB31: 25 | AC31: cm | AD31: 25 | AE31: cm
A32: Storage accessories/Utilitarian storages/Utilitarian boxes | B32: BA073BW-M | C32: =_xlfn.XLOOKUP(B32,Sheet1!A:A,Sheet1!A:A,) -> BA073BW-M | H32: 7438246083052 | J32: Bazar Bizar | K32: Beaded | Z32: 25 | AA32: cm | AB32: 20 | AC32: cm | AD32: 20 | AE32: cm
A33: Storage accessories/Utilitarian storages/Utilitarian boxes | B33: BA073BW-S | C33: =_xlfn.XLOOKUP(B33,Sheet1!A:A,Sheet1!A:A,) -> BA073BW-S | H33: 7438246083045 | J33: Bazar Bizar | K33: Beaded | Z33: 20 | AA33: cm | AB33: 15 | AC33: cm | AD33: 15 | AE33: cm
A34: Storage accessories/Decorative storages/Baskets | B34: BA073BW-SET3 | C34: =_xlfn.XLOOKUP(B34,Sheet1!A:A,Sheet1!A:A,) -> BA073BW-SET3 | F34: Set di 3 cestini con perline in vacchetta bianca e nera | H34: 7438246110192 | J34: Bazar Bizar | K34: DIAMOND HIGH | Z34: 30 | AA34: cm | AB34: 25 | AC34: cm
A35: Decoration/Decoration objects/Figurines | B35: BA087-L | C35: =_xlfn.XLOOKUP(B35,Sheet1!A:A,Sheet1!A:A,) -> BA087-L | H35: 7438246083083 | J35: Bazar Bizar | K35: BLACK RIVER | Z35: 40 | AA35: cm | AB35: 30 | AC35: cm | AD35: 10 | AE35: cm | AT35: Indonesia | AZ35: Sea side | BG35: https://cdn.webshopapp.com/shops/298158/files/426860678/file.jpg | CG35: https://cdn.webshopapp.com/shops/298158/files/426860671/file.jpg | CJ35: https://cdn.webshopapp.com/shops/298158/files/426860665/file.jpg | CM35: https://cdn.webshopapp.com/shops/298158/files/426860661/file.jpg
A36: Decoration/Decoration objects/Figurines | B36: BA087-M | C36: =_xlfn.XLOOKUP(B36,Sheet1!A:A,Sheet1!A:A,) -> BA087-M | H36: 7438246083076 | J36: Bazar Bizar | K36: BLACK RIVER | Z36: 30 | AA36: cm | AB36: 20 | AC36: cm | AD36: 7 | AE36: cm | AT36: Indonesia | AZ36: Sea side | BG36: https://cdn.webshopapp.com/shops/298158/files/426860653/file.jpg | BH36: https://cdn.webshopapp.com/shops/298158/files/426860625/file.jpg | BI36: https://cdn.webshopapp.com/shops/298158/files/426860620/file.jpg | BJ36: https://cdn.webshopapp.com/shops/298158/files/426860609/file.jpg | CG36: https://cdn.webshopapp.com/shops/298158/files/426860645/file.jpg | CJ36: https://cdn.webshopapp.com/shops/298158/files/426860639/file.jpg | CM36: https://cdn.webshopapp.com/shops/298158/files/426860633/file.jpg
A37: Lifestyle/Gadgets/Keychains | B37: BA132W | C37: =_xlfn.XLOOKUP(B37,Sheet1!A:A,Sheet1!A:A,) -> BA132W | D37: Porte-clés coton et coquillage blanc 4x4x15cm | E37: Llavero de algodón y concha en blanco 4x4x15 cm | F37: Portachiavi in cotone e conchiglia bianco 4x4x15 cm | G37: Schlüsselanhänger aus Baumwolle und Muscheln in Weiß 4x4x15cm | H37: 7438246085025 | I37: BA132 | J37: Bazar Bizar | K37: Cowrie | L37: Luxe bohème avec une touche côtière avec ce magnifique porte-clés orné de coquillages et terminé par un pompon en coton. Accrochez-le à un crochet mural, sur une poignée de porte, un rideau, utilisez-le pour la décoration ou suspendez-le à notre porte-clés en métal. Un petit accessoire fabuleux et une excellente idée cadeau. Chaque pièce est unique. | M37: Questo bellissimo portachiavi, decorato con conchiglie e rifinito con una nappa di cotone, è un lusso bohémien con un tocco costiero. Appendilo a un gancio, a una maniglia, a una tenda o al nostro portachiavi in metallo. Un piccolo accessorio favoloso e un'ottima idea regalo. Ogni pezzo è unico. | N37: Este precioso llavero, decorado con conchas y acabado con una borla de algodón, aporta lujo bohemio con un toque costero. Cuélgalo en un gancho, en la puerta de entrada, en una cortina o en nuestro porta-llaveros metálico. Es un accesorio pequeño y bonito, una gran idea de regalo. Cada pieza es única. | O37: Boho-Luxus mit einem Hauch Küste mit diesem schönen Schlüsselanhänger, verziert mit Muscheln und einer Baumwollquaste. Hängen Sie ihn an einen Wandhaken, eine Türklinke, einen Vorhang oder an unseren Metallschlüsselhalter. Ein kleines, schönes Accessoire und eine tolle Geschenkidee. Jedes Stück ist einzigartig. | P37: White | Q37: Cotton | Z37: 15 | AA37: cm | AB37: 4 | AC37: cm | AD37: 4 | AE37: cm | AG37: cm | AT37: Indonesia | BG37: https://bazarbizar.katanapim.com/content/images/thumbs/002/0028595_ba132w.jpeg | CA37: Bazar Bizar | CB37: 2550 | CD37: 4 x 4 x 15 cm | CG37: https://bazarbizar.katanapim.com/content/images/thumbs/002/0020465_the-cowrie-tassel-keychain-white.jpeg | CJ37: https://bazarbizar.katanapim.com/content/images/thumbs/002/0020468_the-cowrie-tassel-keychain-white.jpeg | CM37: https://bazarbizar.katanapim.com/content/images/thumbs/002/0020466_the-cowrie-tassel-keychain-white.jpeg
A38: Decoration/Wall decoration/Decorative plates | B38: BA148W-52 | C38: =_xlfn.XLOOKUP(B38,Sheet1!A:A,Sheet1!A:A,) -> BA148W-52 | H38: 7438246086015 | J38: Bazar Bizar | K38: Tree of life | Z38: 52 | AA38: cm | AB38: 52 | AC38: cm | AD38: 2 | AE38: cm
A39: Decoration/Candles and fragrance/Candles/Candle | B39: BA150B-N | C39: =_xlfn.XLOOKUP(B39,Sheet1!A:A,Sheet1!A:A,) -> BA150B-N | D39: Bougeoir en noix de coco naturel | E39: Portavelas de coco | F39: Portacandele in cocco | G39: Kerzenhalter aus natürlicher Kokosnuss | H39: 7438246094096 | K39: Coconut | L39: Chaque année, des millions de coquilles de noix de coco sont jetées comme des déchets. Nous leur donnons une nouvelle vie sous la forme d'un magnifique bougeoir dont vous pourrez profiter tous les jours. Chaque bougeoir en noix de coco est fabriqué à la main et magnifiquement conçu par notre équipe d'artisans qualifiés à Bali. Décorez votre maison et inspirez-vous et inspirez les autres à accueillir le nouveau. Vous êtes la lumière !Ce sont de vraies noix de coco - la forme et la taille peuvent varier. De légères marques noires sur ce matériau sont inévitables et considérées comme faisant partie de l'attrait du produit. | N39: Cada año se desechan millones de cáscaras de coco residuales. Nosotros, en cambio, les damos una segunda vida y los convertimos en hermosos portavelas que se pueden disfrutar todos los días. Cada portavelas de coco es elaborado a mano y diseñado por nuestro equipo de hábiles artesanos balineses. Decora tu casa e inspira a los demás con tu bonito estilo de decoración costero. Estos son cocos reales: la forma y los tamaños pueden variar. Las ligeras marcas negras en este material son inevitables y se consideran parte del atractivo del producto. | P39: Beige | Z39: 11 | AA39: cm | AC39: cm | AE39: cm | AZ39: Sea side | BG39: https://cdn.webshopapp.com/shops/298158/files/453123176/file.jpg
A40: Decoration/Candles and fragrance/Candle jar | B40: BA150D-Br | C40: =_xlfn.XLOOKUP(B40,Sheet1!A:A,Sheet1!A:A,) -> BA150D-Br | H40: 7438246086053 | J40: Bazar Bizar | K40: Coconut star
A41: Decoration/Decoration objects/Busts and statues | B41: BA152G-L | C41: =_xlfn.XLOOKUP(B41,Sheet1!A:A,Sheet1!A:A,) -> BA152G-L | H41: 7438246169190 | J41: Bazar Bizar | L41: 0 | M41: 0 | N41: 0 | O41: 0 | P41: Gold | Q41: Resin | Z41: 13 | AA41: cm | AB41: 16 | AC41: cm | AD41: 19 | AE41: cm | AG41: cm | AT41: Indonesia | BG41: https://bazarbizar.katanapim.com/content/images/thumbs/001/0016133_the-resin-skull-head-gold-s.jpeg | CA41: Bazar Bizar | CB41: 2550 | CD41: 16 x 19 x 13 cm | EX41: Sea
A42: Decoration/Decoration objects/Busts and statues | B42: BA152S-L | C42: =_xlfn.XLOOKUP(B42,Sheet1!A:A,Sheet1!A:A,) -> BA152S-L | H42: 7438246170127 | J42: Bazar Bizar | L42: 0 | M42: 0 | N42: 0 | O42: 0 | P42: Silver | Q42: Resin | Z42: 13 | AA42: cm | AB42: 16 | AC42: cm | AD42: 19 | AE42: cm | AG42: cm | AT42: Indonesia | BG42: https://bazarbizar.katanapim.com/content/images/thumbs/001/0016094_the-resin-skull-head-silver-l.jpeg | CA42: Bazar Bizar | CB42: 2550 | CD42: 16 x 19 x 13 cm | EX42: Sea
A43: Decoration/Decoration objects/Busts and statues | B43: BA152S-S | C43: =_xlfn.XLOOKUP(B43,Sheet1!A:A,Sheet1!A:A,) -> BA152S-S | H43: 7438246170141 | J43: Bazar Bizar | L43: 0 | M43: 0 | N43: 0 | O43: 0 | P43: Silver | Q43: Resin | Z43: 7 | AA43: cm | AB43: 7 | AC43: cm | AD43: 9 | AE43: cm | AG43: cm | AT43: Indonesia | BG43: https://bazarbizar.katanapim.com/content/images/thumbs/001/0016094_the-resin-skull-head-silver-l.jpeg | CA43: Bazar Bizar | CB43: 2550 | CD43: 7 x 9 x 7 cm | EX43: Sea
A44: Lifestyle/Gadgets/Keychains | B44: BA159B | C44: =_xlfn.XLOOKUP(B44,Sheet1!A:A,Sheet1!A:A,) -> BA159B | D44: Porte-clés coton et coquillage noir 4x4x15cm | E44: Llavero de algodón y concha en negro 4x4x15 cm | F44: Portachiavi in cotone e conchiglia nero 4x4x15 cm | G44: Schlüsselanhänger aus Baumwolle und Muscheln in schwarz 4x4x15cm | H44: 7438246086077 | I44: BA159 | J44: Bazar Bizar | K44: Pompom | L44: Confectionné en coton doux, le porte-clés Pompom présente un charmant design en pompon noir élégant. Cet accessoire ajoute une touche ludique à vos essentiels, qu'il soit attaché à vos clés, votre sac ou votre sac à dos. Sa texture moelleuse et sa couleur noire intemporelle apportent sophistication et style à votre quotidien. | M44: Realizzato in morbido cotone, il portachiavi Pompom presenta un delizioso design a pompon in elegante nero. Questo accessorio aggiunge un tocco giocoso agli oggetti essenziali, sia che sia attaccato alle chiavi, alla borsa o allo zaino. La sua consistenza soffice e il colore nero senza tempo portano raffinatezza e stile nella vita quotidiana. | N44: Elaborado en suave algodón, el llavero Pompom presenta un encantador diseño de pompones en un elegante negro. Este accesorio añade un toque lúdico a tus elementos esenciales, ya sea que esté unido a tus llaves, bolso o mochila. Su textura esponjosa y su color negro atemporal aportan sofisticación y estilo a tu día a día. | O44: Hergestellt aus weicher Baumwolle, präsentiert der Pompom-Schlüsselanhänger ein entzückendes Pompon-Design in elegantem Schwarz. Dieses charmante Accessoire verleiht Ihren Essentials eine verspielte Note, ob es an Schlüsseln, Tasche oder Rucksack befestigt ist. Seine flauschige Textur und die zeitlose schwarze Farbe bringen Eleganz und Stil in Ihren Alltag. | P44: Black | Q44: Cotton | Z44: 15 | AA44: cm | AB44: 4 | AC44: cm | AD44: 4 | AE44: cm | AG44: cm | AT44: Indonesia | BG44: https://bazarbizar.katanapim.com/content/images/thumbs/002/0028593_ba159b.jpeg | CA44: Bazar Bizar | CB44: 2550 | CD44: 4 x 4 x 15 cm | CG44: https://bazarbizar.katanapim.com/content/images/thumbs/002/0023078_the-pompom-keychain-black.jpeg | CJ44: https://bazarbizar.katanapim.com/content/images/thumbs/002/0023077_the-pompom-keychain-black.jpeg
A45: Lifestyle/Gadgets/Keychains | B45: BA159M | C45: =_xlfn.XLOOKUP(B45,Sheet1!A:A,Sheet1!A:A,) -> BA159M | D45: Porte-clés coton et coquillage moka 4x4x15cm | E45: Llavero de algodón y concha en moka 4x4x15 cm | F45: Portachiavi in cotone e conchiglia moka 4x4x15 cm | G45: Schlüsselanhänger aus Baumwolle und Muscheln in Mokka 4x4x15cm | H45: 7438246086091 | I45: BA159 | J45: Bazar Bizar | K45: Pompom | L45: Confectionné en coton doux, le Porte-Clés Pompom arbore un charmant design de pompon dans une riche couleur moka. Cet accessoire charmant ajoute une touche ludique à vos essentiels, qu'il soit attaché à vos clés, votre sac ou votre sac à dos. Laissez sa texture moelleuse et sa profonde couleur moka apporter chaleur et style à votre quotidien. | M45: Realizzato in morbido cotone, il Portachiavi Pompom presenta un delizioso design a pompon in un ricco color moca. Questo accessorio affascinante aggiunge un tocco giocoso ai tuoi elementi essenziali, che sia attaccato alle tue chiavi, borsa o zaino. Lascia che la sua consistenza soffice e il suo profondo colore moca portino calore e stile al tuo quotidiano. | N45: Elaborado en suave algodón, el Llavero Pompom presenta un encantador o de pompones en un rico color moca. Este accesorio encantador añade un toque lúdico a tus elementos esenciales, ya sea que est unido a tus llaves, bolso o mochila. Deja que su textura esponjosa y su profundo color moca aporten calidez y estilo a tu día a día. | O45: Hergestellt aus weicher Baumwolle, präsentiert der Pompom Schlsselanhänger ein entzckendes Pompon-Design in einem reichen Mokka-Farbton. Dieses charmante Accessoire verleiht Ihren Essentials eine verspielte Note, ob es an Ihren Schlsseln, Ihrer Tasche oder Ihrem Rucksack befestigt ist. Lassen Sie seine flauschige Textur und seine tiefe Mokka-Farbe Wärme und Stil in Ihren Alltag bringen. | P45: Brown | Q45: Cotton | Z45: 15 | AA45: cm | AB45: 4 | AC45: cm | AD45: 4 | AE45: cm | AG45: cm | AT45: Indonesia | BG45: https://bazarbizar.katanapim.com/content/images/thumbs/002/0028591_ba159m.jpeg | CA45: Bazar Bizar | CB45: 2550 | CD45: 4 x 4 x 15 cm | CG45: https://bazarbizar.katanapim.com/content/images/thumbs/002/0022977_the-pompom-keychain-mocca.jpeg
A46: Home textiles/Table linen/Placemats | B46: BA161B | C46: =_xlfn.XLOOKUP(B46,Sheet1!A:A,Sheet1!A:A,) -> BA161B | H46: 7438246095031 | J46: Bazar Bizar | K46: Fringe | Z46: 1 | AA46: cm | AB46: 45 | AC46: cm
A47: Indoor lighting/Indoor pendant lights | B47: BA171N-XL-65x105 | C47: =_xlfn.XLOOKUP(B47,Sheet1!A:A,Sheet1!A:A,) -> BA171N-XL-65x105 | D47: L'Abat-jour Kendi - Naturel - XL | H47: 6097309394316 | J47: Bazar Bizar | L47: Il y a quelque chose de réconfortant dans les courbes douces de la suspension Kendi. Tressée à la main en rotin naturel, sa forme aérée apporte un rythme apaisant à la pièce, comme une brise légère passant par une fenêtre ouverte. Sa silhouette sculpturale ajoute de la hauteur et du caractère sans alourdir l’espace, que ce soit suspendue dans un hall à plafond haut ou au-dessus d’une table à manger. La texture joue avec la lumière, dessinant des motifs subtils qui évoluent au fil de la journée. Il s’agit d’un abat-jour uniquement. Complétez votre installation avec une suspension ou un raccord à brancher disponible dans notre boutique. | N47: La Lampara Colgante Kendi aporta un toque de encanto rústico a cualquier habitación, gracias a su construcción de ratán tejido a mano. Los intrincados patrones añaden un toque único, combinando la belleza de la naturaleza con una estética moderna. Dé rienda suelta a su creatividad: cuélguelo del techo para darle un aspecto elegante o colóquelo en el suelo para darle un toque distintivo. ¡Tú eliges! Esta pantalla de lámpara no tiene cableado eléctrico ni enchufes. Vendemos estos accesorios por separado, tanto montados en el techo como con enchufe. Busque un accesorio en nuestra tienda y seleccione el aspecto y el tipo que desee. | P47: Beige | Q47: Rattan | V47: Naturel | W47: Natural | X47: Naturale | Y47: Natur | Z47: 105 | AA47: cm | AB47: 65 | AC47: cm | AD47: 65 | AE47: cm | AG47: cm | AT47: Indonesia | AZ47: Sea side | BE47: Hand washable | BG47: https://media-prod-eu-1.mirakl.net/SOURCE/a31bb60d761742c4b56fb81dbd0232db | BH47: https://media-prod-eu-1.mirakl.net/SOURCE/9817f819d22c4c5f91bfcb71f5fa5489 | BI47: https://media-prod-eu-1.mirakl.net/SOURCE/2bd04cf798234ffd8ff2d03a1b1488fb | BJ47: https://media-prod-eu-1.mirakl.net/SOURCE/ae5c653c0f714b8fa025cd769b4a109d | BK47: https://media-prod-eu-1.mirakl.net/SOURCE/1d9db825268e4a4dbacb82647d0c8be4 | BL47: https://media-prod-eu-1.mirakl.net/SOURCE/f11ada60b3954598a11361fe2bc55e3d | CG47: https://media-prod-eu-1.mirakl.net/SOURCE/c67428f4a35848c6936147a6d1981149 | CJ47: https://media-prod-eu-1.mirakl.net/SOURCE/ce234dfdfdc340aea8e0b62e4e16c844 | CM47: https://media-prod-eu-1.mirakl.net/SOURCE/d73f73116c1d4665b4f5d94aaa05e9f7 | CN47: w | CP47: Oui | CR47: Sí | CT47: Sì | CV47: Ja | EY47: Bulb not supplied | FE47: Electric
A48: Indoor lighting/Indoor pendant lights | B48: BA172B-L-60x60 | C48: =_xlfn.XLOOKUP(B48,Sheet1!A:A,Sheet1!A:A,) -> BA172B-L-60x60 | H48: 7438246111168 | J48: Bazar Bizar | K48: Bottle | Z48: 60 | AA48: cm | AB48: 60 | AC48: cm
A49: Indoor lighting/Indoor pendant lights | B49: BA172B-M-50x50 | C49: =_xlfn.XLOOKUP(B49,Sheet1!A:A,Sheet1!A:A,) -> BA172B-M-50x50 | H49: 7438246111151 | J49: Bazar Bizar | K49: Bottle
A50: Indoor lighting/Indoor pendant lights | B50: BA172N-L-60x60 | C50: =_xlfn.XLOOKUP(B50,Sheet1!A:A,Sheet1!A:A,) -> BA172N-L-60x60 | H50: 7438246087098 | J50: Bazar Bizar | K50: Bottle
A51: Indoor lighting/Indoor pendant lights | B51: BA172N-M-50x50 | C51: =_xlfn.XLOOKUP(B51,Sheet1!A:A,Sheet1!A:A,) -> BA172N-M-50x50 | D51: Suspension rotin marron 50x50x50cm | E51: Lámpara colgante de ratán en marrón 50x50x50 cm | F51: Lampada a sospensione in rattan marrone 50x50x50 cm | G51: Pendelleuchte aus Rattan in braun, 50 x 50 x 50 cm | H51: 7438246087081 | I51: BA172 | J51: Bazar Bizar | K51: Bottle | L51: <p>Laissez-vous porter par une atmosphère détendue et ensoleillée avec cet abat-jour en rotin magnifiquement façonné à la main. Son tissage aéré et sa teinte naturelle douce apportent chaleur et lumière délicate à votre intérieur, créant une touche côtière.</p> <p>Qu’il illumine une chambre, ajoute du charme à une chambre d’enfant ou adoucisse l’ambiance d’une terrasse couverte, ce luminaire suspendu offre une élégance organique toute en simplicité. Associez-le à une suspension ou une douille à brancher de notre boutique pour finaliser le style.</p> <p>Chaque pièce est soigneusement fabriquée à la main avec des matériaux naturels, de légères variations de couleur, de tissage ou de forme peuvent apparaître, conférant à votre lampe une personnalité unique.</p> <p><span>Ce produit est conçu uniquement pour une utilisation en intérieur. Une utilisation en extérieur, même dans des zones couvertes, peut entraîner des dommages dus à l’humidité ou aux conditions météorologiques et n’est pas couverte par la garantie. Les images montrant une utilisation en extérieur sont uniquement destinées à des fins de mise en scène.</span></p> | M51: <p>Immergiti in un’atmosfera rilassata e baciata dal sole con questo paralume in rattan splendidamente realizzato a mano. La sua trama ariosa e il colore naturale tenue portano calore e luce soffusa nei tuoi ambienti, regalando un tocco di costa ovunque venga appeso.</p> <p>Che illumini una camera da letto, aggiunga fascino a una stanza per bambini o ammorbidisca l’atmosfera su una veranda coperta, questa sospensione offre un’eleganza organica e senza sforzo. Abbinala a un attacco a soffitto o a spina disponibile nel nostro shop per completare il look.</p> <p>Ogni pezzo è accuratamente realizzato a mano con materiali naturali, quindi piccole variazioni nel colore, nell’intreccio o nella forma possono comparire e donare alla tua lampada una personalità autentica.</p> <p><span>Questo prodotto è progettato esclusivamente per uso interno. L’utilizzo all’esterno, anche in aree coperte, può causare danni dovuti all’umidità o alle condizioni atmosferiche e non è coperto da garanzia. Le immagini che mostrano l’uso all’esterno sono solo a scopo illustrativo.</span></p> | N51: <p>Déjate llevar por una atmósfera relajada y soleada con esta hermosa pantalla de lámpara de ratán hecha a mano. Su trenzado ligero y color natural suave invitan a la calidez y a una luz suave que llena el espacio con un aire costero.</p> <p>Ya sea que ilumine un dormitorio, aporte encanto a una habitación infantil o suavice el ambiente en una terraza cubierta, esta lámpara colgante irradia una elegancia orgánica y sin esfuerzo. Combínala con una instalación de techo o enchufe de nuestra tienda para completar el look.</p> <p>Cada pieza está cuidadosamente elaborada a mano con materiales naturales, por lo que pueden aparecer ligeras variaciones en el color, el trenzado o la forma que le darán a tu lámpara una personalidad única.</p> <p><span>Este producto está diseñado únicamente para uso en interiores. El uso en exteriores, incluso en áreas cubiertas, puede causar daños debido a la humedad o a las condiciones climáticas y no está cubierto por la garantía. Las imágenes que muestran uso en exteriores son solo para fines de estilismo.</span></p> | O51: <p>Tauche ein in eine entspannte, sonnenverwöhnte Atmosphäre mit diesem wunderschön handgefertigten Lampenschirm aus Rattan. Das luftige Flechtwerk und der sanfte Naturton bringen Wärme und weiches Licht in deinen Raum und verleihen ihm überall ein Gefühl von Küstennähe.</p> <p>Ob im Schlafzimmer, im Kinderzimmer oder auf einer überdachten Terrasse, diese Hängelampe verströmt eine lässige, natürliche Eleganz. Kombiniere sie mit einer passenden Decken- oder Steckfassung aus unserem Shop, um den Look zu vervollständigen.</p> <p>Jedes Stück wird sorgfältig von Hand aus natürlichen Materialien gefertigt, sodass kleine Unterschiede in Farbe, Geflecht oder Form entstehen können, was der Lampe ihren individuellen Charakter verleiht.</p> <p><span>Dieses Produkt ist ausschließlich für den Innenbereich vorgesehen. Die Verwendung im Außenbereich, auch in überdachten Bereichen, kann durch Feuchtigkeit oder Witterungseinflüsse Schäden verursachen und ist nicht durch die Garantie abgedeckt. Bilder, die eine Nutzung im Außenbereich zeigen, dienen ausschließlich zu Stylingzwecken.</span></p> | P51: Beige | Q51: Rattan | Z51: 50 | AA51: cm | AB51: 50 | AC51: cm | AD51: 50 | AE51: cm | AG51: cm | AT51: Indonesia | BG51: https://bazarbizar.katanapim.com/content/images/thumbs/002/0028844_ba172n-m-50x50_2.jpeg | CA51: Bazar Bizar | CB51: 2550 | CD51: 50 x 50 x 50 cm | CG51: https://bazarbizar.katanapim.com/content/images/thumbs/002/0029288_ba172n-m-50x50_300.jpeg | CH51: E27 | CJ51: https://bazarbizar.katanapim.com/content/images/thumbs/002/0029290_ba172n-m-50x50_302.jpeg | CM51: https://bazarbizar.katanapim.com/content/images/thumbs/002/0029291_ba172n-m-50x50_303.jpeg | CN51: w | EY51: Battery not supplied | FE51: Electric | FN51: 1 bulb
A52: Decoration/Decoration objects/Figurines | B52: BA173W-L | C52: =_xlfn.XLOOKUP(B52,Sheet1!A:A,Sheet1!A:A,) -> BA173W-L | H52: 7438246097042 | J52: Bazar Bizar | K52: Papua | Z52: 50 | AA52: cm | AB52: 45 | AC52: cm
A53: Decoration/Decoration objects/Figurines | B53: BA173W-XXL | C53: =_xlfn.XLOOKUP(B53,Sheet1!A:A,Sheet1!A:A,) -> BA173W-XXL | G53: Statue aus Muschel | H53: 7438246113162 | J53: Bazar Bizar | Z53: 110 | AA53: cm | AB53: 80 | AC53: cm | AD53: 80 | AE53: cm | AZ53: Sea side | BG53: https://cdn.webshopapp.com/shops/298158/files/392305441/file.jpg
A54: Decoration/Decoration objects/Figurines | B54: BA175B | C54: =_xlfn.XLOOKUP(B54,Sheet1!A:A,Sheet1!A:A,) -> BA175B | G54: Statuenhalskette aus schwarzen Muscheln auf einer Metallbasis. | H54: 7438246088026 | J54: Bazar Bizar | K54: TIGER COWRIE | P54: Black | Q54: Natural fibers | Z54: 35 | AA54: cm | AB54: 30 | AC54: cm
A55: Decoration/Decoration objects/Busts and statues | B55: BA191W-M | C55: =_xlfn.XLOOKUP(B55,Sheet1!A:A,Sheet1!A:A,) -> BA191W-M | D55: Objet décoratif Marbre Blanc 20x9x35cm | E55: Objeto decorativo de mármol en blanco 20x9x35 cm | F55: Oggetto decorativo in marmo bianco 20x9x35 cm | G55: Dekorationsgegenstand aus Marmor in Weiß 20x9x35cm | H55: 7438246090074 | I55: BA191 | J55: Bazar Bizar | K55: Marble | L55: Notre disque en marbre massif sur support personnalisé apporte une simplicité élégante à une table, une étagère ou un bureau. Le marbre ajoute toujours une touche chic à votre intérieur. Un vrai gagnant pour ceux qui recherchent un affichage décoratif avec un design élégant et facile. | M55: Il nostro disco di marmo solido su supporto personalizzato, porta una semplicit elegante ad un tavolo, scaffale o scrivania. Il marmo aggiunge sempre un tocco chic ai tuoi interni. Un vero elemento vincitore per chi cerca un display decorativo con un design elegante e semplice. | N55: Nuestro disco de mármol macizo sobre un pedestal hecho a medida, aporta una elegante simplicidad a una mesa, estantería o escritorio. El mármol siempre añade un toque refinado a cualquier interior del hogar. Una pieza única para aquellos que buscan un elemento decorativo con un o especial y fácil de combinar. | O55: Unsere massive Marmorscheibe auf einem maßgefertigten Ständer verleiht einem Tisch, Regal oder Schreibtisch eine schlichte Eleganz. Marmor fgt immer eine schicke Note zu Ihrem Haus Interieur. Ein echter Gewinner alle, die nach einem dekorativen Display mit einem stilvollen und einfachen Design suchen. | P55: White | Q55: Marble | Z55: 35 | AA55: cm | AB55: 20 | AC55: cm | AD55: 9 | AE55: cm | AG55: cm | AT55: Indonesia | BG55: https://bazarbizar.katanapim.com/content/images/thumbs/002/0028167_ba191w-m.jpeg | CA55: Bazar Bizar | CB55: 2550 | CD55: 20 x 9 x 35 cm | CG55: https://bazarbizar.katanapim.com/content/images/thumbs/001/0019142_the-marble-disc-on-stand-white-m.jpeg | CJ55: https://bazarbizar.katanapim.com/content/images/thumbs/001/0019143_the-marble-disc-on-stand-white-m.jpeg | CM55: https://bazarbizar.katanapim.com/content/images/thumbs/001/0019141_the-marble-disc-on-stand-white-m.jpeg | EX55: Sea
A56: Decoration/Decoration objects/Busts and statues | B56: BA191W-S | C56: =_xlfn.XLOOKUP(B56,Sheet1!A:A,Sheet1!A:A,) -> BA191W-S | D56: Objet décoratif Marbre Blanc 15x7x25cm | E56: Objeto decorativo de mármol en blanco 15x7x25 cm | F56: Oggetto decorativo in marmo bianco 15x7x25 cm | G56: Dekorationsgegenstand aus Marmor in Weiß 15 x 7 x 25 cm | H56: 7438246090067 | I56: BA191 | J56: Bazar Bizar | K56: Marble | L56: Notre disque en marbre massif sur support, personnalisé, apporte une simplicité élégante à une table, une étagère ou un bureau. Le marbre ajoute toujours une touche chic à votre intérieur. Un vrai gagnant pour ceux qui recherchent un affichage décoratif avec un design élégant et facile. | M56: Il nostro disco di marmo solido su supporto personalizzato, porta una semplicit elegante ad un tavolo, scaffale o scrivania. Il marmo aggiunge sempre un tocco chic ai tuoi interni. Un vero elemento vincitore per chi cerca un display decorativo con un design elegante e semplice. | N56: Nuestro disco de mármol macizo sobre un pedestal hecho a medida, aporta una elegante simplicidad a una mesa, estantería o escritorio. El mármol siempre añade un toque refinado a cualquier interior del hogar. Una pieza única para aquellos que buscan un elemento decorativo con un o especial y fácil de combinar. | O56: Unsere massive Marmorscheibe auf einem maßgefertigten Ständer verleiht einem Tisch, Regal oder Schreibtisch eine schlichte Eleganz. Marmor verleiht Ihrer Inneneinrichtung immer eine schicke Note. Ein echter Gewinner alle, die nach einem dekorativen Display mit einem stilvollen und einfachen Design suchen. | P56: White | Q56: Marble | Z56: 25 | AA56: cm | AB56: 15 | AC56: cm | AD56: 7 | AE56: cm | AG56: cm | AT56: Indonesia | BG56: https://bazarbizar.katanapim.com/content/images/thumbs/002/0028170_ba191w-s.jpeg | CA56: Bazar Bizar | CB56: 2550 | CD56: 15 x 7 x 25 cm | CG56: https://bazarbizar.katanapim.com/content/images/thumbs/002/0020768_the-marble-disc-on-stand-white-s.jpeg | CJ56: https://bazarbizar.katanapim.com/content/images/thumbs/002/0020769_the-marble-disc-on-stand-white-s.jpeg | CM56: https://bazarbizar.katanapim.com/content/images/thumbs/002/0020766_the-marble-disc-on-stand-white-s.jpeg | EX56: Sea
A57: Storage accessories/Decorative storages/Baskets | B57: BABE001B-L | C57: =_xlfn.XLOOKUP(B57,Sheet1!A:A,Sheet1!A:A,) -> BABE001B-L | D57: Panier perles noir 23x23x21cm | E57: Cesta de cuentas en negro 23x23x21 cm | F57: Cesto in perline nero 23x23x21 cm | G57: Korb aus Perlen in schwarz, 23 x 23 x 21 cm | H57: 7438246040055 | I57: BABE001 | J57: Bazar Bizar | K57: Beaded | L57: Tombez amoureux de notre délicat panier perlé fait main, au bel esthétisme qui embellira chaque coin de la maison, que ce soit une chambre, une salle de bain, un dressing, une cuisine ou un salon. Ou placez-les simplement sur une étagère comme un bel objet déco bohème chic. Avec ces paniers, vous pouvez facilement ranger articles de toilette, maquillage ou petits objets dans n’importe quelle pièce. Un véritable accroche-regard pour votre intérieur! | M57: Innamorati del nostro delicato cestino di perline fatto a mano che ha un’estetica raffinata e abbellirà qualsiasi angolo della casa, che sia camera da letto, bagno, cabina armadio, cucina o soggiorno. Oppure posizionalo semplicemente su una mensola come un bellissimo oggetto decorativo boho chic. Con questi cestini puoi facilmente riporre articoli da toeletta, trucchi o piccoli oggetti in qualsiasi stanza. Un vero colpo d’occhio per il tuo interno! | N57: Enamórate de nuestra delicada cesta hecha a mano con cuentas, con una estética hermosa que embellecerá cualquier rincón de la casa, ya sea un dormitorio, baño, vestidor, cocina o sala de estar. O simplemente colócala en una estantería como un hermoso objeto decorativo boho chic. Con estas cestas puedes guardar fácilmente artículos de tocador, maquillaje o pequeños objetos en cualquier habitación. ¡Un verdadero atractivo para tu hogar! | O57: Verlieben Sie sich in unseren zarten handgefertigten Perlenkorb mit einer wunderschönen Ästhetik, der jede Ecke des Hauses verschönert, sei es Schlafzimmer, Bad, Ankleide, Küche oder Wohnzimmer. Oder stellen Sie ihn einfach als schönes Boho-Chic-Dekoobjekt ins Regal. Mit diesen Körben können Sie Toilettenartikel, Make-up oder Kleinigkeiten in jedem Raum einfach verstauen. Ein echter Hingucker für Ihr Zuhause! | P57: Black | Q57: Glass | Z57: 21 | AA57: cm | AB57: 23 | AC57: cm | AD57: 23 | AE57: cm | AG57: cm | AT57: Indonesia | BG57: https://bazarbizar.katanapim.com/content/images/thumbs/002/0027746_babe001b-l.jpeg | CA57: Bazar Bizar | CB57: 2550 | CD57: 23 x 23 x 21 cm | FA57: Square | FQ57: Artisanal
A58: Tableware and kitchen accessories/Table accessories/Bread and fruit baskets | B58: BABE002B-L | C58: =_xlfn.XLOOKUP(B58,Sheet1!A:A,Sheet1!A:A,) -> BABE002B-L | H58: 7438246040093 | J58: Bazar Bizar | K58: Beaded | Z58: 10 | AA58: cm | AB58: 30 | AC58: cm
A59: Storage accessories/Decorative storages/Baskets | B59: BABE004B-S | C59: =_xlfn.XLOOKUP(B59,Sheet1!A:A,Sheet1!A:A,) -> BABE004B-S | D59: Panier de rangement en perles noir 10x10 cm | E59: Cesta de cuentas negro | F59: Cesto contenitore in perline nere 10x10 cm | G59: Korb aus Perlen schwarz | H59: 7438246041021 | I59: BABE004 | J59: Bazar Bizar | K59: Beaded | L59: Tombez sous le charme de notre délicate boîte en perles faite main avec couvercle, dont l’esthétique ravissante embellira chaque recoin de votre maison, que ce soit dans une chambre, une salle de bain, un dressing ou un salon. Ou placez-la simplement sur une étagère comme objet décoratif boho chic. Avec ces boîtes, vous pouvez facilement ranger produits de toilette, maquillage ou petits objets dans n’importe quelle pièce. Un véritable accroche-regard pour votre intérieur ! | M59: Innamorati della nostra delicata scatola con perline fatta a mano con coperchio, dal design incantevole che valorizzerà ogni angolo della casa, sia in camera da letto, in bagno, nel guardaroba o in salotto. Oppure posizionala semplicemente su una mensola come bellissimo oggetto decorativo boho chic. Con queste scatole puoi facilmente riporre articoli da toeletta, trucco o piccoli oggetti in qualsiasi stanza. Un vero colpo d’occhio per il tuo arredamento! | N59: Enamórate de nuestra delicada caja con cuentas hecha a mano con tapa, que embellecerá cualquier rincón de la casa, ya sea en un dormitorio, baño, vestidor o salón. O simplemente colócala en una estantería como un hermoso elemento decorativo boho chic. Con estas cajas puedes guardar fácilmente artículos de tocador, maquillaje o pequeños objetos en cualquier habitación. ¡Un verdadero centro de atención para tu hogar! | O59: Verliebe dich in unsere zarte, handgefertigte Geschenkbox mit Perlen und Deckel, die mit ihrer schönen Ästhetik jede Ecke des Hauses verschönert, ob im Schlafzimmer, Badezimmer, Ankleidezimmer oder Wohnzimmer. Oder stelle sie einfach als schönes Boho-Chic-Dekoobjekt ins Regal. Mit diesen Boxen kannst du ganz einfach Pflegeprodukte, Make-up oder Kleinigkeiten in jedem Raum verstauen. Ein echter Hingucker für dein Zuhause! | P59: Black | Q59: Glass | Z59: 9 | AA59: cm | AB59: 10 | AC59: cm | AD59: 10 | AE59: cm | AG59: cm | AT59: Indonesia | BG59: https://bazarbizar.katanapim.com/content/images/thumbs/001/0010229_babe004b-s_101.webp | CA59: Bazar Bizar | CB59: 2550 | CD59: 10 x 10 x 9 cm | CG59: https://bazarbizar.katanapim.com/content/images/thumbs/001/0010231_babe004b-s.webp | FA59: Square | FQ59: Artisanal
A60: Storage accessories/Decorative storages/Baskets | B60: BABE004G-S | C60: =_xlfn.XLOOKUP(B60,Sheet1!A:A,Sheet1!A:A,) -> BABE004G-S | D60: Panier en perles or | E60: Cesta de cuantas dorada | F60: Cesto di perline oro | G60: Korb aus perlen gold | H60: 7438246041045 | J60: Bazar Bizar | K60: Beaded | L60: Tombez amoureux de notre délicat panier en perles fait main avec couvercle qui a une belle esthétique qui embellira n'importe quel coin de la maison que ce soit dans une chambre, une salle de bain, un dressing ou un salon.Ou simplement les placer sur une étagère comme un bel objet décoratif boho chic. Avec ces paniers, vous pouvez facilement ranger des articles de toilette, du maquillage ou des bricoles dans n'importe quelle pièce. Un véritable accroche-regard pour votre intérieur! | M60: Innamoratevi della nostra delicata Scatola di perline fatto a mano con coperchio, che ha una bella estetica che abbellirà qualsiasi angolo della casa, sia in una camera da letto, bagno, spogliatoio o soggiorno, o semplicemente metterli su una mensola come un bellissimo oggetto decorativo boho chic .Un vero e proprio eye-catcher per i vostri interni. | N60: Enamórate de nuestra delicada cesta con mullos y hecha a mano que tiene una hermosa estética que embellecerá cualquier rincón de la casa, ya sea un dormitorio, baño, vestidor, cocina o sala de estar. O simplemente colócalas en una estantería como un hermoso elemento decorativo bohemio chic. Con estas cestas podrás guardar fácilmente artículos de aseo, maquillaje entre otros. Un verdadero elemento llamativo para el interior de tu hogar. | O60: Verlieben Sie sich in unseren zarten, handgefertigten Perlenkorb mit Deckel, der mit seiner schönen Ästhetik jede Ecke des Hauses verschönert, sei es im Schlafzimmer, im Bad, in der Garderobe oder im Wohnzimmer, oder stellen Sie ihn einfach auf ein Regal als schönes Deko-Objekt im Boho-Chic. Mit diesen Körben können Sie ganz einfach Toilettenartikel, Make-up oder andere Kleinigkeiten in jedem Raum aufbewahren. Ein echter Blickfang für Ihr Zuhause! | P60: Gold | Q60: Natural fibers | V60: Goud | W60: Goud | Z60: 9 | AA60: cm | AB60: 10 | AC60: cm | AD60: 10 | AE60: cm | AZ60: Sea side | BG60: https://cdn.webshopapp.com/shops/298158/files/426872270/file.jpg | BH60: https://cdn.webshopapp.com/shops/298158/files/430897850/file.jpg | CG60: https://cdn.webshopapp.com/shops/298158/files/430897844/file.jpg | CJ60: https://cdn.webshopapp.com/shops/298158/files/430897855/file.jpg | CM60: https://cdn.webshopapp.com/shops/298158/files/342978725/file.jpg | FQ60: Artisanal
A61: Tableware and kitchen accessories/Dishes/Bowl | B61: BABE005B-S | C61: =_xlfn.XLOOKUP(B61,Sheet1!A:A,Sheet1!A:A,) -> BABE005B-S | D61: Panier perles noir 13x13x7cm | E61: Cesta de cuentas en negro 13x13x7 cm | F61: Cesto in perline nero 13x13x7 cm | G61: Korb aus Perlen in schwarz 13 x 13 x 7 cm | H61: 7438246041083 | I61: BABE005 | J61: Bazar Bizar | K61: Beaded | L61: Tombé amoureux de notre délicat bol perlé fait main, à l'esthétique raffinée qui embellira chaque recoin de la maison, chambre, salle de bain, dressing ou salon. Placez-le aussi sur une étagère comme objet déco bohème chic. Parfait pour ranger des articles de toilette, du maquillage ou de petits objets. Un vrai coup d'œil ! | M61: Innamoratevi della nostra delicata ciotola di perline fatta a mano, con una splendida estetica che valorizza ogni angolo della casa, sia in camera da letto, bagno, cabina armadio o soggiorno. Mettetela anche su una mensola come decorazione boho chic. Perfetta per articoli da toeletta, trucco o piccoli oggetti. Un vero colpo d'occhio! | N61: Enamórate de nuestro delicado cuenco con cuentas, hecho a mano, con una estética preciosa que embellecerá cualquier rincón de la casa, ya sea dormitorio, baño, vestidor o salón. También colócalo en una estantería como detalle bohemio chic. Perfecto para guardar artículos de aseo, maquillaje u objetos pequeños. ¡Un verdadero atractivo! | O61: Verlieben Sie sich in unsere zarte, handgefertigte Perlen-Schale, die mit ihrer schönen Ästhetik jeden Winkel verschönert, ob Schlafzimmer, Bad, Ankleide oder Wohnzimmer. Auch einfach auf ein Regal stellen als Boho-Chic-Deko. Ideal für Toilettenartikel, Make-up oder kleine Dinge. Ein echter Hingucker! | P61: Black | Q61: Glass | Z61: 7 | AA61: cm | AB61: 13 | AC61: cm | AD61: 13 | AE61: cm | AG61: cm | AT61: Indonesia | BG61: https://bazarbizar.katanapim.com/content/images/thumbs/002/0027748_babe005b-s.jpeg | CA61: Bazar Bizar | CB61: 2550 | CD61: 13 x 13 x 7 cm | CG61: https://bazarbizar.katanapim.com/content/images/thumbs/002/0024000_the-beaded-bowl-low-black-s.jpeg | CJ61: https://bazarbizar.katanapim.com/content/images/thumbs/002/0023998_the-beaded-bowl-low-gold-s.jpeg | DD61: Without pattern | FQ61: Artisanal
A62: Tableware and kitchen accessories/Dishes/Bowl | B62: BABE005G-S | C62: =_xlfn.XLOOKUP(B62,Sheet1!A:A,Sheet1!A:A,) -> BABE005G-S | D62: Panier perles or 13x13x5cm | E62: Cesta de cuentas en dorado 13x13x5 cm | F62: Cesto in perline dorato 13x13x5 cm | G62: Korb aus Perlen in Gold 13 x 13 x 5 cm | H62: 7438246041069 | I62: BABE005 | J62: Bazar Bizar | K62: Beaded | L62: Tombez amoureux de notre délicat bol perlé fait main, à l’esthétique raffinée qui embellira chaque recoin de votre maison, chambre, salle de bain, dressing ou salon. Ou placez-le simplement sur une étagère comme objet déco bohème chic. Parfait pour ranger des articles de toilette, du maquillage ou de petits objets. Un véritable atout pour votre intérieur ! | M62: Innamoratevi della nostra delicata ciotola di perline fatta a mano, con una splendida estetica che valorizza ogni angolo della casa, in camera da letto, bagno, cabina armadio o soggiorno. Oppure mettetela su una mensola come decorazione boho chic. Perfetta per riporre articoli da toeletta, trucco o piccoli oggetti. Un vero colpo d’occhio per i vostri interni. | N62: Enamórate de nuestro delicado bol con cuentas, hecho a mano con una estética preciosa que embellecerá cualquier rincón de la casa, ya sea dormitorio, baño, vestidor o salón. O colócalo en una estantería como un bonito detalle bohemio chic. Perfecto para guardar artículos de aseo, maquillaje u otros pequeños objetos. Una verdadera pieza llamativa para tu hogar. | O62: Verlieben Sie sich in unsere zarte, handgefertigte Perlen-Schale, die mit ihrer schönen Ästhetik jeden Winkel Ihres Hauses verschönert, ob Schlafzimmer, Bad, Ankleide oder Wohnzimmer. Oder stellen Sie sie einfach auf ein Regal als Boho-Chic-Dekoelement. Ideal zum Aufbewahren von Toilettenartikeln, Make-up oder kleinen Dingen. Ein echter Hingucker für Ihr Zuhause. | P62: Gold | Q62: Glass | Z62: 5 | AA62: cm | AB62: 13 | AC62: cm | AD62: 13 | AE62: cm | AG62: cm | AT62: Indonesia | BG62: https://bazarbizar.katanapim.com/content/images/thumbs/002/0027752_babe005g-s.jpeg | CA62: Bazar Bizar | CB62: 2550 | CD62: 13 x 13 x 5 cm | CG62: https://bazarbizar.katanapim.com/content/images/thumbs/002/0024020_the-beaded-bowl-low-gold-s.jpeg | CJ62: https://bazarbizar.katanapim.com/content/images/thumbs/002/0023998_the-beaded-bowl-low-gold-s.jpeg | DD62: Without pattern | FQ62: Artisanal
A63: Lifestyle/Pockets and wallets/Purses and wallets | B63: BABE006S | C63: =_xlfn.XLOOKUP(B63,Sheet1!A:A,Sheet1!A:A,) -> BABE006S | D63: Pochette perles argent et noir 23x12x2cm | E63: Clutch de cuentas en plateado y negro 23x12x2 cm | F63: Pochette in perline argento e nero 23x12x2 cm | G63: Perlenclutch in Silber und Schwarz, 23 × 12 × 2 cm | H63: 7438246041090 | I63: BABE006 | J63: Bazar Bizar | K63: Beaded | L63: Êtes-vous prête à briller de mille feux ? La pochette argentée est faite pour vous. Son design élégant et compact la rend facile à transporter tout en offrant suffisamment d'espace pour tous vos essentiels, de votre téléphone et vos clés à votre rouge à lèvres préféré. Mais ce n'est pas tout. La pochette argentée rehausse non seulement votre style, mais ajoute aussi une touche ludique à n'importe quelle tenue. Imaginez les compliments que vous recevrez en l'accessoirisant sans effort avec cette superbe pièce. | M63: Siete pronte a brillare? La Silver Clutch è la soluzione ideale. Il design elegante e compatto la rende facile da trasportare, offrendo comunque spazio sufficiente per tutti i vostri oggetti essenziali, dal telefono alle chiavi, fino al rossetto preferito. Ma c'è di più. La Silver Clutch non solo eleva il vostro stile, ma aggiunge anche un tocco di divertimento a qualsiasi outfit. Immaginate i complimenti che riceverete sfoggiando questo splendido pezzo. | N63: ¿Estás lista para deslumbrar? El bolso de mano Silver Clutch es tu mejor aliado. Su diseño elegante y compacto lo hace fácil de llevar, a la vez que ofrece espacio suficiente para todos tus imprescindibles, desde el teléfono y las llaves hasta tu barra de labios favorita. Pero hay más. The Silver Clutch no solo eleva tu estilo, sino que también añade un toque de diversión a cualquier conjunto. Imagina los cumplidos que recibirás al lucirlo con facilidad. | O63: Sind Sie bereit zu glänzen? Dann ist die Silver Clutch genau das Richtige. Dank ihres schlanken, kompakten Designs ist sie leicht zu tragen und bietet dennoch genug Platz für all Ihre Essentials, vom Telefon und Schlüssel bis hin zum Lieblingslippenstift. Aber es gibt noch mehr. Die Silver Clutch wertet nicht nur Ihren Stil auf, sondern verleiht jedem Outfit eine spielerische Note. Stellen Sie sich die Komplimente vor, die Sie erhalten werden, wenn Sie dieses wunderschöne Stück tragen. | P63: Silver | Q63: Glass | Z63: 2 | AA63: cm | AB63: 23 | AC63: cm | AD63: 12 | AE63: cm | AG63: cm | AT63: Indonesia | BG63: https://bazarbizar.katanapim.com/content/images/thumbs/002/0028097_babe006s.jpeg | CA63: Bazar Bizar | CB63: 2550 | CD63: 23 x 12 x 2 cm | CG63: https://bazarbizar.katanapim.com/content/images/thumbs/002/0023027_the-silver-clutch.jpeg | CJ63: https://bazarbizar.katanapim.com/content/images/thumbs/002/0023028_the-silver-clutch.jpeg | CM63: https://bazarbizar.katanapim.com/content/images/thumbs/002/0023025_the-silver-clutch.jpeg
A64: Lifestyle/Pockets and wallets/Purses and wallets | B64: BABE008B | C64: =_xlfn.XLOOKUP(B64,Sheet1!A:A,Sheet1!A:A,) -> BABE008B | D64: Portefeuille perles noir 14x10x2cm | E64: Cartera de cuentas en negro 14x10x2 cm | F64: Portafoglio in perline nero 14x10x2 cm | G64: Geldbörse aus Perlen in schwarz 14 x 10 x 2 cm | H64: 7438246042028 | I64: BABE008 | J64: Bazar Bizar | K64: Beaded | L64: Imaginez les regards admiratifs lorsque vous sortez gracieusement le porte-monnaie Black Beaded de votre sac ou de votre poche. Sa silhouette élégante et ses perles scintillantes en font un accessoire remarquable qui ajoute une touche de glamour à n'importe quelle tenue. Fabriqué avec précision et souci du détail, ce porte-monnaie est orné de perles noires complexes qui dégagent un luxe et une sophistication discrets. | M64: Immagina gli sguardi ammirati mentre estrai con grazia il portafoglio Black Beaded dalla borsa o dalla tasca. La sua silhouette elegante e le perline scintillanti lo rendono un accessorio di spicco che aggiunge un tocco di glamour a qualsiasi look. Realizzato con precisione e attenzione ai dettagli, questo portafoglio è ornato da perline nere intricate che emanano lusso e raffinatezza. | N64: Imagina las miradas de admiración cuando saques con elegancia la billetera Black Beaded de tu bolso o bolsillo. Su elegante silueta y sus brillantes cuentas la convierten en un accesorio destacado que añade un toque de glamour a cualquier conjunto. Elaborada con precisión y atención al detalle, esta billetera está adornada con intrincadas cuentas negras que irradian lujo y sofisticación discretos. | O64: Stellen Sie sich die bewundernden Blicke vor, wenn Sie das Black Beaded Portemonnaie anmutig aus Ihrer Tasche ziehen. Seine schlanke Silhouette und die schimmernden Perlen machen es zu einem auffälligen Accessoire, das jedem Outfit einen Hauch von Glamour verleiht. Dieses mit Präzision und Liebe zum Detail gefertigte Portemonnaie ist mit kunstvollen schwarzen Perlen verziert, die dezenten Luxus und Raffinesse ausstrahlen. | P64: Black | Q64: Glass | Z64: 2 | AA64: cm | AB64: 14 | AC64: cm | AD64: 10 | AE64: cm | AG64: cm | AT64: Indonesia | BG64: https://bazarbizar.katanapim.com/content/images/thumbs/002/0028101_babe008b.jpeg | CA64: Bazar Bizar | CB64: 2550 | CD64: 14 x 10 x 2 cm | CG64: https://bazarbizar.katanapim.com/content/images/thumbs/002/0022967_the-black-beaded-wallet.jpeg
A65: Lifestyle/Pockets and wallets/Purses and wallets | B65: BABE010B | C65: =_xlfn.XLOOKUP(B65,Sheet1!A:A,Sheet1!A:A,) -> BABE010B | D65: Pochette perles noir 20x10x10cm | E65: Clutch de cuentas en negro 20x10x10 cm | F65: Pochette in perline nera 20x10x10 cm | G65: Clutch aus Perlen in schwarz 20 x 10 x 10 cm | H65: 7438246030070 | I65: BABE010 | J65: Bazar Bizar | K65: Beaded | L65: Dites adieu aux bureaux en désordre et aux stylos perdus, et bonjour à la trousse à crayons, votre solution ultime pour ranger vos stylos et crayons, tout en servant de maison parfaite pour vos essentiels de maquillage. Du rouge à lèvres à l'eyeliner, du blush aux pinceaux, cette trousse multifonction vous accompagne partout. | M65: Dite addio alle scrivanie disordinate e alle penne smarrite e date il benvenuto all'astuccio per matite, la soluzione ideale per tenere in ordine penne e matite e ospitare il trucco essenziale. Dal rossetto all'eyeliner, dal fard ai pennelli, questa meraviglia multifunzionale ha tutto. | N65: Despídete de los escritorios desordenados y de los bolígrafos perdidos, y da la bienvenida al estuche para lápices: la solución definitiva para mantener lápices y bolígrafos organizados, además de servir como el hogar perfecto para tus productos de maquillaje. Desde pintalabios hasta delineador, colorete y brochas, esta maravilla multifuncional lo tiene todo. | O65: Verabschieden Sie sich von unordentlichen Schreibtischen und verlorenen Stiften und begrüßen Sie das Federmäppchen, Ihre ideale Lösung, um Stifte und Bleistifte zu ordnen und gleichzeitig ein Zuhause für Ihre Make-up-Utensilien zu bieten. Vom Lippenstift bis zum Eyeliner, vom Rouge bis zu den Pinseln – dieses multifunktionale Wunder hat alles. | P65: Black | Q65: Glass | Z65: 10 | AA65: cm | AB65: 20 | AC65: cm | AD65: 10 | AE65: cm | AG65: cm | AT65: Indonesia | BG65: https://bazarbizar.katanapim.com/content/images/thumbs/002/0028104_babe010b.jpeg | BH65: https://bazarbizar.katanapim.com/content/images/thumbs/002/0023079_the-pencil-case-black.jpeg | BI65: https://bazarbizar.katanapim.com/content/images/thumbs/002/0023080_the-pencil-case-black.jpeg | CA65: Bazar Bizar | CB65: 2550 | CD65: 20 x 10 x 10 cm | CG65: https://bazarbizar.katanapim.com/content/images/thumbs/002/0023086_the-pencil-case-black.jpeg | CJ65: https://bazarbizar.katanapim.com/content/images/thumbs/002/0023083_the-pencil-case-black.jpeg | CM65: https://bazarbizar.katanapim.com/content/images/thumbs/002/0023084_the-pencil-case-black.jpeg
A66: Lifestyle/Pockets and wallets/Purses and wallets | B66: BABE010G | C66: =_xlfn.XLOOKUP(B66,Sheet1!A:A,Sheet1!A:A,) -> BABE010G | D66: Pochette perles or 20x10x10cm | E66: Clutch de cuentas en dorado 20x10x10 cm | F66: Pochette in perline oro 20x10x10 cm | G66: Clutch aus Perlen in goldfarben 20 x 10 x 10 cm | H66: 7438246030087 | I66: BABE010 | J66: Bazar Bizar | K66: Beaded | L66: Dites adieu aux bureaux en désordre et aux stylos perdus, et bonjour à la trousse à crayons, la solution ultime pour ranger vos stylos et crayons, tout en servant d'écrin parfait pour votre maquillage. Du rouge à lèvres à l'eyeliner, du blush aux pinceaux, cette trousse multifonctionnelle répond à tous vos besoins. | M66: Dite addio alle scrivanie disordinate e alle penne smarrite e date il benvenuto all'astuccio per matite, la soluzione definitiva per organizzare penne e matite e custodire il vostro trucco. Dal rossetto all'eyeliner, dal fard ai pennelli, questa meraviglia multifunzionale ha tutto. | N66: Despídete de los escritorios desordenados y de los bolígrafos perdidos y da la bienvenida al estuche para lápices, la solución definitiva para organizar lápices y bolígrafos, además de ser el hogar perfecto para tu maquillaje. Desde pintalabios hasta delineador, colorete y brochas, esta maravilla multifuncional lo tiene todo. | O66: Verabschieden Sie sich von unordentlichen Schreibtischen und verlorenen Stiften und begrüßen Sie das Federmäppchen, die ultimative Lösung, um Stifte und Bleistifte zu ordnen und gleichzeitig ein perfektes Zuhause für Ihr Make-up zu bieten. Vom Lippenstift bis zum Eyeliner, vom Rouge bis zu Pinseln, dieses multifunktionale Wunder hat alles. | P66: Gold | Q66: Glass | Z66: 10 | AA66: cm | AB66: 20 | AC66: cm | AD66: 10 | AE66: cm | AG66: cm | AT66: Indonesia | BG66: https://bazarbizar.katanapim.com/content/images/thumbs/002/0028105_babe010g.jpeg | CA66: Bazar Bizar | CB66: 2550 | CD66: 20 x 10 x 10 cm | CG66: https://bazarbizar.katanapim.com/content/images/thumbs/002/0022996_the-pencil-case-gold.jpeg | CJ66: https://bazarbizar.katanapim.com/content/images/thumbs/002/0022995_the-pencil-case-gold.jpeg | CM66: https://bazarbizar.katanapim.com/content/images/thumbs/002/0022994_the-pencil-case-gold.jpeg
A67: Tableware and kitchen accessories/Dishes/Bowl | B67: BABE012B-M | C67: =_xlfn.XLOOKUP(B67,Sheet1!A:A,Sheet1!A:A,) -> BABE012B-M | D67: Panier perles noir 13x13x10cm | E67: Cesta de cuentas en negro 13x13x10 cm | F67: Cesto in perline nero 13x13x10 cm | G67: Korb aus Perlen in schwarz 13 x 13 x 10 cm | H67: 7438246043018 | I67: BABE012 | J67: Bazar Bizar | K67: Beaded | L67: <p>Tombez sous le charme de notre délicat bol en perles fait main, qui embellira chaque coin de la maison, que ce soit chambre, salle de bain, dressing ou salon. Idéal pour articles de toilette, maquillage ou petits objets. Aussi joli en décoration boho chic sur une étagère. Un vrai coup d’œil pour votre intérieur !</p> | M67: Innamorati della nostra delicata ciotola di caramelle con perline fatta a mano, che abbellisce ogni angolo della casa, sia in camera, bagno, spogliatoio o soggiorno. Perfetta per articoli da toeletta, trucco o piccoli oggetti. Anche bella come oggetto decorativo boho chic su uno scaffale. Un vero richiamo visivo! | N67: Enamórate de nuestra delicada dulcera de cuentas hecha a mano, que embellece cada rincón de la casa, ya sea dormitorio, baño, vestidor o sala de estar. Ideal para artículos de aseo, maquillaje o pequeños objetos. También hermosa como decoración boho chic en una estantería. ¡Un verdadero punto de atracción! | O67: <p>Verlieben Sie sich in unsere zarten, handgefertigten Perlenkörbe, die mit ihrer schönen ästhetik jede Ecke des Hauses verschönern, sei es im Schlafzimmer, im Bad, in der Ankleide, in der Kche oder im Wohnzimmer. Mit diesen Körben können Sie ganz einfach Toilettenartikel, Make-up oder andere Kleinigkeiten in jedem Raum aufbewahren. Ein echter Blickfang Ihr Zuhause!</p> | P67: Black | Q67: Glass | Z67: 10 | AA67: cm | AB67: 13 | AC67: cm | AD67: 13 | AE67: cm | AG67: cm | AT67: Indonesia | BG67: https://bazarbizar.katanapim.com/content/images/thumbs/002/0027759_babe012b-m.jpeg | CA67: Bazar Bizar | CB67: 2550 | CD67: 13 x 13 x 10 cm | CG67: https://bazarbizar.katanapim.com/content/images/thumbs/001/0010307_babe012b-m_103.webp | CJ67: https://bazarbizar.katanapim.com/content/images/thumbs/001/0010304_babe012b-m_100.webp | CM67: https://bazarbizar.katanapim.com/content/images/thumbs/001/0010308_babe012b-m_2.webp | DD67: Without pattern | FQ67: Artisanal
A68: Lifestyle/Gadgets/Keychains | B68: BABF005 | C68: =_xlfn.XLOOKUP(B68,Sheet1!A:A,Sheet1!A:A,) -> BABF005 | D68: Porte-clés en perles multicolore H15 cm | E68: Llavero sorpresa | F68: Portachiavi in perline multicolore H15 cm | G68: Der Überrasch-mich-Schlüsselanhänger | H68: 7438245988969 | I68: BABF005 | J68: Bazar Bizar | K68: Surprise | L68: <p>Le Porte-clés Surprise-moi en Couleurs Mixtes est un accessoire ludique et fait main, confectionné avec des perles éclatantes. Chaque pièce est unique, débordant de couleurs vives et de charme bohème, aucun n'est identique. Ajoutez une touche amusante et éclectique à vos clés, sacs ou cadeaux avec ce porte-clés accrocheur. Léger et plein de personnalité, il est parfait pour ceux qui aiment les surprises, les combinaisons de couleurs audacieuses et les détails artisanaux. Un petit accessoire avec beaucoup de caractère.</p> | M68: <p><span>Il Portachiavi Sorpresa in Colori Misti è un accessorio giocoso e artigianale realizzato con perline vivaci. Ogni pezzo è unico, ricco di colori allegri e fascino boho, non ce ne sono due uguali. Aggiungi un tocco divertente ed eclettico alle tue chiavi, borse o regali con questo portachiavi accattivante. Leggero e pieno di personalità, è perfetto per chi ama le sorprese, le combinazioni di colori audaci e i dettagli fatti a mano. Un piccolo accessorio con un grande carattere.</span></p> | N68: <p><span>El Llavero Sorpresa en Colores Mixtos es un accesorio divertido y artesanal, hecho con cuentas vibrantes. Cada pieza es única, llena de colores alegres y encanto bohemio, no hay dos iguales. Añade un toque divertido y ecléctico a tus llaves, bolsos o regalos con este llamativo llavero. Ligero y lleno de personalidad, es perfecto para quienes aman las sorpresas, las combinaciones de colores audaces y los detalles hechos a mano. Un pequeño accesorio con gran carácter.</span></p> | O68: <p><span>Der Überrasch-mich-Schlüsselanhänger in bunten Farben ist ein verspieltes, handgefertigtes Accessoire aus leuchtenden Perlen. Jedes Stück ist einzigartig, voller fröhlicher Farben und Boho-Charme, kein Anhänger gleicht dem anderen. Verleihen Sie Ihren Schlüsseln, Taschen oder Geschenken mit diesem auffälligen Schlüsselanhänger eine lustige, eklektische Note. Leicht und voller Persönlichkeit, perfekt für alle, die Überraschungen, kräftige Farbkombinationen und handgefertigte Details lieben. Ein kleines Accessoire mit großem Charakter.</span></p> | P68: Multicolour | Q68: Glass | V68: Mixte / Multicolore | W68: Mixto / Multicolor | X68: Misto / Multicolore | Y68: Gemischt / Mehrfarbig | Z68: 15 | AA68: cm | AB68: 3 | AC68: cm | AD68: 3 | AE68: cm | AG68: cm | AT68: Indonesia | BG68: https://bazarbizar.katanapim.com/content/images/thumbs/001/0016095_the-surprise-me-keychain.jpeg | CA68: Bazar Bizar | CB68: 2550 | CD68: 3 x 3 x 15 cm
A69: Decoration/Wall decoration/Decorative plates | B69: BABL004W-M | C69: =_xlfn.XLOOKUP(B69,Sheet1!A:A,Sheet1!A:A,) -> BABL004W-M | D69: Décoration suspendue Coquillage Blanc 20x4x30cm | E69: Decoración de pared de conchas en blanco 20x4x30cm | F69: Decorazione da parete in conchiglie bianche 20x4x30cm | G69: Hängende Dekoration aus Muscheln in weiß, 20 x 4 x 30 cm | H69: 7438245961948 | I69: BABL004 | J69: Bazar Bizar | K69: Kai | L69: Ces belles croix décoratives de style côtier sont recouvertes de coquillages blancs formant un élégant motif floral. Elles sont superbes accrochées ou posées sur une table ou une étagère. Un véritable must-have pour votre décoration côtière. | M69: Queste splendide croci decorative in stile costiero sono rivestite di conchiglie bianche che formano un elegante motivo floreale. Perfette da appendere o da appoggiare su un tavolo o su una mensola. Un vero must-have della decorazione costiera. | N69: Estas bonitas cruces decorativas de estilo costero están cubiertas de conchas blancas que forman un delicado motivo floral. Son ideales para colgar o colocar sobre una mesa o estantería. Una auténtica pieza imprescindible para tu decoración costera. | O69: Diese wunderschönen dekorativen Küstenkreuze sind mit weißen Muscheln bedeckt, die ein elegantes Blumenmuster bilden. Sie sehen großartig aus, ob aufgehängt oder auf einem Tisch oder Regal platziert. Ein echtes Must-have für Ihre Küstendeko. | P69: White | Q69: Mother-of-pear | Z69: 30 | AA69: cm | AB69: 20 | AC69: cm | AD69: 4 | AE69: cm | AG69: cm | AT69: Indonesia | BG69: https://bazarbizar.katanapim.com/content/images/thumbs/002/0028350_babl004w-m.jpeg | CA69: Bazar Bizar | CB69: 2550 | CD69: 20 x 4 x 30 cm | EX69: Sea
A70: Decoration/Wall decoration/Decorative plates | B70: BABL005W-L | C70: =_xlfn.XLOOKUP(B70,Sheet1!A:A,Sheet1!A:A,) -> BABL005W-L | D70: Décoration suspendue en coquillage blanc | E70: Decoración colgante de conchas blanco | F70: Decorazione da appendere di conchiglie bianche | G70: Hängedekoration aus Muscheln weiss | H70: 7438245961955 | J70: Bazar Bizar | L70: Boules de coquillages en forme de fleurs entièrement réalisées à la main par des artisans balinais, elles disposent d'une ficelle pour les suspendre et sont disponibles en 2 tailles différentes.A rassembler dans un bol, à poser ou à suspendre, elles s'accorderont parfaitement à un intérieur bohème, un must have pour votre décoration! | M70: La nostra palla fiore di conchiglia a forma di fiore realizzata interamente a mano da artigiani balinesi, è dotata di una corda per appenderla ed è disponibile in 2 diverse misure. Da raccogliere in una ciotola, da posizionare o da appendere, si adattano perfettamente ad un interno bohemien, un must per la vostra decorazione! | N70: Estas bolas decorativas cubiertas de conchas en forma de flor son elaboradas completamente a mano por artesanos balineses, vienen con un cordón para colgarlas donde tú desees y las puedes encontrar en 2 tamaños diferentes. Son perfectas para ser juntadas en un plato hondo, reposando sobre un mueble o también para colgarlas. No importa como decidas combinarlas, estas siempre quedaran muy bonitas en cualquiera de tus espacios interiores de estilo bohemio, ¡serán el toque perfecto para tu decoración! | O70: Blumenförmige Muschelkugeln, die von balinesischen Handwerkern vollständig von Hand gefertigt werden. Sie haben eine Schnur, um sie zu hängen und sind in 2 verschiedenen Größen erhältlich. Zum Sammeln in einer Schale, zum Aufstellen oder Aufhängen, sie passen perfekt zu einem Bohème-Interieur, ein Must-Have für Ihre Dekoration! | P70: White | Q70: Mother-of-pear | R70: Coquille | S70: Concha | T70: Schale | U70: Conchiglia | V70: Blanc | W70: Blanco | X70: Bianco | Y70: Weiss | Z70: 12 | AA70: cm | AB70: 12 | AC70: cm | AD70: 12 | AE70: cm | AG70: cm | AT70: Indonesia | AZ70: Sea side | BG70: https://bazarbizar.katanapim.com/content/images/thumbs/0010352_babl005w-l.webp | CD70: 12cm x 12cm x 12cm | CG70: https://bazarbizar.katanapim.com/content/images/thumbs/0010350_babl005w-l_101.webp | CJ70: https://bazarbizar.katanapim.com/content/images/thumbs/0010349_babl005w-l_102.webp | EX70: Sea
A71: Decoration/Wall decoration/Decorative plates | B71: BABL005W-M | C71: =_xlfn.XLOOKUP(B71,Sheet1!A:A,Sheet1!A:A,) -> BABL005W-M | H71: 7438245961962 | J71: Bazar Bizar | L71: Boules de coquillages en forme de fleurs entièrement réalisées à la main par des artisans balinais, elles disposent d'une ficelle pour les suspendre et sont disponibles en 2 tailles différentes.A rassembler dans un bol, à poser ou à suspendre, elles s'accorderont parfaitement à un intérieur bohème, un must have pour votre décoration! | M71: La nostra palla fiore di conchiglia a forma di fiore realizzata interamente a mano da artigiani balinesi, è dotata di una corda per appenderla ed è disponibile in 2 diverse misure. Da raccogliere in una ciotola, da posizionare o da appendere, si adattano perfettamente ad un interno bohemien, un must per la vostra decorazione! | N71: Estas bolas decorativas cubiertas de conchas en forma de flor son elaboradas completamente a mano por artesanos balineses, vienen con un cordón para colgarlas donde tú desees y las puedes encontrar en 2 tamaños diferentes. Son perfectas para ser juntadas en un plato hondo, reposando sobre un mueble o también para colgarlas. No importa como decidas combinarlas, estas siempre quedaran muy bonitas en cualquiera de tus espacios interiores de estilo bohemio, ¡serán el toque perfecto para tu decoración! | O71: Blumenförmige Muschelkugeln, die von balinesischen Handwerkern vollständig von Hand gefertigt werden. Sie haben eine Schnur, um sie zu hängen und sind in 2 verschiedenen Größen erhältlich. Zum Sammeln in einer Schale, zum Aufstellen oder Aufhängen, sie passen perfekt zu einem Bohème-Interieur, ein Must-Have für Ihre Dekoration! | P71: White | Q71: Natural fibers | AA71: cm | AB71: 12 | AC71: cm | AD71: 9 | AE71: cm | BG71: https://cdn.webshopapp.com/shops/298158/files/441459490/file.jpg | CG71: https://cdn.webshopapp.com/shops/298158/files/441459307/file.jpg | CJ71: https://cdn.webshopapp.com/shops/298158/files/441459312/file.jpg | CM71: https://cdn.webshopapp.com/shops/298158/files/441459310/file.jpg
A72: Decoration/Wall decoration/Decorative plates | B72: BABL006W-M | C72: =_xlfn.XLOOKUP(B72,Sheet1!A:A,Sheet1!A:A,) -> BABL006W-M | D72: Décoration suspendue en coquillage de couleur blanche 9 x 9 x 9 cm | E72: Decoración de pared de conchas en blanco 9x9x9cm | F72: Decorazione da parete in conchiglie bianche 9x9x9cm | G72: Hängedekoration aus Muschel in weiß, 9 × 9 × 9 cm | H72: 7438245961986 | I72: BABL006 | J72: Bazar Bizar | K72: Rose | L72: <p>Découvrez la beauté discrète du design artisanal avec notre boule décorative en coquillages, un objet sculptural qui célèbre les matériaux naturels. Faite main à partir de coquilles blanches lisses, elle offre texture visuelle et élégance tactile, devenant une pièce adaptable pour des intérieurs raffinés.</p> <p>Parfaite comme centre de table, intégrée à une bibliothèque ou placée dans une mise en scène, cette boule apporte du caractère subtil sans dominer l’espace. Ses tons naturels s’harmonisent avec des esthétiques bohèmes, côtières ou contemporaines, permettant une intégration fluide.</p> <p>Chaque décoration en coquillage faite main révèle de subtiles irrégularités, témoignant du savoir-faire artisanal. Ces détails rendent chaque boule unique, renforçant son authenticité et sa valeur de collection. Plus qu’un ornement, c’est une œuvre d’art conçue pour apporter charme intemporel et sophistication discrète.</p> | M72: <p>Vivi la bellezza silenziosa del design artigianale con la nostra sfera decorativa di conchiglie, un oggetto scultoreo che celebra i materiali naturali. Realizzata a mano con conchiglie bianche lisce, offre texture visiva ed eleganza tattile, rendendola un pezzo versatile per interni raffinati.</p> <p>Perfetta come centrotavola, inserita in una libreria o all’interno di una composizione decorativa, questa sfera bianca aggiunge carattere sottile senza sovrastare lo spazio. Le tonalità naturali si armonizzano con estetiche boho, costiere e contemporanee, permettendo un’integrazione fluida.</p> <p>Ogni decorazione in conchiglie fatta a mano rivela sottili irregolarità, segno della maestria artigiana. Queste sfumature rendono ogni sfera unica, aumentandone autenticità e valore collezionistico. Più che un semplice ornamento, è una piccola opera d’arte che porta fascino senza tempo e raffinata eleganza nella tua casa.</p> | N72: <p>Descubre la tranquila belleza del diseño artesanal con nuestra bola decorativa de conchas, un objeto escultórico que celebra los materiales naturales. Hecha a mano con conchas blancas lisas, ofrece textura visual y elegancia táctil, convirtiéndose en una pieza adaptable para interiores refinados.</p> <p>Perfecta como centro de mesa, en estanterías o dentro de una composición decorativa, esta bola de conchas blancas añade carácter sutil sin dominar el espacio. Sus tonos naturales armonizan con estéticas bohemias, costeras y contemporáneas, permitiendo una integración fluida.</p> <p>Cada adorno de conchas hecho a mano revela sutiles irregularidades, mostrando la artesanía de los expertos. Estas particularidades hacen que cada bola sea única, aumentando su autenticidad y valor coleccionable. Más que un adorno, es una pequeña obra de arte que aporta encanto atemporal y sofisticación.</p> | O72: <p>Erleben Sie die stille Schönheit handwerklichen Designs mit unserer dekorativen Muschelkugel, einem skulpturalen Objekt, das natürliche Materialien würdigt. Handgefertigt aus glatten weißen Muscheln, bietet sie visuelle Textur und taktile Eleganz und wird so zu einem vielseitigen Stück für anspruchsvolle Interieurs.</p> <p>Perfekt als Mittelpunkt auf einem Esstisch, im Regal oder als Teil einer dekorativen Anordnung, fügt diese weiße Muschelkugel subtilen Charakter hinzu, ohne den Raum zu dominieren. Ihre natürlichen Töne harmonieren mit Bohème-, Küsten- und modernen Ästhetiken und lassen sich mühelos integrieren.</p> <p>Jede handgefertigte Muschel-Dekoration zeigt feine Unregelmäßigkeiten, die das Können der Kunsthandwerker widerspiegeln. Diese Details machen jede Kugel einzigartig und verstärken Authentizität und Sammlerwert. Mehr als nur ein Ornament, ist sie ein kleines Kunstwerk voller zeitlosem Charme und leiser Raffinesse.</p> | P72: White | Q72: Mother-of-pear | Z72: 9 | AA72: cm | AB72: 9 | AC72: cm | AD72: 9 | AE72: cm | AG72: cm | AT72: Indonesia | BG72: https://bazarbizar.katanapim.com/content/images/thumbs/002/0028351_babl006w-m.jpeg | CA72: Bazar Bizar | CB72: 2550 | CD72: 9 x 9 x 9 cm | CG72: https://bazarbizar.katanapim.com/content/images/thumbs/001/0019178_the-rose-shell-ball-white-m.jpeg | CJ72: https://bazarbizar.katanapim.com/content/images/thumbs/001/0019177_the-misty-cushion-cover-natural-black.jpeg | CM72: https://bazarbizar.katanapim.com/content/images/thumbs/001/0019179_the-rose-shell-ball-white-l.jpeg | EX72: Sea
A73: Decoration/Wall decoration/Decorative plates | B73: BABL009W-M | C73: =_xlfn.XLOOKUP(B73,Sheet1!A:A,Sheet1!A:A,) -> BABL009W-M | H73: 7438246063047 | J73: Bazar Bizar | K73: Palawan
A74: Decoration/Wall decoration/Decorative plates | B74: BABL009W-S | C74: =_xlfn.XLOOKUP(B74,Sheet1!A:A,Sheet1!A:A,) -> BABL009W-S | H74: 7438246063054 | J74: Bazar Bizar | K74: Palawan
A75: Decoration/Wall decoration/Decorative plates | B75: BABL010WPi-S | C75: =_xlfn.XLOOKUP(B75,Sheet1!A:A,Sheet1!A:A,) -> BABL010WPi-S | D75: Décoration suspendue en coquillage blanc | E75: Decoración colgante de conchas | F75: Decorazione da appendere di conchiglie | H75: 7438246063061 | L75: Ce magnifique cintre est fabriqué à la main en coquillages par des artisans indonésiens. A accrocher sur les portes, les rideaux ou les murs selon vos envies, ou simplement posé sur une commode, ce cintre donnera une ambiance exotique et bohème à votre décoration. | N75: Este hermoso colgador hecho a mano con conchas por artesanos indonesios es perfecto para colgarse en puertas, cortinas, paredes o simplemente lo puedes poner sobre una cómoda. ¡Dale un toque exótico y bohemio a tu decoración! | P75: White | Q75: Natural fibers | Z75: 8 | AA75: cm | AB75: 8 | AC75: cm | AD75: 2 | AE75: cm | BG75: https://cdn.webshopapp.com/shops/298158/files/454899861/file.jpg
A76: Decoration/Wall decoration/Decorative plates | B76: BABL011W-S | C76: =_xlfn.XLOOKUP(B76,Sheet1!A:A,Sheet1!A:A,) -> BABL011W-S | D76: Décoration suspendue en coquillage blanc | E76: Decoración colgante de conchas | F76: Decorazione da appendere di conchiglie | H76: 7438246063078 | L76: Ce magnifique cintre est fabriqué à la main en coquillages par des artisans indonésiens. A accrocher sur les portes, les rideaux ou les murs selon vos envies, ou simplement posé sur une commode, ce cintre donnera une ambiance exotique et bohème à votre décoration. | N76: Este hermoso colgador hecho a mano con conchas por artesanos indonesios es perfecto para colgarse en puertas, cortinas, paredes o simplemente lo puedes poner sobre una cómoda. ¡Dale un toque exótico y bohemio a tu decoración! | P76: White | Q76: Natural fibers | Z76: 8 | AA76: cm | AB76: 8 | AC76: cm | AD76: 2 | AE76: cm | BG76: https://cdn.webshopapp.com/shops/298158/files/454893795/file.jpg
A77: Decoration/Wall decoration/Decorative plates | B77: BABL012W-S | C77: =_xlfn.XLOOKUP(B77,Sheet1!A:A,Sheet1!A:A,) -> BABL012W-S | D77: Décoration suspendue en coquillage blanc | E77: Decoración colgante de conchas | F77: Decorazione da appendere di conchiglie | H77: 7438246063085 | L77: Ce magnifique cintre est fabriqué à la main en coquillages par des artisans indonésiens. A accrocher sur les portes, les rideaux ou les murs selon vos envies, ou simplement posé sur une commode, ce cintre donnera une ambiance exotique et bohème à votre décoration. | N77: Este hermoso colgador hecho a mano con conchas por artesanos indonesios es perfecto para colgarse en puertas, cortinas, paredes o simplemente lo puedes poner sobre una cómoda. ¡Dale un toque exótico y bohemio a tu decoración! | P77: White | Q77: Natural fibers | Z77: 8 | AA77: cm | AB77: 8 | AC77: cm | AD77: 2 | AE77: cm | BG77: https://cdn.webshopapp.com/shops/298158/files/454890456/file.jpg
A78: Decoration/Wall decoration/Decorative plates | B78: BABL020W-L | C78: =_xlfn.XLOOKUP(B78,Sheet1!A:A,Sheet1!A:A,) -> BABL020W-L | H78: 7438246221218 | J78: Bazar Bizar | L78: Cette étoile de mer décorative est entièrement composée de magnifiques coquillages blancs, collés ensemble sous la forme de jolies fleurs. Vous pouvez la suspendre dans votre salle de bains grâce à son cordon, ou la placer sur une étagère ou une table (d'appoint) pour créer une ambiance côtière où vous le souhaitez. | M78: Questa stella marina decorativa è realizzata completamente con bellissime conchiglie bianche, incastrate tra loro a forma di fiore. Potete appenderla in bagno con la sua cordicella o posizionarla su una mensola o un tavolino per creare un'atmosfera costiera ovunque vogliate. | N78: Esta estrella de mar decorativa está hecha completamente de preciosas conchas blancas, pegadas unas a otras en adorables formas de flores. Puedes colgarla en el baño con su cuerda, o colocarla en una estantería o mesa (auxiliar) para crear un ambiente costero donde quieras. | O78: Dieser dekorative Seestern ist komplett aus schönen weißen Muscheln gefertigt, die in schönen Blumenformen zusammengesteckt sind. Sie können ihn an seiner Kordel in Ihrem Badezimmer aufhängen oder ihn auf ein Regal oder einen (Beistell-)Tisch stellen, um überall eine Küstenatmosphäre zu schaffen, wo Sie wollen. | P78: White | Q78: Mother-of-pear | R78: Coquille | S78: Concha | T78: Schale | U78: Conchiglia | V78: Blanc | W78: Blanco | X78: Bianco | Y78: Weiss | Z78: 25 | AA78: cm | AB78: 25 | AC78: cm | AD78: 3 | AE78: cm | AG78: cm | AT78: Indonesia | AZ78: Sea side | BG78: https://bazarbizar.katanapim.com/content/images/thumbs/0009738_babl020w-l.webp | BH78: https://bazarbizar.katanapim.com/content/images/thumbs/0009735_babl020w-l_102.webp | BI78: https://bazarbizar.katanapim.com/content/images/thumbs/0009731_babl020w-l_2.webp | BJ78: https://bazarbizar.katanapim.com/content/images/thumbs/0009730_babl020w-l_3.webp | BK78: https://bazarbizar.katanapim.com/content/images/thumbs/0009725_babl020w-l_4.webp | CD78: 25cm x 3cm x 25cm | CG78: https://bazarbizar.katanapim.com/content/images/thumbs/0009632_babl020w-l_104.webp | CJ78: https://bazarbizar.katanapim.com/content/images/thumbs/0009727_babl020w-l_302.webp | CM78: https://bazarbizar.katanapim.com/content/images/thumbs/0009732_babl020w-l_106.webp | EX78: Sea
A79: Decoration/Wall decoration/Decorative plates | B79: BABL022W | C79: =_xlfn.XLOOKUP(B79,Sheet1!A:A,Sheet1!A:A,) -> BABL022W | H79: 7438246289201 | J79: Bazar Bizar | L79: <p>Faites entrer les tropiques dans votre maison avec cette jolie pièce de décoration suspendue en forme de palmier ! Il est entièrement fabriqué à partir de coquillages et constituera un ajout unique à votre salon, votre salle de bains ou même votre espace extérieur. Chaque pièce est fabriquée à la main par des habitants de Bali.</p> | M79: <p>Portate i tropici a casa vostra con questo simpatico oggetto da appendere a forma di palma! È realizzato interamente con conchiglie e sarà un'aggiunta unica al vostro salotto, al bagno o anche all'esterno. Ogni pezzo è realizzato a mano dagli abitanti di Bali.</p> | N79: <p>Lleva el trópico a tu casa con este bonito adorno colgante en forma de palmera. Está hecha totalmente de conchas y será un complemento único para tu salón, cuarto de baño o incluso espacio exterior. Todas las piezas están hechas a mano en Bali.</p> | O79: <p>Holen Sie sich die Tropen in Ihr Zuhause mit dieser niedlichen Hängedeko in Form einer Palme! Sie ist komplett aus Muscheln gefertigt und eine einzigartige Ergänzung für Ihr Wohnzimmer, Ihr Badezimmer oder sogar Ihren Außenbereich. Jedes Stück wird von Einheimischen in Bali handgefertigt.</p> | P79: White | Q79: Mother-of-pear | R79: Coquille | S79: Concha | T79: Schale | U79: Conchiglia | V79: Blanc | W79: Blanco | X79: Bianco | Y79: Weiss | Z79: 40 | AA79: cm | AB79: 25 | AC79: cm | AD79: 4 | AE79: cm | AG79: cm | AT79: Indonesia | AZ79: Sea side | BG79: https://bazarbizar.katanapim.com/content/images/thumbs/0009715_babl022w.webp | BH79: https://bazarbizar.katanapim.com/content/images/thumbs/0009846_babl022w_5.webp | BI79: https://bazarbizar.katanapim.com/content/images/thumbs/0009847_babl022w_6.webp | BJ79: https://bazarbizar.katanapim.com/content/images/thumbs/0009848_babl022w_7.webp | CD79: 25cm x 4cm x 40cm | CG79: https://bazarbizar.katanapim.com/content/images/thumbs/0009713_babl022w_101.webp | CJ79: https://bazarbizar.katanapim.com/content/images/thumbs/0009714_babl022w_100.webp | CM79: https://bazarbizar.katanapim.com/content/images/thumbs/0009712_babl022w_2.webp | EX79: Sea
A80: Decoration/Wall decoration/Decorative plates | B80: BABL023W | C80: =_xlfn.XLOOKUP(B80,Sheet1!A:A,Sheet1!A:A,) -> BABL023W | D80: Décoration murale de coquillages | E80: Decoración mural de conchas | F80: Decorazione murale di conchiglie 25x4 cm | G80: Wanddekoration aus Muscheln | H80: 7438246261276 | I80: BABL023 | J80: Bazar Bizar | K80: Shell | L80: Cet hippocampe dcoratif est entièrement ralis partir de magnifiques coquillages blancs, finis par des franges en raphia. Il s'agit d'un accessoire amusant et joliment ralis que vous pouvez accrocher où bon vous semble. Il sera certainement le sujet de conversation ! | M80: Questo cavalluccio marino decorativo è realizzato completamente con bellissime conchiglie bianche, rifinite con frange di rafia. Si tratta di un accessorio divertente e di ottima fattura che potrete appendere in qualsiasi posto vi piaccia. Sar sicuramente oggetto di conversazione! | N80: Este caballito de mar decorativo está hecho completamente de preciosas conchas blancas, rematadas con flecos de rafia. Se trata de un divertido y bonito accesorio que podrás colgar en cualquier lugar que te apetezca. Seguro que dará mucho que hablar! | O80: Dieses dekorative Seepferdchen ist komplett aus schönen weißen Muscheln gefertigt und mit Fransen aus Bast verziert. Es ist ein lustiges und wunderschönes Accessoire, das Sie an jedem beliebigen Ort aufhängen können. Es wird sicherlich Gesprächsstoff sorgen! | P80: White | Q80: Mother-of-pear | R80: Coquille | S80: Caparazón | T80: Hülse | U80: Conchiglia | V80: Blanc | W80: Blanco | X80: Bianco | Y80: Weiß | Z80: 40 | AA80: cm | AB80: 25 | AC80: cm | AD80: 4 | AE80: cm | AG80: cm | AT80: Indonesia | BG80: https://bazarbizar.katanapim.com/content/images/thumbs/001/0019892_the-shell-sea-horse-white.jpeg | BH80: https://bazarbizar.katanapim.com/content/images/thumbs/001/0019895_the-shell-sea-horse-white.jpeg | BI80: https://bazarbizar.katanapim.com/content/images/thumbs/001/0019891_the-shell-sea-horse-white.jpeg | BJ80: https://bazarbizar.katanapim.com/content/images/thumbs/001/0019893_the-shell-sea-horse-white.jpeg | CA80: Bazar Bizar | CB80: 2550 | CD80: 25 x 4 x 40 cm | CG80: https://bazarbizar.katanapim.com/content/images/thumbs/001/0019897_the-shell-sea-horse-white.jpeg | CJ80: https://bazarbizar.katanapim.com/content/images/thumbs/001/0019896_the-shell-sea-horse-white.jpeg | CM80: https://bazarbizar.katanapim.com/content/images/thumbs/001/0019899_the-shell-sea-horse-white.jpeg | EX80: Sea
A81: Indoor lighting/Indoor pendant lights | B81: BABL026B | C81: =_xlfn.XLOOKUP(B81,Sheet1!A:A,Sheet1!A:A,) -> BABL026B | D81: Suspension bois et fer noir 48x48x27cm | E81: Lámpara colgante de madera y hierro en negro 48x48x27 cm | F81: Lampada a sospensione in legno e ferro nero 48x48x27 cm | G81: Pendelleuchte aus Holz und Eisen in schwarz 48 x 48 x 27 cm | H81: 6097312323396 | I81: BABL026 | J81: Bazar Bizar | K81: Wooden | L81: <p>La Suspension Wooden Bead Dome s’exprime par la forme et la texture. En tant que suspension décorative noire, elle attire le regard par sa courbe douce et sa finition mate. Des couches de perles en bois sculptées à la main reposent sur une base en fer solide, laissant filtrer la lumière à travers le motif pour créer une atmosphère douce.</p> <p>Qu’elle éclaire une salle à manger ou un coin lecture, elle ancre l’espace dans une chaleur naturelle et une sobriété intemporelle. Son design célèbre l’ombre, le contraste et la beauté de l’imperfection artisanale.</p> <p>Fabriquée en petites séries par des artisans indonésiens, elle reflète un dialogue entre tradition et design moderne. Le rythme du travail manuel perdure dans chaque courbe et surface.</p> <p><span>Ce produit est conçu uniquement pour une utilisation en intérieur. Une utilisation en extérieur, même dans des zones couvertes, peut entraîner des dommages dus à l’humidité ou aux conditions météorologiques et n’est pas couverte par la garantie. Les images montrant une utilisation en extérieur sont uniquement destinées à des fins de mise en scène.</span></p> | M81: <p>La lampada a sospensione in perline di legno parla attraverso forma e texture. Come lampada decorativa nera, cattura lo sguardo con la sua curva delicata e la finitura opaca.&nbsp;</p> <p>Strati di perline di legno intagliate a mano poggiano su una solida base in ferro, lasciando filtrare la luce in modo morbido e creando un’atmosfera accogliente. Che illumini una sala da pranzo o un angolo lettura, dona calore naturale e sobria eleganza allo spazio. Il design celebra ombra, contrasto e la bellezza dell’imperfezione artigianale.</p> <p>Realizzata a mano in piccole serie da artigiani indonesiani, riflette un dialogo tra tradizione e design moderno. Il ritmo del lavoro manuale vive in ogni curva e superficie.</p> <p><span>Questo prodotto è progettato esclusivamente per uso interno. L’utilizzo all’esterno, anche in aree coperte, può causare danni dovuti all’umidità o alle condizioni atmosferiche e non è coperto da garanzia. Le immagini che mostrano l’uso all’esterno sono solo a scopo illustrativo.</span></p> | N81: <p>La Lámpara Colgante Wooden Bead Dome habla en forma y textura. Como lámpara decorativa negra, atrae la mirada con su suave curva y su acabado mate.</p> <p>Capas de cuentas de madera talladas a mano descansan sobre una base de hierro resistente, permitiendo que la luz se filtre suavemente creando atmósfera sin deslumbrar. Ya sea iluminando un comedor o colgando sobre un rincón de lectura, aporta calidez natural y elegancia atemporal.</p> <p>Su diseño celebra la sombra, el contraste y la belleza de la imperfección artesanal. Hecha a mano por artesanos en Indonesia, refleja el diálogo entre la tradición y el diseño moderno. El ritmo del trabajo manual perdura en cada curva y superficie.</p> <p><span>Este producto está diseñado únicamente para uso en interiores. El uso en exteriores, incluso en áreas cubiertas, puede causar daños debido a la humedad o a las condiciones climáticas y no está cubierto por la garantía. Las imágenes que muestran uso en exteriores son solo para fines de estilismo.</span></p> | O81: <p>Die Wooden Bead Dome Pendelleuchte spricht in Form und Textur. Als schwarze dekorative Pendelleuchte zieht sie mit sanfter Kurve und matter Oberfläche die Blicke auf sich.</p> <p>Schichten handgeschnitzter Holzkugeln ruhen auf einer stabilen Eisenbasis, sodass das Licht weich durch das Muster fällt und Atmosphäre statt Blendung schafft. Ob über einem Esstisch oder einer Leseecke, sie verleiht dem Raum natürliche Wärme und zeitlose Eleganz.</p> <p>Das Design feiert Schatten, Kontraste und die Schönheit handwerklicher Unvollkommenheit. In kleinen Serien von indonesischen Handwerkern gefertigt, spiegelt sie den Dialog zwischen Tradition und modernem Design wider. Der Rhythmus des Handwerks lebt in jeder Kurve weiter.</p> <p><span>Dieses Produkt ist ausschließlich für den Innenbereich vorgesehen. Die Verwendung im Außenbereich, auch in überdachten Bereichen, kann durch Feuchtigkeit oder Witterungseinflüsse Schäden verursachen und ist nicht durch die Garantie abgedeckt. Bilder, die eine Nutzung im Außenbereich zeigen, dienen ausschließlich zu Stylingzwecken.</span></p> | P81: Black | Q81: Wood | Z81: 27 | AA81: cm | AB81: 48 | AC81: cm | AD81: 48 | AE81: cm | AG81: cm | AT81: Indonesia | BG81: https://bazarbizar.katanapim.com/content/images/thumbs/002/0028845_babl026b.jpeg | BH81: https://bazarbizar.katanapim.com/content/images/thumbs/002/0025748_sample-lamp-026-wooden-beads-black.jpeg | BI81: https://bazarbizar.katanapim.com/content/images/thumbs/002/0025754_sample-lamp-026-wooden-beads-black.jpeg | CA81: Bazar Bizar | CB81: 2550 | CD81: 48 x 48 x 27 cm | CG81: https://bazarbizar.katanapim.com/content/images/thumbs/002/0029292_babl026b_100.jpeg | CH81: E27 | CJ81: https://bazarbizar.katanapim.com/content/images/thumbs/002/0029293_babl026b_101.jpeg | CM81: https://bazarbizar.katanapim.com/content/images/thumbs/002/0025751_sample-lamp-026-wooden-beads-black.jpeg | CN81: w | EY81: Battery not supplied | FE81: Electric | FN81: 1 bulb
A82: Indoor lighting/Indoor pendant lights | B82: BABL026N | C82: =_xlfn.XLOOKUP(B82,Sheet1!A:A,Sheet1!A:A,) -> BABL026N | D82: Suspension bois et fer marron 48x48x27cm | E82: Lámpara colgante de madera y hierro en marrón 48x48x27 cm | F82: Lampada a sospensione in legno e ferro marrone 48x48x27 cm | G82: Pendelleuchte aus Holz und Eisen in braun, 48 x 48 x 27 cm | H82: 6097312323327 | I82: BABL026 | J82: Bazar Bizar | K82: Wooden | L82: <p>La Suspension Wooden Bead Dome allie lumière et texture. Cette suspension décorative naturelle incarne l’équilibre et la simplicité. Sa silhouette en dôme diffuse une lumière douce à travers des rangées de perles de bois lisses, créant une lueur tamisée rappelant les matins côtiers.</p> <p>L’effet est à la fois ancré et aérien, rehaussant les espaces empreints de calme et d’authenticité. Idéale pour les grands espaces, les salles à manger ou les plafonds hauts, cette suspension tressée à la main apporte une chaleur subtile sans dominer la pièce.</p> <p>Ses tons neutres s’accordent parfaitement avec les fibres naturelles et les textures minérales. Fabriquée à la main à Bali, chaque pièce reflète le rythme de l’artisan. Chaque perle est enfilée à la main, chaque courbe façonnée avec patience, révélant des variations subtiles qui rendent chaque lampe unique.</p> <p><span>Ce produit est conçu uniquement pour une utilisation en intérieur. Une utilisation en extérieur, même dans des zones couvertes, peut entraîner des dommages dus à l’humidité ou aux conditions météorologiques et n’est pas couverte par la garantie. Les images montrant une utilisation en extérieur sont uniquement destinées à des fins de mise en scène.</span></p> | M82: <p>Luce e texture si intrecciano nella lampada a sospensione in perline di legno, una lampada naturale che incarna equilibrio e semplicità. La silhouette a cupola diffonde la luce attraverso file di perline di legno lisce, creando un bagliore soffuso che ricorda le mattine costiere.</p> <p>L’effetto è insieme radicato e leggero, valorizzando gli ambienti che celebrano calma e autenticità. Ideale per ampi spazi abitativi, sale da pranzo o soffitti alti, questa lampada intrecciata a mano introduce calore senza dominare la stanza. Le tonalità neutre si abbinano perfettamente a fibre naturali e texture in pietra.</p> <p>Realizzata a mano a Bali, ogni pezzo riflette il ritmo dell’artigiano. Ogni perlina è infilata a mano e ogni curva modellata con pazienza, con sottili variazioni che rendono ogni lampada unica.</p> <p><span>Questo prodotto è progettato esclusivamente per uso interno. L’utilizzo all’esterno, anche in aree coperte, può causare danni dovuti all’umidità o alle condizioni atmosferiche e non è coperto da garanzia. Le immagini che mostrano l’uso all’esterno sono solo a scopo illustrativo.</span></p> | N82: <p>Luz y textura se entrelazan en La Lámpara Colgante Wooden Bead Dome, una lámpara decorativa natural que encarna el equilibrio y la sencillez. Su silueta abovedada difunde la luz a través de filas de cuentas de madera lisa, creando un resplandor suave que recuerda a las mañanas costeras.&nbsp;</p> <p>El efecto es a la vez natural y etéreo, realzando los espacios con calma y autenticidad. Ideal para áreas abiertas, comedores o techos altos, esta lámpara colgante tejida a mano aporta calidez sin abrumar. Sus tonos neutros combinan perfectamente con fibras naturales y texturas de piedra.</p> <p>Hecha a mano en Bali, cada pieza refleja el ritmo del artesano. Cada cuenta está ensartada a mano y cada curva moldeada con paciencia, mostrando variaciones sutiles que la hacen única.</p> <p><span>Este producto está diseñado únicamente para uso en interiores. El uso en exteriores, incluso en áreas cubiertas, puede causar daños debido a la humedad o a las condiciones climáticas y no está cubierto por la garantía. Las imágenes que muestran uso en exteriores son solo para fines de estilismo.</span></p> | O82: <p>Licht und Struktur verschmelzen in der Wooden Bead Dome Pendelleuchte, einer natürlichen dekorativen Lampe, die Gleichgewicht und Schlichtheit verkörpert. Die kuppelförmige Silhouette lässt das Licht durch glatte Holzkugeln strömen und erzeugt einen weichen Schimmer, der an ruhige Morgen am Meer erinnert.&nbsp;</p> <p>Der Effekt ist sowohl geerdet als auch luftig und verleiht Räumen Ruhe und Authentizität. Ideal für offene Wohnbereiche, Esszimmer oder hohe Decken, bringt diese handgewebte Pendelleuchte Wärme in den Raum, ohne ihn zu dominieren. Ihre neutralen Töne harmonieren perfekt mit Naturfasern und Steinelementen.</p> <p>Handgefertigt auf Bali, spiegelt jedes Stück den Rhythmus des Handwerkers wider. Jede Perle wird einzeln aufgefädelt und jede Kurve sorgfältig geformt, wodurch feine Unterschiede entstehen, die jedes Exemplar einzigartig machen.</p> <p><span>Dieses Produkt ist ausschließlich für den Innenbereich vorgesehen. Die Verwendung im Außenbereich, auch in überdachten Bereichen, kann durch Feuchtigkeit oder Witterungseinflüsse Schäden verursachen und ist nicht durch die Garantie abgedeckt. Bilder, die eine Nutzung im Außenbereich zeigen, dienen ausschließlich zu Stylingzwecken.</span></p> | P82: Beige | Q82: Wood | Z82: 27 | AA82: cm | AB82: 48 | AC82: cm | AD82: 48 | AE82: cm | AG82: cm | AT82: Indonesia | BG82: https://bazarbizar.katanapim.com/content/images/thumbs/002/0028846_babl026n.jpeg | BH82: https://bazarbizar.katanapim.com/content/images/thumbs/002/0025761_the-wooden-bead-dome-pendant-natural.jpeg | CA82: Bazar Bizar | CB82: 2550 | CD82: 48 x 48 x 27 cm | CG82: https://bazarbizar.katanapim.com/content/images/thumbs/002/0029294_babl026n_100.jpeg | CH82: E27 | CJ82: https://bazarbizar.katanapim.com/content/images/thumbs/002/0025759_the-wooden-bead-dome-pendant-natural.jpeg | CM82: https://bazarbizar.katanapim.com/content/images/thumbs/002/0025758_the-wooden-bead-dome-pendant-natural.jpeg | CN82: w | EY82: Battery not supplied | FE82: Electric | FN82: 1 bulb
A83: Lifestyle/Bags/Tote bags | B83: BABOM008N | C83: =_xlfn.XLOOKUP(B83,Sheet1!A:A,Sheet1!A:A,) -> BABOM008N | D83: Sac raphia marron 50x20x38cm | E83: Bolsa de rafia en marrón 50x20x38 cm | F83: Borsa in rafia marrone 50x20x38 cm | G83: Tasche aus Raffia in braun, 50 x 20 x 38 cm | H83: 7438246266202 | I83: BABOM008 | J83: Bazar Bizar | K83: Ti amo | L83: Le Ti Amo Shopper est un sac idéal pour tous les jours, parfait pour une sortie à la plage ou une journée de shopping. Son design léger et robuste est parfait pour se promener en ville, tandis que l’intérieur spacieux, facilement accessible grâce à la large ouverture supérieure, accueillera tout ce dont vous avez besoin. Fabriqué en magnifique raphia, c’est un sac souple qui brillera sur vos épaules. | M83: La shopper Ti Amo è una borsa ideale per tutti i giorni, perfetta per una gita in spiaggia o una giornata di shopping. Il design leggero e robusto è perfetto per passeggiare in città, mentre l’interno spazioso, facilmente accessibile grazie all’ampia apertura superiore, può contenere tutto ciò di cui avete bisogno. Realizzata in splendida rafia, è una borsa flessibile che brillerà sulle vostre spalle. | N83: El Ti Amo Shopper es un bolso ideal para el día a día, perfecto para ir a la playa o de compras. Su diseño ligero y resistente es perfecto para pasear por la ciudad, mientras que su espacioso interior, fácilmente accesible gracias a la amplia abertura superior, ofrece lugar para todo lo que necesites. Fabricado con preciosa rafia, es un bolso flexible que lucirá sobre tus hombros. | O83: Die Ti Amo Tragetasche ist eine großartige Alltagstasche, perfekt für einen Strandtag oder zum Einkaufen. Das leichte und robuste Design eignet sich ideal für einen Stadtbummel, während das geräumige Innere mit breiter Öffnung Platz für alles bietet, was Sie brauchen. Hergestellt aus schöner Rafia, eine flexible Tasche, die auf Ihrer Schulter glänzt. | P83: Beige | Q83: Natural fibers | Z83: 38 | AA83: cm | AB83: 50 | AC83: cm | AD83: 20 | AE83: cm | AG83: cm | AT83: Indonesia | BG83: https://bazarbizar.katanapim.com/content/images/thumbs/002/0023045_the-ti-amo-shopper.jpeg | BH83: https://bazarbizar.katanapim.com/content/images/thumbs/002/0023041_the-ti-amo-shopper.jpeg | BI83: https://bazarbizar.katanapim.com/content/images/thumbs/002/0020107_the-ti-amo-shopper.jpeg | BJ83: https://bazarbizar.katanapim.com/content/images/thumbs/002/0023044_the-ti-amo-shopper.jpeg | BK83: https://bazarbizar.katanapim.com/content/images/thumbs/001/0019775_the-ti-amo-shopper.jpeg | CA83: Bazar Bizar | CB83: 2550 | CD83: 50 x 20 x 38 cm | CG83: https://bazarbizar.katanapim.com/content/images/thumbs/002/0023043_the-ti-amo-shopper.jpeg | CJ83: https://bazarbizar.katanapim.com/content/images/thumbs/001/0018564_the-ti-amo-shopper.jpeg | CM83: https://bazarbizar.katanapim.com/content/images/thumbs/002/0023046_the-ti-amo-shopper.jpeg | DD83: Without pattern
A84: Lifestyle/Bags/Tote bags | B84: BABOM010B-L | C84: =_xlfn.XLOOKUP(B84,Sheet1!A:A,Sheet1!A:A,) -> BABOM010B-L | D84: Sac cuir noir 48x13x63cm | E84: Bolsa de piel en negro 48x13x63 cm | F84: Borsa in pelle nera 48x13x63 cm | G84: Ledertasche in schwarz 48 x 13 x 63 cm | H84: 6097314184186 | I84: BABOM010 | J84: Bazar Bizar | K84: Execu-shopper | L84: L’Execu-Shopper est un cabas raffiné en cuir noir conçu pour allier solidité et élégance discrète.Ses lignes épurées et sa grande taille en font un accessoire aussi pratique qu’élégant.Idéal pour transporter l’essentiel, il est assez grand pour ordinateurs, documents ou affaires du week-end, tout en restant léger et agréable à porter.L’extérieur lisse en cuir garde sa forme, assurant résistance et modernité.Chaque sac est fabriqué à la main par des artisans, où les techniques traditionnelles rencontrent un design contemporain.De légères variations de grain et de finition confèrent un caractère unique à chaque modèle. | M84: Questa borsa capiente in pelle nera è progettata per unire resistenza ed eleganza sobria. Le linee pulite e le dimensioni generose la rendono un accessorio tanto pratico quanto raffinato. Perfetta per trasportare tutto il necessario, è abbastanza spaziosa per laptop, documenti o oggetti da weekend, rimanendo leggera e comoda. L’esterno liscio in pelle mantiene la forma, garantendo durata senza perdere il fascino moderno. Ogni borsa è realizzata a mano da artigiani, dove le tecniche tradizionali incontrano il design contemporaneo. Leggere variazioni di grana e finitura sottolineano l’unicità di ogni pezzo. | N84: <p><span>El Execu-Shopper es un bolso shopper de cuero negro refinado, diseñado para equilibrar durabilidad con elegancia discreta. Sus líneas limpias y tamaño generoso lo convierten en un accesorio tan práctico como elegante.<br><br>Perfectamente confeccionado para llevar lo esencial, es lo bastante amplio para portátiles, documentos o artículos de fin de semana, manteniéndose ligero y cómodo. El exterior de cuero liso conserva su forma y garantiza resistencia sin perder su atractivo moderno.<br><br>Cada bolso está hecho a mano por artesanos, donde las técnicas tradicionales se unen al diseño contemporáneo. Ligeras variaciones en el grano y acabado destacan su individualidad.</span></p> | O84: <p><span>Der Execu-Shopper ist eine raffinierte schwarze Ledershopper Tasche, entworfen um Langlebigkeit mit schlichter Eleganz zu verbinden. Seine klaren Linien und großzügige Größe machen ihn zu einem Accessoire, das ebenso praktisch wie elegant ist.<br><br>Perfekt gefertigt, um Alltagsutensilien zu tragen, groß genug für Laptops, Dokumente oder Wochenendbedarf, und dennoch leicht und bequem. Das glatte Leder behält seine Form und garantiert Widerstandsfähigkeit ohne modernen Charme zu verlieren.<br><br>Jede Tasche wird von Hand gefertigt, wo traditionelle Techniken auf modernes Design treffen. Subtile Unterschiede in Narbung und Finish machen jedes Stück einzigartig.</span></p> | P84: Black | Q84: Leather split leather | Z84: 63 | AA84: cm | AB84: 48 | AC84: cm | AD84: 13 | AE84: cm | AG84: cm | AT84: Indonesia | BG84: https://bazarbizar.katanapim.com/content/images/thumbs/002/0027545_babom010b-l.jpeg | BH84: https://media-prod-eu-1.mirakl.net/SOURCE/aa8efd325e5248a5b546d4dc8ac5411a | CA84: Bazar Bizar | CB84: 2550 | CD84: 48 x 13 x 63 cm | CG84: https://media-prod-eu-1.mirakl.net/SOURCE/6b4319500180410c927c40fcc8a3dc57 | CJ84: https://media-prod-eu-1.mirakl.net/SOURCE/429e7577e44d46bf9ee2a0fa12e9fe4c | CM84: https://media-prod-eu-1.mirakl.net/SOURCE/8aeecb928468413ba3c1e81dc843dc04 | DD84: Without pattern
A85: Lifestyle/Bags/Tote bags | B85: BABOM010B-M | C85: =_xlfn.XLOOKUP(B85,Sheet1!A:A,Sheet1!A:A,) -> BABOM010B-M | D85: Sac cuir noir 36x10x48cm | E85: Bolsa de piel en negro 36x10x48 cm | F85: Borsa in pelle nera 36x10x48 cm | G85: Ledertasche in schwarz, 36 x 10 x 48 cm | H85: 6097314185114 | I85: BABOM010 | J85: Bazar Bizar | K85: Shortlist | L85: Le Shortlist Shopper apporte une confiance discrète à votre style quotidien, conçu pour ceux qui apprécient la praticité et le raffinement. Au cœur réside l’essence d’un sac shopper en cuir fait main, pensé pour associer fonction et silhouette élégante. De taille moyenne, son intérieur spacieux accueille carnets, tablettes ou essentiels du quotidien. L’extérieur structuré en cuir conserve sa forme, tandis que la finition lisse assure polyvalence, aussi bien pour le bureau, un déjeuner décontracté ou le week-end. Chaque sac est fabriqué artisanalement, laissant apparaître de légères variations de grain et de texture. Ces détails font de chaque pièce une expression intemporelle de savoir-faire. | M85: Questa borsa in pelle di medie dimensioni porta una fiducia discreta allo stile quotidiano, pensata per chi apprezza praticità e raffinatezza. Al suo cuore vi è l’essenza di una borsa artigianale creata per unire funzione ed eleganza. L’interno è spazioso e accoglie quaderni, tablet o oggetti di uso quotidiano. L’esterno strutturato in pelle mantiene la forma, mentre la finitura liscia garantisce versatilità, adatta all’ufficio, ai pranzi o alle commissioni. Ogni borsa è realizzata a mano, con variazioni sottili nella grana e nella tessitura che rivelano la mano artigiana. Questi dettagli rendono ogni pezzo unico e senza tempo. | N85: <p><span>El Shortlist Shopper aporta confianza tranquila a tu estilo diario, diseñado para quienes valoran la practicidad y la sofisticación. En su esencia está el bolso shopper de cuero hecho a mano, creado para unir función y una silueta elegante.<br><br>Aunque de tamaño medio, su interior es amplio para cuadernos, tabletas o lo necesario a diario. El exterior de cuero estructurado mantiene la forma, y el acabado liso asegura versatilidad para reuniones, comidas informales o recados.<br><br>Cada bolso está cuidadosamente hecho a mano, mostrando variaciones sutiles en grano y textura. Estos detalles artesanales convierten cada pieza en una expresión atemporal de artesanía.</span></p> | O85: <p><span>Der Shortlist Shopper bringt leises Selbstvertrauen in Ihren Alltag, entworfen für alle, die sowohl Zweckmäßigkeit als auch Eleganz schätzen. Im Kern liegt die Essenz einer handgefertigten Ledershopper Tasche, geschaffen, um Funktion und Silhouette zu vereinen.<br><br>Obwohl mittelgroß, ist das Innere geräumig genug für Notizbücher, Tablets oder Alltagsutensilien. Das strukturierte Leder behält seine Form, während die glatte Oberfläche Vielseitigkeit garantiert, für Büro, Mittagspausen oder Wochenenden.<br><br>Jede Tasche ist sorgfältig handgefertigt, wobei subtile Unterschiede in Narbung und Textur zum Ausdruck kommen. Diese Details machen jedes Stück einzigartig und zeitlos.</span></p> | P85: Black | Q85: Leather split leather | Z85: 48 | AA85: cm | AB85: 36 | AC85: cm | AD85: 10 | AE85: cm | AG85: cm | AT85: Indonesia | BG85: https://bazarbizar.katanapim.com/content/images/thumbs/002/0027551_babom010b-m.jpeg | BH85: https://media-prod-eu-1.mirakl.net/SOURCE/43fc30b4dd2a49a5aeb8c86621efd933 | CA85: Bazar Bizar | CB85: 2550 | CD85: 36 x 10 x 48 cm | CG85: https://media-prod-eu-1.mirakl.net/SOURCE/1292441bd2fe4b6b883a931bd8738aeb | CJ85: https://media-prod-eu-1.mirakl.net/SOURCE/5790e08a2cfe4151ae244f8f606f7a7a | CM85: https://media-prod-eu-1.mirakl.net/SOURCE/8297138d5696451c8a09d1b8e13a45f5 | DD85: Without pattern
A86: Tableware and kitchen accessories/Dishes/Flatware/Tablespoon | B86: BABRA001G | C86: =_xlfn.XLOOKUP(B86,Sheet1!A:A,Sheet1!A:A,) -> BABRA001G | D86: Cuillère à salade laiton or 26x6x1cm | E86: Cuchara para ensalada de latón en dorado 26x6x1 cm | F86: Cucchiaio da insalata in ottone oro 26x6x1 cm | G86: Salatlöffel aus Messing in Gold 26 x 6 x 1 cm | H86: 7438246260200 | I86: BABRA001 | J86: Bazar Bizar | K86: Pineapple | L86: Voici notre première collection de couverts, jolie et brillante ! Ces fourchettes et cuillères sont un vrai luxe, fabriquées en laiton massif avec de magnifiques détails. Vos invités seront impressionnés par leur poids et leur qualité. Chaque pièce est décorée d’un ananas ou d’un palmier, impossible de faire plus tropical ! Disponibles en plusieurs tailles et designs. | M86: È arrivata la nostra prima collezione di posate, ed è splendida e brillante! Queste forchette e cucchiai sono puro lusso, realizzati in ottone massiccio con dettagli straordinari. I tuoi ospiti saranno colpiti dal peso e dalla qualità di questi must-have. Ogni pezzo è decorato con un’ananas o una palma, più tropicale di così non si può. Disponibili in varie misure e design. | N86: Nuestra primera colección de cubiertos ha llegado y es hermosa y brillante. Estos tenedores y cucharas son puro lujo, fabricados en latón macizo con detalles increíbles. Tus invitados quedarán impresionados por el peso y la calidad de estas piezas imprescindibles. Cada pieza está decorada con una piña o una palmera, más tropical imposible. Disponibles en varios tamaños y diseños. | O86: Unsere erste Besteckkollektion ist da, hübsch und glänzend! Diese Gabeln und Löffel sind purer Luxus, aus massivem Messing gefertigt mit wunderschönen Details. Ihre Gäste werden vom Gewicht und der Qualität begeistert sein. Jedes Teil ist mit einer Ananas oder einer Palme verziert, tropischer geht’s nicht. Erhältlich in verschiedenen Größen und Designs. | P86: Gold | Q86: Metal | Z86: 1 | AA86: cm | AB86: 26 | AC86: cm | AD86: 6 | AE86: cm | AG86: cm | AT86: Indonesia | BG86: https://bazarbizar.katanapim.com/content/images/thumbs/002/0028694_babra001g.jpeg | CA86: Bazar Bizar | CB86: 2550 | CD86: 26 x 6 x 1 cm | CG86: https://bazarbizar.katanapim.com/content/images/thumbs/001/0016477_the-pineapple-salad-spoon-gold.jpeg | CJ86: https://bazarbizar.katanapim.com/content/images/thumbs/001/0016479_the-pineapple-salad-spoon-gold.jpeg | CM86: https://bazarbizar.katanapim.com/content/images/thumbs/001/0016478_the-pineapple-salad-spoon-gold.jpeg | DD86: Without pattern | FQ86: Artisanal
A87: Tableware and kitchen accessories/Dishes/Flatware/Fork | B87: BABRA002G | C87: =_xlfn.XLOOKUP(B87,Sheet1!A:A,Sheet1!A:A,) -> BABRA002G | D87: Fourchette à salade laiton or 26x6x1cm | E87: Tenedor para ensalada de latón en dorado 26x6x1 cm | F87: Forchetta da insalata in ottone oro 26x6x1 cm | G87: Salatgabel aus Messing in Gold 26 x 6 x 1 cm | H87: 7438246260217 | I87: BABRA002 | J87: Bazar Bizar | K87: Pineapple | L87: Voici notre première collection de couverts, jolie et brillante ! Ces fourchettes et cuillères sont un vrai luxe, fabriquées en laiton massif avec de magnifiques détails. Vos invités seront impressionnés par leur poids et leur qualité. Chaque pièce est décorée d’un ananas ou d’un palmier, impossible de faire plus tropical ! Disponibles en plusieurs tailles et modèles. | M87: È arrivata la nostra prima collezione di posate ed è splendida e brillante. Queste forchette e cucchiai sono puro lusso, realizzati in ottone massiccio con dettagli straordinari. I tuoi ospiti saranno colpiti dal peso e dalla qualità di questi must-have. Ogni pezzo è decorato con un’ananas o una palma, più tropicale di così non si può. Disponibili in varie misure e modelli. | N87: Nuestra primera colección de cubiertos ha llegado y es hermosa y brillante. Estos tenedores y cucharas son puro lujo, fabricados en latón macizo con detalles increíbles. Tus invitados quedarán impresionados por el peso y la calidad de estos imprescindibles. Cada pieza está decorada con una piña o una palmera, no puede ser más tropical. Disponibles en varios tamaños y diseños. | O87: Unsere erste Besteckkollektion ist da, hübsch und glänzend! Diese Gabeln und Löffel sind purer Luxus, aus massivem Messing gefertigt mit wundervollen Details. Ihre Gäste werden vom Gewicht und der Qualität dieser echten Messingstücke begeistert sein. Jedes Teil ist mit einer Ananas oder einer Palme verziert, tropischer geht’s nicht. Erhältlich in verschiedenen Größen und Designs. | P87: Gold | Q87: Metal | Z87: 1 | AA87: cm | AB87: 26 | AC87: cm | AD87: 6 | AE87: cm | AG87: cm | AT87: Indonesia | BG87: https://bazarbizar.katanapim.com/content/images/thumbs/002/0028696_babra002g.jpeg | CA87: Bazar Bizar | CB87: 2550 | CD87: 26 x 6 x 1 cm | CG87: https://bazarbizar.katanapim.com/content/images/thumbs/000/0000654_the-pineapple-tea-spoon-gold.jpeg | DD87: Without pattern | FQ87: Artisanal
A88: Tableware and kitchen accessories/Dishes/Flatware/Tablespoon | B88: BABRA003G | C88: =_xlfn.XLOOKUP(B88,Sheet1!A:A,Sheet1!A:A,) -> BABRA003G | D88: Cuillère à salade en laiton doré 26 x 6 x 1 cm | E88: Cuchara para ensalada de latón en dorado 26x6x1 cm | F88: Cucchiaio da insalata in ottone oro 26x6x1 cm | G88: Salatlöffel aus Messing in Goldoptik, 26 × 6 × 1 cm | H88: 7438246260224 | I88: BABRA003 | J88: Bazar Bizar | K88: Palm tree | L88: Notre première collection de couverts est arrivée et elle est belle et brillante. Ces fourchettes et cuillères sont un pur luxe, fabriquées en laiton massif avec de magnifiques détails. Vos invités seront impressionnés par le poids et la qualité de ces incontournables en laiton véritable. Chaque pièce est décorée d’un ananas ou d’un palmier, rien de plus tropical. Disponibles en plusieurs tailles et modèles. | M88: La nostra prima collezione di posate è arrivata ed è splendida e brillante. Queste forchette e cucchiai sono puro lusso, realizzati in ottone massiccio con dettagli meravigliosi. I vostri ospiti saranno colpiti dal peso e dalla qualità di questi pezzi in vero ottone. Tutti i pezzi sono decorati con un ananas o una palma, più tropicale di così non si può. Disponibili in varie dimensioni e design. | N88: Nuestra primera colección de cubiertos ya está aquí y es bonita y brillante. Estos tenedores y cucharas son puro lujo, fabricados en latón macizo con detalles increíbles. Sus invitados quedarán impresionados por el peso y la calidad de estas piezas de auténtico latón. Todas las piezas están decoradas con una piña o una palmera, no puede ser más tropical. Disponibles en varios tamaños y diseños. | O88: Unsere erste Besteckkollektion ist da, und sie ist schön und glänzend. Diese Gabeln und Löffel sind purer Luxus, gefertigt aus massivem Messing mit wunderbaren Details. Ihre Gäste werden vom Gewicht und der Qualität dieser echten Messing-Must-haves beeindruckt sein. Alle Stücke sind mit einer Ananas oder einer Palme verziert, tropischer geht nicht. Erhältlich in verschiedenen Größen und Designs. | P88: Gold | Q88: Metal | Z88: 1 | AA88: cm | AB88: 26 | AC88: cm | AD88: 6 | AE88: cm | AG88: cm | AT88: Indonesia | BG88: https://bazarbizar.katanapim.com/content/images/thumbs/002/0028702_babra003g.jpeg | BH88: https://bazarbizar.katanapim.com/content/images/thumbs/002/0021854_the-palm-tree-salad-spoon-gold.jpeg | BI88: https://bazarbizar.katanapim.com/content/images/thumbs/002/0021858_the-burned-tapas-spoon.jpeg | BJ88: https://bazarbizar.katanapim.com/content/images/thumbs/002/0021856_the-palm-tree-salad-spoon-gold.jpeg | CA88: Bazar Bizar | CB88: 2550 | CD88: 26 x 6 x 1 cm | CG88: https://bazarbizar.katanapim.com/content/images/thumbs/002/0021366_the-palm-tree-salad-spoon-gold.jpeg | CJ88: https://bazarbizar.katanapim.com/content/images/thumbs/002/0021839_the-palm-tree-salad-spoon-gold.jpeg | CM88: https://bazarbizar.katanapim.com/content/images/thumbs/002/0021857_the-palm-tree-salad-spoon-gold.jpeg | DD88: Without pattern | FQ88: Artisanal
A89: Tableware and kitchen accessories/Dishes/Flatware/Fork | B89: BABRA004G | C89: =_xlfn.XLOOKUP(B89,Sheet1!A:A,Sheet1!A:A,) -> BABRA004G | D89: Fourchette à salade en laiton doré 26 x 6 x 1 cm | E89: Tenedor para ensalada de latón en dorado 26x6x1 cm | F89: Forchetta da insalata in ottone oro 26x6x1 cm | G89: Salatgabel aus Messing in Goldoptik, 26 × 6 × 1 cm | H89: 7438246260231 | I89: BABRA004 | J89: Bazar Bizar | K89: Palm tree | L89: Notre première collection de couverts est arrivée et elle est magnifique et brillante. Ces fourchettes et cuillères sont un luxe pur, réalisées en laiton massif avec de superbes détails. Vos invités seront impressionnés par le poids et la qualité de ces indispensables en laiton véritable. Toutes les pièces sont ornées d’un ananas ou d’un palmier, plus tropical, impossible. Disponibles en plusieurs tailles et modèles. | M89: La nostra prima collezione di posate è arrivata ed è splendida e lucente. Queste forchette e cucchiai sono puro lusso, realizzati in ottone massiccio con dettagli straordinari. I vostri ospiti saranno colpiti dal peso e dalla qualità di queste posate in vero ottone. Tutti i pezzi sono decorati con un ananas o una palma, più tropicale di così non si può. Disponibili in varie dimensioni e modelli. | N89: Nuestra primera colección de cubiertos ya está aquí y es bonita y brillante. Estos tenedores y cucharas son puro lujo, fabricados en latón macizo con detalles increíbles. Sus invitados quedarán impresionados por el peso y la calidad de estos imprescindibles de latón auténtico. Todas las piezas están decoradas con una piña o una palmera, más tropical imposible. Disponibles en varios tamaños y diseños. | O89: Unsere erste Besteckkollektion ist da und sie ist wunderschön und glänzend. Diese Gabeln und Löffel sind purer Luxus, gefertigt aus massivem Messing mit tollen Details. Ihre Gäste werden vom Gewicht und der Qualität dieser echten Messingteile beeindruckt sein. Alle Stücke sind mit einer Ananas oder Palme verziert, tropischer geht es nicht. Erhältlich in verschiedenen Größen und Ausführungen. | P89: Gold | Q89: Metal | Z89: 1 | AA89: cm | AB89: 26 | AC89: cm | AD89: 6 | AE89: cm | AG89: cm | AT89: Indonesia | BG89: https://bazarbizar.katanapim.com/content/images/thumbs/002/0028701_babra004g.jpeg | CA89: Bazar Bizar | CB89: 2550 | CD89: 26 x 6 x 1 cm | CG89: https://bazarbizar.katanapim.com/content/images/thumbs/002/0021709_the-palm-tree-salad-fork-gold.jpeg | CJ89: https://bazarbizar.katanapim.com/content/images/thumbs/002/0021710_the-palm-tree-salad-fork-gold.jpeg | CM89: https://bazarbizar.katanapim.com/content/images/thumbs/002/0021366_the-palm-tree-salad-spoon-gold.jpeg | DD89: Without pattern | FQ89: Artisanal
A90: Tableware and kitchen accessories/Dishes/Flatware/Fork | B90: BABRA005G | C90: =_xlfn.XLOOKUP(B90,Sheet1!A:A,Sheet1!A:A,) -> BABRA005G | D90: Fourchette laiton or 22x3x1cm | E90: Tenedor de latón en dorado 22x3x1 cm | F90: Forchetta in ottone oro 22x3x1 cm | G90: Gabel aus Messing in Gold 22x3x1cm | H90: 7438246260248 | I90: BABRA005 | J90: Bazar Bizar | K90: Palm tree | L90: Notre première collection de couverts est là et elle est belle et brillante ! Ces fourchettes et cuillères sont un pur luxe, réalisées en laiton massif avec des détails incroyables. Vos invités seront impressionnés par le poids et la qualité de ces couverts en véritable laiton. Toutes les pièces sont décorées d'un ananas ou d'un palmier, rien de plus tropical ! Disponibles en plusieurs tailles et modèles. | M90: La nostra prima collezione di posate è arrivata ed è bella e brillante. Queste forchette e cucchiai sono puro lusso, realizzati in ottone massiccio con dettagli incredibili. I vostri ospiti rimarranno colpiti dal peso e dalla qualità di queste posate in vero ottone. Tutti i pezzi sono decorati con un ananas o una palma, più tropicale di così non si può. Disponibili in varie dimensioni e design. | N90: Nuestra primera colección de cubiertos ya está aquí y es bonita y brillante. Estos tenedores y cucharas son puro lujo, fabricados en latón macizo con detalles increíbles. Sus invitados quedarán impresionados por el peso y la calidad de estos cubiertos de auténtico latón. Todas las piezas están decoradas con una piña o una palmera, más tropical imposible. Disponibles en varios tamaños y diseños. | O90: Unsere erste Besteckkollektion ist da und sie glänzt wunderschön! Diese Gabeln und Löffel sind purer Luxus, gefertigt aus massivem Messing mit erstaunlichen Details. Ihre Gäste werden vom Gewicht und der Qualität dieser echten Messing-Bestecke beeindruckt sein. Alle Stücke sind mit einer Ananas oder einer Palme verziert, tropischer geht es nicht. Erhältlich in verschiedenen Größen und Designs. | P90: Gold | Q90: Metal | Z90: 1 | AA90: cm | AB90: 22 | AC90: cm | AD90: 3 | AE90: cm | AG90: cm | AT90: Indonesia | BG90: https://bazarbizar.katanapim.com/content/images/thumbs/002/0028704_babra005g.jpeg | BH90: https://bazarbizar.katanapim.com/content/images/thumbs/002/0021266_the-palm-tree-fork-gold.jpeg | BI90: https://bazarbizar.katanapim.com/content/images/thumbs/002/0021408_the-palm-tree-spoon-gold.jpeg | CA90: Bazar Bizar | CB90: 2550 | CD90: 22 x 3 x 1 cm | CG90: https://bazarbizar.katanapim.com/content/images/thumbs/002/0021410_the-pineapple-tea-spoon-gold.jpeg | CJ90: https://bazarbizar.katanapim.com/content/images/thumbs/002/0021407_the-palm-tree-fork-gold.jpeg | CM90: https://bazarbizar.katanapim.com/content/images/thumbs/002/0021409_the-palm-tree-spoon-gold.jpeg | DD90: Without pattern | FQ90: Artisanal
A91: Tableware and kitchen accessories/Dishes/Flatware/Fork | B91: BABRA006G | C91: =_xlfn.XLOOKUP(B91,Sheet1!A:A,Sheet1!A:A,) -> BABRA006G | D91: Fourchette en laiton doré 22 x 3 x 1 cm | E91: Tenedor de latón en dorado 22x3x1 cm | F91: Forchetta in ottone oro 22x3x1 cm | G91: Gabel aus Messing in Goldoptik, 22 × 3 × 1 cm | H91: 7438246260255 | I91: BABRA006 | J91: Bazar Bizar | K91: Pineapple | L91: Notre première collection de couverts est arrivée et elle est jolie et brillante ! Ces fourchettes et cuillères sont un pur luxe, fabriquées en laiton massif avec des détails étonnants. Vos invités seront impressionnés par le poids et la qualité de ces indispensables en laiton véritable. Toutes les pièces sont décorées d'un ananas ou d'un palmier, il n'y a pas plus tropical que cela. Disponibles en plusieurs tailles et modèles. | M91: La nostra prima collezione di posate è arrivata ed è bella e brillante. Queste forchette e cucchiai sono puro lusso, realizzati in ottone massiccio con dettagli sorprendenti. I vostri ospiti rimarranno colpiti dal peso e dalla qualità di questi must-have in vero ottone. Tutti i pezzi sono decorati con un ananas o una palma, più tropicale di così non si può. Disponibili in varie dimensioni e design. | N91: Nuestra primera colección de cubiertos ya está aquí, bonita y brillante. Estos tenedores y cucharas son puro lujo, fabricados en latón macizo con detalles increíbles. Sus invitados quedarán impresionados por el peso y la calidad de estos imprescindibles de latón auténtico. Todas las piezas están decoradas con una piña o una palmera, no puede ser más tropical. Disponibles en varios tamaños y diseños. | O91: Unsere erste Besteckkollektion ist da, und sie glänzt wunderschön. Diese Gabeln und Löffel sind purer Luxus, hergestellt aus massivem Messing mit großartigen Details. Ihre Gäste werden vom Gewicht und der Qualität dieser echten Messing-Must-haves beeindruckt sein. Alle Stücke sind mit einer Ananas oder einer Palme verziert, tropischer geht es nicht. Erhältlich in verschiedenen Größen und Designs. | P91: Gold | Q91: Metal | Z91: 1 | AA91: cm | AB91: 22 | AC91: cm | AD91: 3 | AE91: cm | AG91: cm | AT91: Indonesia | BG91: https://bazarbizar.katanapim.com/content/images/thumbs/002/0028707_babra006g.jpeg | BH91: https://bazarbizar.katanapim.com/content/images/thumbs/002/0021285_the-pineapple-fork-gold.jpeg | BI91: https://bazarbizar.katanapim.com/content/images/thumbs/002/0021441_the-pineapple-fork-gold.jpeg | CA91: Bazar Bizar | CB91: 2550 | CD91: 22 x 3 x 1 cm | CG91: https://bazarbizar.katanapim.com/content/images/thumbs/002/0021442_the-cascais-sauce-bowl-s.jpeg | CJ91: https://bazarbizar.katanapim.com/content/images/thumbs/002/0021440_the-pineapple-fork-gold.jpeg | CM91: https://bazarbizar.katanapim.com/content/images/thumbs/002/0021443_the-comporta-pasta-plate-l-set-of-4.jpeg | DD91: Without pattern | FQ91: Artisanal
A92: Tableware and kitchen accessories/Dishes/Flatware/Tablespoon | B92: BABRA007G | C92: =_xlfn.XLOOKUP(B92,Sheet1!A:A,Sheet1!A:A,) -> BABRA007G | D92: Cuillère longue laiton or 20x3x1cm | E92: Cuchara larga de latón en dorado 20x3x1 cm | F92: Cucchiaio lungo in ottone oro 20x3x1 cm | G92: Langer Löffel aus Messing in goldfarben 20 x 3 x 1 cm | H92: 7438246260262 | I92: BABRA007 | J92: Bazar Bizar | K92: Palm tree | L92: Voici notre première collection de couverts et elle est jolie et brillante! Ces fourchettes et cuillères sont un vrai luxe, fabriquées en laiton massif avec de magnifiques détails. Vos invités seront impressionnés par leur poids et leur qualité. Chaque pièce est décorée avec un ananas ou un palmier, impossible de faire plus tropical. Disponibles en plusieurs tailles et designs. | M92: È arrivata la nostra prima collezione di posate ed è splendida e brillante! Queste forchette e cucchiai sono puro lusso, realizzati in ottone massiccio con dettagli straordinari. I tuoi ospiti saranno colpiti dal peso e dalla qualità di questi must-have. Ogni pezzo è decorato con un’ananas o una palma, più tropicale di così non si può. Disponibili in varie misure e design. | N92: ¡Nuestra primera colección de cubiertos ya está aquí y es bonita y brillante! Estos tenedores y cucharas son puro lujo, fabricados en latón macizo con detalles increíbles. Tus invitados quedarán impresionados por el peso y la calidad de estas piezas imprescindibles. Cada pieza está decorada con una piña o una palmera, no puede ser más tropical. Disponibles en varios tamaños y diseños. | O92: Unsere erste Besteckkollektion ist da und sie ist hübsch und glänzend! Diese Gabeln und Löffel sind purer Luxus, aus massivem Messing gefertigt und mit wundervollen Details versehen. Ihre Gäste werden vom Gewicht und der Qualität dieser echten Messing-Stücke begeistert sein. Jedes Teil ist mit einer Ananas oder einer Palme verziert, tropischer geht es nicht. Erhältlich in verschiedenen Größen und Designs. | P92: Gold | Q92: Metal | Z92: 1 | AA92: cm | AB92: 20 | AC92: cm | AD92: 3 | AE92: cm | AG92: cm | AT92: Indonesia | BG92: https://bazarbizar.katanapim.com/content/images/thumbs/002/0028710_babra007g.jpeg | CA92: Bazar Bizar | CB92: 2550 | CD92: 20 x 3 x 1 cm | CG92: https://bazarbizar.katanapim.com/content/images/thumbs/002/0021953_the-palm-tree-long-spoon-gold.jpeg | CJ92: https://bazarbizar.katanapim.com/content/images/thumbs/002/0021950_the-palm-tree-long-spoon-gold.jpeg | CM92: https://bazarbizar.katanapim.com/content/images/thumbs/002/0021952_the-palm-tree-long-spoon-gold.jpeg | DD92: Without pattern | FQ92: Artisanal
A93: Tableware and kitchen accessories/Table decorations/Napkin rings | B93: BABRA008G | C93: =_xlfn.XLOOKUP(B93,Sheet1!A:A,Sheet1!A:A,) -> BABRA008G | D93: Rond de serviette laiton or 7x6x5cm | E93: Servilletero de latón en dorado 7x6x5 cm | F93: Portatovagliolo in ottone oro 7x6x5 cm | G93: Serviettenring aus Messing in gold 7 x 6 x 5 cm | H93: 7438246260279 | I93: BABRA008 | J93: Bazar Bizar | K93: Pineapple | L93: Ajoutez une touche de luxe à votre table avec ce rond de serviette ananas en laiton massif. Lourd et riche en détails, il s'accorde parfaitement avec notre collection de couverts en laiton massif, comprenant cuillères et fourchettes. Faites briller votre table pour vos invités. | M93: Aggiungete lusso puro alla vostra tavola con questo portatovagliolo in ottone massiccio. Pesante e dettagliato, si abbina alla nostra collezione di posate in ottone, comprese cucchiai e forchette. Fate risplendere la vostra tavola per gli ospiti. | N93: Añada puro lujo a su mesa con este servilletero de piña en latón macizo. Pesado y lleno de detalles, combina con nuestra colección de cubiertos en latón, que incluye cucharas y tenedores. Haga que su mesa brille para sus invitados. | O93: Bringen Sie puren Luxus auf Ihren Tisch mit diesem Serviettenring in Ananasform aus massivem Messing. Schwer und detailreich, er passt perfekt zu unserer Besteckkollektion aus Messing mit Löffeln und Gabeln. Lassen Sie Ihren Tisch glänzen. | P93: Gold | Q93: Metal | Z93: 5 | AA93: cm | AB93: 7 | AC93: cm | AD93: 6 | AE93: cm | AG93: cm | AT93: Indonesia | BG93: https://bazarbizar.katanapim.com/content/images/thumbs/002/0027464_babra008g.jpeg | BH93: https://bazarbizar.katanapim.com/content/images/thumbs/002/0021605_the-pineapple-napkin-ring-gold.jpeg | BI93: https://bazarbizar.katanapim.com/content/images/thumbs/002/0021609_the-pineapple-napkin-ring-gold.jpeg | CA93: Bazar Bizar | CB93: 2550 | CG93: https://bazarbizar.katanapim.com/content/images/thumbs/002/0021611_the-pineapple-napkin-ring-gold.jpeg | CJ93: https://bazarbizar.katanapim.com/content/images/thumbs/002/0021610_the-pineapple-napkin-ring-gold.jpeg | CM93: https://bazarbizar.katanapim.com/content/images/thumbs/002/0021612_the-pineapple-napkin-ring-gold.jpeg
A94: Tableware and kitchen accessories/Dishes/Flatware/Tablespoon | B94: BABRA009G | C94: =_xlfn.XLOOKUP(B94,Sheet1!A:A,Sheet1!A:A,) -> BABRA009G | D94: Cuillère longue en laiton doré 20 x 3 x 1 cm | E94: Cuchara larga de latón en dorado 20x3x1 cm | F94: Cucchiaio lungo in ottone oro 20x3x1 cm | G94: Langer Löffel aus Messing in Goldoptik, 20 × 3 × 1 cm | H94: 7438246262280 | I94: BABRA009 | J94: Bazar Bizar | K94: Pineapple | L94: Voici notre première collection de couverts, jolie et brillante. Ces fourchettes et cuillères sont un vrai luxe, fabriquées en laiton massif avec de magnifiques détails. Vos invités seront impressionnés par leur poids et leur qualité. Chaque pièce est décorée avec un ananas ou un palmier, impossible de faire plus tropical. Disponibles en plusieurs tailles et designs. | M94: È arrivata la nostra prima collezione di posate, splendida e brillante. Queste forchette e cucchiai sono puro lusso, realizzati in ottone massiccio con dettagli straordinari. I tuoi ospiti saranno colpiti dal peso e dalla qualità di questi pezzi indispensabili. Ogni pezzo è decorato con un’ananas o una palma, più tropicale di così non si può. Disponibili in varie misure e design. | N94: Nuestra primera colección de cubiertos ha llegado y es hermosa y brillante. Estos tenedores y cucharas son puro lujo, fabricados en latón macizo con detalles increíbles. Tus invitados quedarán impresionados por el peso y la calidad de estas piezas imprescindibles. Cada pieza está decorada con una piña o una palmera, más tropical imposible. Disponibles en varios tamaños y diseños. | O94: Unsere erste Besteckkollektion ist da, hübsch und glänzend. Diese Gabeln und Löffel sind purer Luxus, aus massivem Messing gefertigt mit wundervollen Details. Ihre Gäste werden vom Gewicht und der Qualität dieser Messing-Stücke begeistert sein. Jedes Teil ist mit einer Ananas oder einer Palme verziert, tropischer geht es nicht. Erhältlich in verschiedenen Größen und Designs. | P94: Gold | Q94: Metal | Z94: 1 | AA94: cm | AB94: 20 | AC94: cm | AD94: 3 | AE94: cm | AG94: cm | AT94: Indonesia | BG94: https://bazarbizar.katanapim.com/content/images/thumbs/002/0028711_babra009g.jpeg | CA94: Bazar Bizar | CB94: 2550 | CD94: 20 x 3 x 1 cm | CG94: https://bazarbizar.katanapim.com/content/images/thumbs/002/0021977_the-pineapple-long-spoon-gold.jpeg | CJ94: https://bazarbizar.katanapim.com/content/images/thumbs/002/0021978_the-pineapple-long-spoon-gold.jpeg | DD94: Without pattern | FQ94: Artisanal
A95: Tableware and kitchen accessories/Dishes/Flatware/Tablespoon | B95: BABRA010G | C95: =_xlfn.XLOOKUP(B95,Sheet1!A:A,Sheet1!A:A,) -> BABRA010G | D95: Cuillère laiton or 22x4x1cm | E95: Cuchara de latón en dorado 22x4x1 cm | F95: Cucchiaio in ottone oro 22x4x1 cm | G95: Löffel aus Messing in Gold 22x4x1cm | H95: 7438246265236 | I95: BABRA010 | J95: Bazar Bizar | K95: Pineapple | L95: Voici notre première collection de couverts, jolie et brillante ! Ces fourchettes et cuillères sont un véritable luxe, fabriquées en laiton massif avec de magnifiques détails. Vos invités seront impressionnés par leur poids et leur qualité. Chaque pièce est décorée d’un ananas ou d’un palmier, impossible de faire plus tropical ! Disponibles en plusieurs tailles et modèles. | M95: È arrivata la nostra prima collezione di posate ed è splendida e brillante! Queste forchette e cucchiai sono puro lusso, realizzati in ottone massiccio con dettagli straordinari. I tuoi ospiti saranno colpiti dal peso e dalla qualità di questi must-have. Ogni pezzo è decorato con un’ananas o una palma, più tropicale di così non si può. Disponibili in varie misure e design. | N95: Nuestra primera colección de cubiertos ha llegado y es hermosa y brillante. Estos tenedores y cucharas son puro lujo, fabricados en latón macizo con detalles increíbles. Tus invitados quedarán impresionados por el peso y la calidad de estas piezas imprescindibles. Cada pieza está decorada con una piña o una palmera, no puede ser más tropical. Disponibles en varios tamaños y diseños. | O95: Unsere erste Besteckkollektion ist da, hübsch und glänzend! Diese Gabeln und Löffel sind purer Luxus, gefertigt aus massivem Messing mit wunderschönen Details. Ihre Gäste werden vom Gewicht und der Qualität dieser echten Messingstücke begeistert sein. Jedes Teil ist mit einer Ananas oder einer Palme verziert, tropischer geht es nicht. Erhältlich in verschiedenen Größen und Designs. | P95: Gold | Q95: Metal | Z95: 1 | AA95: cm | AB95: 22 | AC95: cm | AD95: 4 | AE95: cm | AG95: cm | AT95: Indonesia | BG95: https://bazarbizar.katanapim.com/content/images/thumbs/002/0028713_babra010g.jpeg | CA95: Bazar Bizar | CB95: 2550 | CD95: 22 x 4 x 1 cm | CG95: https://bazarbizar.katanapim.com/content/images/thumbs/000/0000654_the-pineapple-tea-spoon-gold.jpeg | DD95: Without pattern | FQ95: Artisanal
A96: Tableware and kitchen accessories/Dishes/Flatware/Tablespoon | B96: BABRA011G | C96: =_xlfn.XLOOKUP(B96,Sheet1!A:A,Sheet1!A:A,) -> BABRA011G | D96: Cuillère en laiton doré 22 x 4 x 1 cm | E96: Cuchara de latón en dorado 22x4x1 cm | F96: Cucchiaio in ottone oro 22x4x1 cm | G96: Löffel aus Messing in Goldoptik, 22 × 4 × 1 cm | H96: 7438246265229 | I96: BABRA011 | J96: Bazar Bizar | K96: Palm tree | L96: Notre première collection de couverts est là, et elle est belle et brillante ! Ces fourchettes et cuillères sont un pur luxe, réalisées en laiton massif avec des détails incroyables. Vos invités seront impressionnés par le poids et la qualité de ces couverts en laiton véritable. Toutes les pièces sont décorées d'un ananas ou d'un palmier, tellement tropical ! Disponibles en plusieurs tailles et modèles. | M96: La nostra prima collezione di posate è arrivata, ed è bella e lucente. Queste forchette e cucchiai sono puro lusso, realizzati in ottone massiccio con dettagli incredibili. I vostri ospiti saranno colpiti dal peso e dalla qualità di queste posate in vero ottone. Tutti i pezzi sono decorati con un ananas o una palma, così tropicale. Disponibile in varie dimensioni e design. | N96: Nuestra primera colección de cubiertos ya está aquí, y es bonita y brillante. Estos tenedores y cucharas son puro lujo, fabricados en latón macizo con detalles increíbles. Sus invitados quedarán impresionados por el peso y la calidad de estos cubiertos de latón auténtico. Todas las piezas están decoradas con una piña o una palmera, tan tropical. Disponibles en varios tamaños y diseños. | O96: Unsere erste Besteckkollektion ist da, und sie glänzt wunderschön. Diese Gabeln und Löffel sind purer Luxus, hergestellt aus massivem Messing mit erstaunlichen Details. Ihre Gäste werden vom Gewicht und der Qualität dieser echten Messing-Must-haves beeindruckt sein. Alle Stücke sind mit einer Ananas oder einer Palme verziert, tropischer geht es nicht. Erhältlich in verschiedenen Größen und Designs. | P96: Gold | Q96: Metal | Z96: 1 | AA96: cm | AB96: 22 | AC96: cm | AD96: 4 | AE96: cm | AG96: cm | AT96: Indonesia | BG96: https://bazarbizar.katanapim.com/content/images/thumbs/002/0028715_babra011g.jpeg | CA96: Bazar Bizar | CB96: 2550 | CD96: 22 x 4 x 1 cm | CG96: https://bazarbizar.katanapim.com/content/images/thumbs/002/0021944_the-palm-tree-spoon-gold.jpeg | CJ96: https://bazarbizar.katanapim.com/content/images/thumbs/002/0021409_the-palm-tree-spoon-gold.jpeg | CM96: https://bazarbizar.katanapim.com/content/images/thumbs/002/0021408_the-palm-tree-spoon-gold.jpeg | DD96: Without pattern | FQ96: Artisanal
A97: Tableware and kitchen accessories/Dishes/Flatware/Tablespoon | B97: BABRA013G | C97: =_xlfn.XLOOKUP(B97,Sheet1!A:A,Sheet1!A:A,) -> BABRA013G | D97: Cuillère à thé en laiton doré 14 x 3 x 1 cm | E97: Cucharilla de té de latón en dorado 14x3x1 cm | F97: Cucchiaino da tè in ottone oro 14x3x1 cm | G97: Teelöffel aus Messing in Goldoptik, 14 × 3 × 1 cm | H97: 7438246265250 | I97: BABRA013 | J97: Bazar Bizar | K97: Palm tree | L97: Notre première collection de couverts est arrivée et elle est belle et brillante. Ces fourchettes et cuillères sont du pur luxe, fabriquées en laiton massif avec des détails soignés. Vos invités seront impressionnés par le poids et la qualité de ces couverts en véritable laiton. Chaque pièce est ornée d'un ananas ou d'un palmier, difficile de faire plus tropical. Disponibles en plusieurs tailles et modèles. | M97: La nostra prima collezione di posate è arrivata ed è bella e brillante. Queste forchette e cucchiai sono puro lusso, realizzati in ottone massiccio con dettagli accurati. I vostri ospiti saranno colpiti dal peso e dalla qualità di queste posate in vero ottone. Tutti i pezzi sono decorati con un ananas o una palma, più tropicale di così non si può. Disponibile in varie dimensioni e design. | N97: Nuestra primera colección de cubiertos ya está aquí y es bonita y brillante. Estas cucharas y tenedores son puro lujo, fabricados en latón macizo con detalles cuidados. Sus invitados quedarán impresionados por el peso y la calidad de estos cubiertos de auténtico latón. Todas las piezas están decoradas con una piña o una palmera, no puede ser más tropical. Disponibles en varios tamaños y diseños. | O97: Unsere erste Besteckkollektion ist da und sie glänzt wunderschön. Diese Gabeln und Löffel sind purer Luxus, gefertigt aus massivem Messing mit feinen Details. Ihre Gäste werden vom Gewicht und der Qualität dieser echten Messing-Besteckstücke beeindruckt sein. Alle Stücke sind mit einer Ananas oder einer Palme verziert, tropischer geht es nicht. Erhältlich in verschiedenen Größen und Designs. | P97: Gold | Q97: Metal | Z97: 1 | AA97: cm | AB97: 14 | AC97: cm | AD97: 3 | AE97: cm | AG97: cm | AT97: Indonesia | BG97: https://bazarbizar.katanapim.com/content/images/thumbs/002/0028719_babra013g.jpeg | CA97: Bazar Bizar | CB97: 2550 | CD97: 14 x 3 x 1 cm | CG97: https://bazarbizar.katanapim.com/content/images/thumbs/002/0021836_the-burned-tapas-spoon.jpeg | CJ97: https://bazarbizar.katanapim.com/content/images/thumbs/002/0021360_the-burned-bowl-black-s.jpeg | CM97: https://bazarbizar.katanapim.com/content/images/thumbs/002/0021839_the-palm-tree-salad-spoon-gold.jpeg | DD97: Without pattern | FQ97: Artisanal
A98: Furniture/Living room furniture/Coffee tables | B98: BADE001B-110 | C98: =_xlfn.XLOOKUP(B98,Sheet1!A:A,Sheet1!A:A,) -> BADE001B-110 | G98: Couchtisch aus glänzendem schwarzem Kunstharz | H98: 7438246051075 | J98: Bazar Bizar | K98: High gloss | P98: Black | Q98: Resin | Z98: 35 | AA98: cm | AB98: 80 | AC98: cm
A99: Furniture/Living room furniture/Coffee tables | B99: BADE001W-110 | C99: =_xlfn.XLOOKUP(B99,Sheet1!A:A,Sheet1!A:A,) -> BADE001W-110 | G99: Couchtisch aus glänzendem weißem Kunstharz | H99: 7438246048068 | J99: Bazar Bizar | K99: HIGH GLOSS | P99: White | Q99: Resin | Z99: 35 | AA99: cm | AB99: 110 | AC99: cm
A100: Furniture/Living room furniture/Side tables | B100: BADE003B-70x40 | C100: =_xlfn.XLOOKUP(B100,Sheet1!A:A,Sheet1!A:A,) -> BADE003B-70x40 | H100: 7438246051037 | J100: Bazar Bizar | K100: High gloss | Z100: 40 | AA100: cm | AB100: 70 | AC100: cm
...

Sheet Error Details
A1: line-number | B1: provider-unique-identifier | C1: channels | D1: attribute-label | E1: attribute-codes | F1: error-code | G1: error-message
A2: 3 | B2: JABR098WN | D2: Product title | E2: attr_name | F2: MCM-05000 | G2: The 'attr_name' attribute is required.
A3: 3 | B3: JABR098WN | D3: Product title | E3: attr_name_es | F3: MCM-05000 | G3: The 'attr_name_es' attribute is required.
A4: 3 | B4: JABR098WN | D4: Product title | E4: attr_name_it | F4: MCM-05000 | G4: The 'attr_name_it' attribute is required.
A5: 3 | B5: JABR098WN | D5: Product title | E5: attr_name_de | F5: MCM-05000 | G5: The 'attr_name_de' attribute is required.
A6: 3 | B6: JABR098WN | D6: Description | E6: attr_description | F6: MCM-05000 | G6: The 'attr_description' attribute is required.
A7: 3 | B7: JABR098WN | D7: Description | E7: attr_description_it | F7: MCM-05000 | G7: The 'attr_description_it' attribute is required.
A8: 3 | B8: JABR098WN | D8: Description | E8: attr_description_es | F8: MCM-05000 | G8: The 'attr_description_es' attribute is required.
A9: 3 | B9: JABR098WN | D9: Description | E9: attr_description_de | F9: MCM-05000 | G9: The 'attr_description_de' attribute is required.
A10: 3 | B10: JABR098WN | D10: Color | E10: attr_color | F10: MCM-05000 | G10: The 'attr_color' attribute is required.
A11: 3 | B11: JABR098WN | D11: Main Material | E11: attr_material | F11: MCM-05000 | G11: The 'attr_material' attribute is required.
A12: 3 | B12: JABR098WN | D12: Media 2 | E12: attr_media_2 | F12: MCM-05000 | G12: The 'attr_media_2' attribute is required.
A13: 3 | B13: JABR098WN | C13: FR | F13: SLOW : Slowmover
A14: 4 | B14: JABR098BB | D14: Product title | E14: attr_name | F14: MCM-05000 | G14: The 'attr_name' attribute is required.
A15: 4 | B15: JABR098BB | D15: Product title | E15: attr_name_es | F15: MCM-05000 | G15: The 'attr_name_es' attribute is required.
A16: 4 | B16: JABR098BB | D16: Product title | E16: attr_name_it | F16: MCM-05000 | G16: The 'attr_name_it' attribute is required.
A17: 4 | B17: JABR098BB | D17: Product title | E17: attr_name_de | F17: MCM-05000 | G17: The 'attr_name_de' attribute is required.
A18: 4 | B18: JABR098BB | D18: Description | E18: attr_description | F18: MCM-05000 | G18: The 'attr_description' attribute is required.
A19: 4 | B19: JABR098BB | D19: Description | E19: attr_description_it | F19: MCM-05000 | G19: The 'attr_description_it' attribute is required.
A20: 4 | B20: JABR098BB | D20: Description | E20: attr_description_es | F20: MCM-05000 | G20: The 'attr_description_es' attribute is required.
A21: 4 | B21: JABR098BB | D21: Description | E21: attr_description_de | F21: MCM-05000 | G21: The 'attr_description_de' attribute is required.
A22: 4 | B22: JABR098BB | C22: FR | F22: SLOW : Slowmover
A23: 4 | B23: JABR098BB | C23: IT | F23: SLOW : Slowmover
A24: 7 | B24: BAFU006DW | D24: Description | E24: attr_description | F24: MCM-05012 | G24: The 'attr_description' attribute does not comply with script validation because: La description contient des balises html interdites.
A25: 7 | B25: BAFU006DW | D25: Description | E25: attr_description_it | F25: MCM-05012 | G25: The 'attr_description_it' attribute does not comply with script validation because: La descrizione contiene tag html vietati.
A26: 7 | B26: BAFU006DW | D26: Description | E26: attr_description_es | F26: MCM-05012 | G26: The 'attr_description_es' attribute does not comply with script validation because: La descripción contiene etiquetas html prohibidas.
A27: 7 | B27: BAFU006DW | D27: Description | E27: attr_description_de | F27: MCM-05012 | G27: The 'attr_description_de' attribute does not comply with script validation because: Die Beschreibung enthält verbotene html-Tags.
A28: 23 | B28: BAFU002DW | D28: Description | E28: attr_description | F28: MCM-05012 | G28: The 'attr_description' attribute does not comply with script validation because: La description contient des balises html interdites.
A29: 23 | B29: BAFU002DW | D29: Description | E29: attr_description_it | F29: MCM-05012 | G29: The 'attr_description_it' attribute does not comply with script validation because: La descrizione contiene tag html vietati.
A30: 23 | B30: BAFU002DW | D30: Description | E30: attr_description_es | F30: MCM-05012 | G30: The 'attr_description_es' attribute does not comply with script validation because: La descripción contiene etiquetas html prohibidas.
A31: 23 | B31: BAFU002DW | D31: Description | E31: attr_description_de | F31: MCM-05012 | G31: The 'attr_description_de' attribute does not comply with script validation because: Die Beschreibung enthält verbotene html-Tags.
A32: 25 | B32: BAPI010DW-XL | D32: Description | E32: attr_description | F32: MCM-05012 | G32: The 'attr_description' attribute does not comply with script validation because: La description contient des balises html interdites.
A33: 25 | B33: BAPI010DW-XL | D33: Description | E33: attr_description_es | F33: MCM-05012 | G33: The 'attr_description_es' attribute does not comply with script validation because: La descripción contiene etiquetas html prohibidas.
A34: 41 | B34: BAYU013N-L-80 | D34: Description | E34: attr_description | F34: MCM-05012 | G34: The 'attr_description' attribute does not comply with script validation because: La description contient des balises html interdites.
A35: 41 | B35: BAYU013N-L-80 | D35: Description | E35: attr_description_it | F35: MCM-05012 | G35: The 'attr_description_it' attribute does not comply with script validation because: La descrizione contiene tag html vietati.
... A52: 92 | B52: INME006B-L | D52: Description | E52: attr_description_de | F52: MCM-05012 | G52: The 'attr_description_de' attribute does not comply with script validation because: Die Beschreibung enthält verbotene html-Tags.
A53: 99 | B53: BAYU004N-S-22x50 | C53: ES | F53: OFF : Offer strategy
A54: 105 | B54: JACI008N | D54: Description | E54: attr_description | F54: MCM-05012 | G54: The 'attr_description' attribute does not comply with script validation because: La description contient des balises html interdites.
A55: 105 | B55: JACI008N | D55: Description | E55: attr_description_it | F55: MCM-05012 | G55: The 'attr_description_it' attribute does not comply with script validation because: La descrizione contiene tag html vietati.
A56: 105 | B56: JACI008N | D56: Description | E56: attr_description_es | F56: MCM-05012 | G56: The 'attr_description_es' attribute does not comply with script validation because: La descripción contiene etiquetas html prohibidas.
A57: 105 | B57: JACI008N | D57: Description | E57: attr_description_de | F57: MCM-05012 | G57: The 'attr_description_de' attribute does not comply with script validation because: Die Beschreibung enthält verbotene html-Tags.
A58: 105 | B58: JACI008N | C58: FR | F58: SLOW : Slowmover | G58: RETIRE LE 03/04/25
A59: 105 | B59: JACI008N | C59: IT | F59: SLOW : Slowmover
A60: 107 | B60: JAHU015N | D60: Description | E60: attr_description | F60: MCM-05012 | G60: The 'attr_description' attribute does not comply with script validation because: La description contient des balises html interdites.
A61: 107 | B61: JAHU015N | D61: Description | E61: attr_description_it | F61: MCM-05012 | G61: The 'attr_description_it' attribute does not comply with script validation because: La descrizione contiene tag html vietati.
A62: 107 | B62: JAHU015N | D62: Description | E62: attr_description_es | F62: MCM-05012 | G62: The 'attr_description_es' attribute does not comply with script validation because: La descripción contiene etiquetas html prohibidas.
A63: 107 | B63: JAHU015N | D63: Description | E63: attr_description_de | F63: MCM-05012 | G63: The 'attr_description_de' attribute does not comply with script validation because: Die Beschreibung enthält verbotene html-Tags.
A64: 108 | B64: JAHER001N-M | D64: Description | E64: attr_description | F64: MCM-05012 | G64: The 'attr_description' attribute does not comply with script validation because: La description contient des balises html interdites.
A65: 108 | B65: JAHER001N-M | D65: Description | E65: attr_description_it | F65: MCM-05012 | G65: The 'attr_description_it' attribute does not comply with script validation because: La descrizione contiene tag html vietati.
A66: 108 | B66: JAHER001N-M | D66: Description | E66: attr_description_es | F66: MCM-05012 | G66: The 'attr_description_es' attribute does not comply with script validation because: La descripción contiene etiquetas html prohibidas.
A67: 108 | B67: JAHER001N-M | D67: Description | E67: attr_description_de | F67: MCM-05012 | G67: The 'attr_description_de' attribute does not comply with script validation because: Die Beschreibung enthält verbotene html-Tags.
A68: 108 | B68: JAHER001N-M | C68: FR | F68: SLOW : Slowmover | G68: RETIRE LE 03/04/25
A69: 108 | B69: JAHER001N-M | C69: IT | F69: SLOW : Slowmover
A70: 109 | B70: CNWE002ConGr-M | D70: Description | E70: attr_description_es | F70: MCM-05012 | G70: The 'attr_description_es' attribute does not comply with script validation because: La descripción contiene etiquetas html prohibidas.
A71: 113 | B71: JACA011N-60x40 | D71: Description | E71: attr_description | F71: MCM-05012 | G71: The 'attr_description' attribute does not comply with script validation because: La description contient des balises html interdites.
